Workbook

Sheet Cronograma
B2: Revisitação Obrigações 2022 / 2023 / 2024
B3: Outubro
B4: Seg | C4: Ter | D4: Qua | E4: Qui | F4: Sex
B5: 13 | C5: 14 | D5: 15 | E5: 16 | F5: 17
B6: Juliana Cabral (1) 14:30 - 15:00 | C6: Fernando Rodrigues (2) 09:00 - 10:00 | D6: Walcy Borges (1) 11:30 - 12:00 | E6: Luciana Santos (13) 11:00 - 12:00 | F6: Leonardo Medina (1) 15:00 - 15:30
B7: Larissa Valois (2) 15:00 - 15:30 | C7: Walcy Borges (1) 14:00 - 14:30 | D7: ** | E7: ** | F7: **
B8: ** | C8: Leonardo Medina (1) 15:00 - 15:30 | D8: ** | E8: ** | F8: **
B9: Seg | C9: Ter | D9: Qua | E9: Qui | F9: Sex
B10: 20 | C10: 21 | D10: 22 | E10: 23 | F10: 24
B11: ** | C11: ** | D11: Luciana Santos (13) 09:00 - 10:00 | E11: ** | F11: **
B14: Revisitação Obrigações 2025
B15: Outubro
B16: Seg | C16: Ter | D16: Qua | E16: Qui | F16: Sex
B17: 6 | C17: 7 | D17: 8 | E17: 9 | F17: 10
B18: Fabio Mota 15:00 - 16:00 | C18: ** | D18: ** | E18: Fabio Mota 14:00 - 15:00 | F18: **
B19: Seg | C19: Ter | D19: Qua | E19: Qui | F19: Sex
B20: 13 | C20: 14 | D20: 15 | E20: 16 | F20: 17
B21: ** | C21: ** | D21: Fabio Mota 13:30 - 15:00 | E21: Fabio Mota 13:30 - 15:00 | F21: **
B22: Seg | C22: Ter | D22: Qua | E22: Qui | F22: Sex
B23: 20 | C23: 21 | D23: 22 | E23: 23 | F23: 24
B24: ** | C24: Fernando Rodrigues 15:00 - 16:00 | D24: ** | E24: Fabio Mota 15:00 - 16:30 | F24: Fernando Rodrigues 14:30 - 15:30
B25: Seg | C25: Ter | D25: Qua | E25: Qui | F25: Sex
B26: 27 | C26: 28 | D26: 29 | E26: 30 | F26: 31
B27: Fernando Rodrigues 14:00 - 15:30 | C27: Luciana Santos 14:00 - 15:00 | D27: Fabio Mota 14:00 - 15:00 | E27: Fabio Mota 14:00 - 15:00 | F27: **
B28: Novembro
B29: Seg | C29: Ter | D29: Qua | E29: Qui | F29: Sex
B30: 3 | C30: 4 | D30: 5 | E30: 6 | F30: 7
B31: Fernando Rodrigues 14:00 - 15:00 | C31: Fabio Mota 09:00 - 10:00 | D31: ** | E31: ** | F31: **
B32: ** | C32: Fernando Rodrigues 14:00 - 15:00 | D32: ** | E32: ** | F32: **
B33: Seg | C33: Ter | D33: Qua | E33: Qui | F33: Sex
B34: 10 | C34: 11 | D34: 12 | E34: 13 | F34: 14
B35: Marcelo Ribeiro 14:00 - 15:00 | C35: Fernando Rodrigues 14:00 - 15:00 | D35: ** | E35: ** | F35: Fabio Mota 14:00 - 15:30
B36: Seg | C36: Ter | D36: Qua | E36: Qui | F36: Sex
B37: 17 | C37: 18 | D37: 19 | E37: 20 | F37: 21
B38: Análise das respostas das obrigações anteriores a 2025 09:00 - 11:30 | C38: ** | D38: Análise Crítica SEG | E38: Feriado | F38: **
B39: Seg | C39: Ter | D39: Qua | E39: Qui | F39: Sex
B40: 24 | C40: 25 | D40: 26 | E40: 27 | F40: 28
B41: Fabio Mota 15:00 - 16:00 | C41: Análise das respostas das obrigações anteriores a 2025 09:00 - 10:30 | D41: Fabio Mota 09:00 - 10:00 | E41: ** | F41: Fabio Mota 14:00 - 15:00
B42: Dezembro
B43: Seg | C43: Ter | D43: Qua | E43: Qui | F43: Sex
B44: 1 | C44: 2 | D44: 3 | E44: 4 | F44: 5
B45: Fabio Mota 09:30 - 10:30 | C45: Fabio Mota 09:30 - 10:30 | D45: ** | E45: Análise das respostas das obrigações Processo Gerir PGR 09:00 - 10:30 | F45: **
B46: ** | C46: ** | D46: ** | E46: Juliana Cabral 14:00 - 15:30 | F46: **
B47: Seg | C47: Ter | D47: Qua | E47: Qui | F47: Sex
B48: 8 | C48: 9 | D48: 10 | E48: 11 | F48: 12
B49: ** | C49: Fabio Mota 09:30 - 11:00 | D49: ** | E49: ** | F49: **
B50: ** | C50: Juliana Cabral 15:00 - 16:00 | D50: ** | E50: ** | F50: Leonardo Medina 14:00 - 15:30
B51: Seg | C51: Ter | D51: Qua | E51: Qui | F51: Sex
B52: 15 | C52: 16 | D52: 17 | E52: 18 | F52: 19
B53: Leonardo Medina 09:30 - 11:00 | C53: ** | D53: ** | E53: Felipe Sampaio 09:00 - 10:30 | F53: **
B54: Juliana Cabral 15:00 - 16:00 | C54: ** | D54: ** | E54: Juliana Cabral 14:00 - 15:00 | F54: Juliana Cabral 14:00 - 15:00
B55: Seg | C55: Ter | D55: Qua | E55: Qui | F55: Sex
B56: 22 | C56: 23 | D56: 24 | E56: 25 | F56: 26
B57: ** | C57: Felipe Sampaio 14:00 - 15:00 | D57: ** | E57: ** | F57: **
B58: ** | C58: Juliana Cabral 15:00 - 16:00 | D58: ** | E58: ** | F58: **
B59: 29 | C59: 30 | D59: 31 | E59: 1 | F59: 2
B60: Felipe Sampaio 10:00 - 11:00 | C60: ** | D60: ** | E60: ** | F60: **
B61: Juliana Cabral 14:00 - 15:00 | C61: ** | D61: ** | E61: ** | F61: **
B62: Janeiro.2026
B63: Seg | C63: Ter | D63: Qua | E63: Qui | F63: Sex
B64: 5 | C64: 6 | D64: 7 | E64: 8 | F64: 9
B65: Larissa Valois 15:00 - 16:00 | C65: ** | D65: Francisco Batalha 14:00 - 15:00 | E65: Larissa Valois 10:00 - 11:00 | F65: Francisco Batalha 14:00 - 15:00
B66: 12 | C66: 13 | D66: 14 | E66: 15 | F66: 16
B67: Juliana Cabral 10:00 - 11:00 | C67: ** | D67: ** | E67: ** | F67: **
B68: Fernando Rodrigues 14:00 - 15:00 | C68: Larissa Valois 14:00 - 15:00 | D68: Fernando Rodrigues 14:00 - 15:00 | E68: Larissa Valois 14:00 - 15:00 | F68: Fernando Rodrigues 10:00 - 11:00
B69: 19 | C69: 20 | D69: 21 | E69: 22 | F69: 23
B70: Fernando Rodrigues 14:00 - 15:00 | C70: ** | D70: ** | E70: ** | F70: **
B71: Fevereiro.2026
B72: Seg | C72: Ter | D72: Qua | E72: Qui | F72: Sex
B73: 2 | C73: 3 | D73: 4 | E73: 5 | F73: 6
B74: Felipe Sampaio 14:00 - 15:00 | C74: ** | D74: Felipe Sampaio 14:00 - 15:00 | E74: ** | F74: Felipe Sampaio 14:00 - 15:00
B75: Seg | C75: Ter | D75: Qua | E75: Qui | F75: Sex
B76: 9 | C76: 10 | D76: 11 | E76: 12 | F76: 13
B77: ** | C77: ** | D77: Felipe Sampaio 10:00 - 11:30 | E77: ** | F77: **

Sheet Resumo
B2: ATIVO I
B4: Contagem de Situação - ATIVO I | C4: Rótulos de Coluna
B5: Rótulos de Linha | C5: Devolver | D5: Não Respondida | E5: Respondida | F5: Transferir | G5: Abrir RTA | H5: Total Geral
B6: Arnaldo Carvalho - ZMIG | D6: 1 | H6: 1
B7: Bruno Lopes-PL2F | E7: 4 | H7: 4
B8: Em análise | F8: 31 | H8: 31
B9: FABIO MOTA DXV9 | C9: 21 | D9: 1 | E9: 134 | H9: 156
B10: Felipe Sampaio- ZP4I | D10: 9 | E10: 24 | F10: 1 | G10: 3 | H10: 37
B11: Fernando Rodrigues- CMQ6 | C11: 1 | D11: 4 | E11: 76 | F11: 44 | H11: 125
B12: Francisco Batalha- URFV | E12: 8 | H12: 8
B13: Juliana Cabral-CYT6 | D13: 3 | E13: 10 | F13: 1 | H13: 14
B14: Larissa Valois-FIUX | D14: 2 | E14: 31 | F14: 10 | H14: 43
B15: LEONARDO MEDINA - CSQE | E15: 40 | H15: 40
B16: Luciana Santos-URFU | D16: 1 | E16: 24 | H16: 25
B17: Marcelo Ribeiro - URWD | E17: 6 | H17: 6
B18: Walcy Borges- SESM | D18: 38 | E18: 22 | F18: 3 | H18: 63
B19: Walter Motta- F49B | E19: 7 | H19: 7
B20: Alex Angeli - FLVR | D20: 52 | H20: 52
B21: Juliana Cabral-CYT6 Luciano Dumiense-F5WZ | E21: 1 | H21: 1
B22: Total Geral | C22: 22 | D22: 111 | E22: 387 | F22: 90 | G22: 3 | H22: 613

Sheet Resumo 2 - RAC
B2: ATIVO I
B4: Contagem de Situação - ATIVO I | C4: Rótulos de Coluna
B5: Rótulos de Linha | C5: Não Respondida | D5: Respondida | E5: Total Geral
B6: Abrangência | C6: 1 | E6: 1
B7: Gerir Anomalias de SMS | C7: 3 | D7: 11 | E7: 14
B8: Gerir Ergonomia | C8: 9 | D8: 24 | E8: 33
B9: Gerir Higiene Ocupacional | D9: 49 | E9: 49
B10: Gerir M&I de Equipamentos de Segurança | C10: 1 | D10: 32 | E10: 33
B11: Gerir PGR | C11: 3 | D11: 133 | E11: 136
B12: Gerir Prontidão, Emergência e Contingência | C12: 37 | D12: 22 | E12: 59
B13: Gerir Requisitos Legais - CIPLAT | C13: 51 | E13: 51
B14: Gerir Requisitos Legais - NR-35 e NR-37 | C14: 6 | D14: 77 | E14: 83
B15: Gerir Requisitos Legais - Seg. Química | C15: 2 | D15: 31 | E15: 33
B16: Gerir Requisitos Legais - NR-34 | D16: 7 | E16: 7
B17: Total Geral | C17: 113 | D17: 386 | E17: 499
B19: Rótulos de Linha | C19: Não Revisitada | D19: Revisitada
B20: Abrangência | C20: 1 | E20: 1
B21: Gerir Anomalias de SMS | C21: 3 | D21: 11 | E21: 14
B22: Gerir Ergonomia | C22: 9 | D22: 24 | E22: 33
B23: Gerir Higiene Ocupacional | D23: 49 | E23: 49
B24: Gerir M&I de Equipamentos de Segurança | C24: 1 | D24: 32 | E24: 33
B25: Gerir PGR | C25: 3 | D25: 133 | E25: 136
B26: Gerir Prontidão, Emergência e Contingência | C26: 37 | D26: 22 | E26: 59
B27: Gerir Requisitos Legais - CIPLAT | C27: 51 | E27: 51
B28: Gerir Requisitos Legais - NR-35 e NR-37 | C28: 6 | D28: 77 | E28: 83
B29: Gerir Requisitos Legais - Seg. Química | C29: 2 | D29: 31 | E29: 33
B30: Gerir Requisitos Legais - NR-34 | D30: 7 | E30: 7
B31: Total Geral | C31: 113 | D31: 386 | E31: 499
B35: Rótulos de Linha | C35: Contagem de Situação - ATIVO I
B36: Devolver | C36: 22
B37: Não Respondida | C37: 113
B38: Respondida | C38: 387
B39: Transferir | C39: 90
B40: Abrir RTA | C40: 3
B41: Total Geral | C41: 615
B42: Não Revisitada | C42: 113
B43: Revisitada | C43: 387
B44: Análise de Responsabilidade | C44: 112
B45: Abrir RTA | C45: 3
B59: Rótulos de Linha | C59: Contagem de Situação - ATIVO I | D59: Contagem de Processo SEG
B60: Não Respondida | C60: 303 | D60: 303
B61: Abrangência | C61: 1 | D61: 1
B62: Gerir Anomalias de SMS | C62: 3 | D62: 3
B63: Gerir Ergonomia | C63: 21 | D63: 21
B64: Gerir Higiene Ocupacional | C64: 49 | D64: 49
B65: Gerir M&I de Equipamentos de Segurança | C65: 9 | D65: 9
B66: Gerir PGR | C66: 4 | D66: 4
B67: Gerir Prontidão, Emergência e Contingência | C67: 59 | D67: 59
B68: Gerir Requisitos Legais - CIPLAT | C68: 51 | D68: 51
B69: Gerir Requisitos Legais - NR-35 e NR-37 | C69: 65 | D69: 65
B70: Gerir Requisitos Legais - Seg. Química | C70: 41 | D70: 41
B71: Total Geral | C71: 303 | D71: 303
B74: Abrangência | C74: 1
B75: Gerir Anomalias de SMS | C75: 3
B76: Gerir Ergonomia | C76: 21
B77: Gerir Higiene Ocupacional | C77: 49
B78: Gerir M&I de Equipamentos de Segurança | C78: 9
B79: Gerir PGR | C79: 4
B80: Gerir Prontidão, Emergência e Contingência | C80: 59
B81: Gerir Requisitos Legais - CIPLAT | C81: 51
B82: Gerir Requisitos Legais - NR-35 e NR-37 | C82: 65
B83: Gerir Requisitos Legais - Seg. Química | C83: 41

Sheet Evidências
B2: Obrigação - 83749 - Fabio Mota
B4: ISA PBR-2025-0016584 - https://petrobrasbr.sharepoint.com/:f:/r/teams/bdoc_20240301023456/Documentos%20Compartilhados/2%20-%20Interna/06%20-%20Requisitos%20Legais%20de%20SMS/Gest%C3%A3o%20VCL/Evid%C3%AAncia%20de%20Obriga%C3%A7%C3%B5es%20VCL/Ciclo%20de%20Revisita%C3%A7%C3%A3o%202025-2026/Obriga%C3%A7%C3%A3o%20-%2083749%20-%20Fabio%20Mota?csf=1&web=1&e=XDMbiP
B43: Obrigação - 80273 - Fernando Rodrigues
C45: Sertec - CT-ENGP-EN-009-2024 rev.0 - https://petrobrasbr.sharepoint.com/:b:/r/teams/bdoc_20240301023456/Documentos%20Compartilhados/2%20-%20Interna/06%20-%20Requisitos%20Legais%20de%20SMS/Gest%C3%A3o%20VCL/Evid%C3%AAncia%20de%20Obriga%C3%A7%C3%B5es%20VCL/Ciclo%20de%20Revisita%C3%A7%C3%A3o%202025-2026/Obriga%C3%A7%C3%A3o%20-%2080273%20-%20Fernando%20Rodrigues/CT-ENGP-EN-009-2024_rev.0_assinado%20(1).pdf?csf=1&web=1&e=45exQ4
B146: Obrigação - 52495 - Fabio Mota
B186: Obrigação - 83806 - Fabio Mota
B188: Obrigação - 83806 - Fabio Mota
B190: OBS: Deverá ser emitido novo ISA para RT da NR-33 e resposta ser atualizada
B231: Obrigação - 107137 / 107154 /106842/ 53076/ 107056- Larissa Valois-FIUX
B258: Obrigações 80207 E 80223 - Fernando
B310: Obrigação 80556 - Fernando

Sheet CICLO 2025-2026
B1: Código Obrigação | C1: Validado? | D1: Obrigação | E1: Requisito de SMS | F1: Ementa | G1: Artigo/Item | H1: Assunto | I1: Situação Obrigação | J1: Resposta Anterior | K1: Resposta Ciclo 2025/2026 - ATIVO I | L1: Link Evidência - ATIVO I | M1: Resposta Ciclo 2025/2026 - ATIVO II | N1: Link Evidência - ATIVO II | O1: Processo SEG | P1: Situação - ATIVO I | Q1: Situação - ATIVO II | R1: Responsável pela Resposta no Ciclo | S1: Data Atualização Anterior | T1: Data da Última Atualização | U1: Observação | V1: Análise resposta | W1: Ok? | X1: Observações - Fernanda | Y1: Observações - Sandra | Z1: Observações - Pri
B2: 92673 | D2: A partir da implantação em meio digital do PPP ou de documento que venha a substituí-lo, esse formulário é preenchido para todos os segurados empregados, avulsos e cooperados vinculados a cooperativas de trabalho ou de produção, independentemente do ramo de atividade da empresa, da exposição a agentes prejudiciais à saúde? | E2: INSTRUÇÃO NORMATIVA PRES/INSS Nº 128, DE 28 DE MARÇO DE 2022 | F2: Disciplina as regras, procedimentos e rotinas necessárias à efetiva aplicação das normas de direito previdenciário. | G2: Art. 284, § 1º | H2: RISCOS - Promover a redução e prevenção dos riscos no ambiente do trabalho | I2: Conforme | J2: A emissão via eSocial tem seus dados ambientais extraídos do SIS - Sistema Informatizado de Saúde, para preenchimento automatizado do PPP Digital, e tem seu fluxo descrito no Anexo D.2, do padrão PP-1PBR-00438, gerido pelo SMS/ECES/HOE Walter Motta- F49B | K2: Sim. Conforme previsto no Anexo D, do padrão PP-1PBR-00438- GERIR HIGIENE OCUPACIONAL | L2: PP-1PBR-00438: https://sinpep.petrobras.com.br/SINPEP_Padrao_Web/PadraoEditar?PadraoId=1432# | M2: Sim. Conforme previsto no Anexo D, do padrão PP-1PBR-00438 | N2: PP-1PBR-00438: https://sinpep.petrobras.com.br/SINPEP_Padrao_Web/PadraoEditar?PadraoId=1432# | O2: Gerir Higiene Ocupacional | P2: Respondida | Q2: Respondida | R2: Walter Motta- F49B | S2: 10/4/2025 | T2: 46003 | V2: Analisado | W2: FALSE | Y2: =VLOOKUP($B2,'Rascunho - PRI'!B1:X603,23,FALSE) -> 0 | Z2: Sim. A partir da implantação do PPP em meio digital, o formulário passa a ser preenchido para todos os segurados — empregados, avulsos e cooperados de cooperativas de trabalho ou de produção — independentemente: do ramo de atividade da empresa; e da existência ou não de exposição a agentes prejudiciais à saúde. Conforme previsto no Anexo D do padrão PP‑1PBR‑00438.
B3: 82309 | D3: A empresa elabora e mantém atualizado o PPP para os seus funcionários, bem como fornece o mesmo nas situações elencadas abaixo: I - por ocasião da rescisão do contrato de trabalho ou da desfiliação da cooperativa, sindicato ou órgão gestor de mão de obra, com fornecimento de uma das vias para o trabalhador, mediante recibo; II - sempre que solicitado pelo trabalhador, para fins de requerimento de reconhecimento de períodos laborados em condições especiais; III - para fins de análise de benefícios e serviços previdenciários e quando solicitado pelo INSS; IV - para simples conferência por parte do trabalhador, quando da revisão do Programa de Gerenciamento de Riscos - PGR; e V - quando solicitado pelas autoridades competentes? | E3: INSTRUÇÃO NORMATIVA PRES/INSS Nº 128, DE 28 DE MARÇO DE 2022 | F3: Disciplina as regras, procedimentos e rotinas necessárias à efetiva aplicação das normas de direito previdenciário. | G3: Art. 284, § 5º | H3: RISCOS - Promover a redução e prevenção dos riscos no ambiente do trabalho | I3: Conforme | J3: "O fluxo para emissão (I), solicitação (II, III, IV e V) é atendido, conforme descrito nos itens 3.2 e 3.3, alineas ""a"" e ""b"" do Padrão PE-1PBR-00852, gerido pelo RH/RBO/PB. O processo para solicitação e emissão é descrito no item 3.13 do padrão PE-1PBR-01151, e auditado pelo Serviços de Relações de Trabalho, do Centro de Operações de RH e Atendimento" Walter Motta Junior- F49B | K3: Sim. O fluxo para emissão (I), solicitação (II, III, IV e V) é atendido, conforme descrito nos itens 3.2 e 3.3, alineas ""a"" e ""b"" do Padrão PE-1PBR-00852- EMITIR PERFIL PROFISSIOGRÁFICO PREVIDENCIÁRIO (PPP), gerido pelo RH/RBO/PB. O processo para solicitação e emissão é descrito no item 3.13 do padrão PE-1PBR-01151-GERIR PERFIL PROFISSIOGRÁFICO PREVIDENCIÁRIO - PPP, e auditado pelo Serviços de Relações de Trabalho, do Centro de Operações de RH e Atendimento | L3: PE-1PBR-00852: https://sinpep.petrobras.com.br/SINPEP_Padrao_Web/PadraoEditar?TipoBusca=ONLINE&PadraoId=2601 PE-1PBR-01151: https://sinpep.petrobras.com.br/SINPEP_Padrao_Web/PadraoEditar?PadraoId=1530 | M3: Sim. O fluxo para emissão (I), solicitação (II, III, IV e V) é atendido, conforme descrito nos itens 3.2 e 3.3, alineas ""a"" e ""b"" do Padrão PE-1PBR-00852, gerido pelo RH/RBO/PB. O processo para solicitação e emissão é descrito no item 3.13 do padrão PE-1PBR-01151, e auditado pelo Serviços de Relações de Trabalho, do Centro de Operações de RH e Atendimento | N3: PE-1PBR-00852: https://sinpep.petrobras.com.br/SINPEP_Padrao_Web/PadraoEditar?TipoBusca=ONLINE&PadraoId=2601 PE-1PBR-01151: https://sinpep.petrobras.com.br/SINPEP_Padrao_Web/PadraoEditar?PadraoId=1530 | O3: Gerir Higiene Ocupacional | P3: Respondida | Q3: Respondida | R3: Walter Motta- F49B | S3: 10/4/2025 | T3: 46003 | V3: Analisado | W3: TRUE | Y3: =VLOOKUP($B3,'Rascunho - PRI'!B2:X604,23,FALSE) -> 0 | Z3: ok.
B4: 82381 | D4: A empresa, quando da emissão do LTCAT, observa os elementos informativos exigidos por esta Instrução Normativa? NOTA: Art 276, I - se individual ou coletivo; II - identificação da empresa; III - identificação do setor e da função; IV - descrição da atividade; V - identificação do agente prejudicial à saúde, arrolado na Legislação Previdenciária; VI - localização das possíveis fontes geradoras; VII - via e periodicidade de exposição ao agente prejudicial à saúde; VIII - metodologia e procedimentos de avaliação do agente prejudicial à saúde; IX - descrição das medidas de controle existentes; X - conclusão do LTCAT; XI - assinatura e identificação do médico do trabalho ou engenheiro de segurança do trabalho; e XII - data da realização da avaliação ambiental. IX - descrição das medidas de controle existentes; X - conclusão do LTCAT; XI - assinatura e identificação do médico do trabalho ou engenheiro de segurança do trabalho; e XII - data da realização da avaliação ambiental. | E4: INSTRUÇÃO NORMATIVA PRES/INSS Nº 128, DE 28 DE MARÇO DE 2022 | F4: Disciplina as regras, procedimentos e rotinas necessárias à efetiva aplicação das normas de direito previdenciário. | G4: Art. 276 | H4: RISCOS - Promover a redução e prevenção dos riscos no ambiente do trabalho | I4: Conforme | J4: Os LTCAT são elaborados e emitidos, observando os itens de I a XI, por Demanda Judicial, Exigência do INSS ou Solicitação a Ouvidoria._x000D_ Evidenciando durante a VCL o atendimento a obrigação legal. | K4: Sim. Os LTCAT são elaborados e emitidos, observando os itens de I a XI, por Demanda Judicial, Exigência do INSS ou Solicitação a Ouvidoria, confrome determinado no Manual anexo ao Padrão PE-1PBR-001151- GERIR PERFIL PROFISSIOGRÁFICO PREVIDENCIÁRIO - PPP. | L4: Padrão PE-1PBR-001151: https://sinpep.petrobras.com.br/SINPEP_Padrao_Web/PadraoEditar?TipoBusca=ONLINE&PadraoId=1530 | M4: Sim. Os LTCAT são elaborados e emitidos, observando os itens de I a XI, por Demanda Judicial, Exigência do INSS ou Solicitação a Ouvidoria, confrome determinado no Manual anexo ao Padrão PE-1PBR-001151. | N4: Padrão PE-1PBR-001151: https://sinpep.petrobras.com.br/SINPEP_Padrao_Web/PadraoEditar?TipoBusca=ONLINE&PadraoId=1530 | O4: Gerir Higiene Ocupacional | P4: Respondida | Q4: Respondida | R4: Walter Motta- F49B | S4: 27/1/2025 | T4: 46003 | V4: Analisado | W4: TRUE | Y4: =VLOOKUP($B4,'Rascunho - PRI'!B3:X605,23,FALSE) -> 0 | Z4: ok
B5: 53116 | D5: A comprovação da efetiva exposição dos empregados da empresa aos agentes nocivos faz-se mediante emissão do formulário denominado perfil profissiográfico previdenciário, na forma estabelecida pelo Instituto Nacional do Seguro Social, com base em laudo técnico de condições ambientais do trabalho expedido por médico do trabalho ou engenheiro de segurança do trabalho? | E5: DECRETO Nº 3.048, DE 06 DE MAIO DE 1999 | F5: Aprova o Regulamento da Previdência Social, e dá outras providências. | G5: Art. 68, § 2º | H5: RISCOS - Promover a redução e prevenção dos riscos no ambiente do trabalho | I5: Conforme | J5: "A emissão de PPP é realizada com base na profissiografia informada pelo RH, bem como os dados ambientais das Campanhas de PPRA. _x000D_ A elaboração de LTCAT é feita somente para as seguintes situações: Demanda Judicial, Exigência do INSS ou Solicitação pela Ouvidoria, conforme determinado no Padrão PE-1PBR-01151 - GERIR PERFIL PROFISSIOGRÁFICO PREVIDENCIÁRIO - PPP e seu Anexo ""D""." | K5: Sim. A comprovação da efetiva exposição a agentes nocivos é feita conforme determinado no Padrão PE-1PBR-01151 - GERIR PERFIL PROFISSIOGRÁFICO PREVIDENCIÁRIO - PPP e seu Manual (Anexo) | L5: PE-1PBR-001151: https://sinpep.petrobras.com.br/SINPEP_Padrao_Web/PadraoEditar?TipoBusca=ONLINE&PadraoId=1530 | M5: Sim. A comprovação da efetiva exposição a agentes nocivos é feita conforme determinado no Padrão PE-1PBR-01151 - GERIR PERFIL PROFISSIOGRÁFICO PREVIDENCIÁRIO - PPP e seu Manual (Anexo) | N5: PE-1PBR-001151: https://sinpep.petrobras.com.br/SINPEP_Padrao_Web/PadraoEditar?TipoBusca=ONLINE&PadraoId=1530 | O5: Gerir Higiene Ocupacional | P5: Respondida | Q5: Respondida | R5: Walter Motta- F49B | S5: 18/3/2025 | T5: 46003 | V5: Analisado | W5: TRUE | Y5: =VLOOKUP($B5,'Rascunho - PRI'!B4:X606,23,FALSE) -> 0 | Z5: ok
B6: 82382 | D6: A empresa, a partir de 01/01/2004, realiza o preenchimento do formulário PPP de forma individualizada para seus empregados, trabalhadores avulsos e contribuintes individuais cooperados, que trabalhem expostos a agentes prejudiciais à saúde, ainda que não presentes os requisitos para fins de enquadramento de atividade especial, seja pela eficácia dos equipamentos de proteção, coletivos ou individuais, seja por não se caracterizar a permanência? NOTA: A partir da implantação em meio digital do PPP ou de documento que venha a substituí-lo, esse formulário deverá ser preenchido para todos os segurados empregados, avulsos e cooperados vinculados a cooperativas de trabalho ou de produção, independentemente do ramo de atividade da empresa, da exposição a agentes prejudiciais à saúde. | E6: INSTRUÇÃO NORMATIVA PRES/INSS Nº 128, DE 28 DE MARÇO DE 2022 | F6: Disciplina as regras, procedimentos e rotinas necessárias à efetiva aplicação das normas de direito previdenciário. | G6: Art. 284 | H6: RISCOS - Promover a redução e prevenção dos riscos no ambiente do trabalho | I6: Conforme | J6: A Emissão do PPP é realizada individualizadamente, conforme descrito no item 3.13 do padrão PE-1PBR-01151 e atende em seu conteúdo pautado no descrito no item 3.19, do Anexo B - Guia Técnico de Higiene Ocupacional Petrobras, do PP-1PBR-00438 Walter Motta-F49B | K6: Sim. O preenchimento do PPP é feito conforme determinado no Padrão PE-1PBR-01151 - GERIR PERFIL PROFISSIOGRÁFICO PREVIDENCIÁRIO - PPP e seu Manual (Anexo) | L6: PE-1PBR-001151: https://sinpep.petrobras.com.br/SINPEP_Padrao_Web/PadraoEditar?TipoBusca=ONLINE&PadraoId=1530 | M6: Sim. O preenchimento do PPP é feito conforme determinado no Padrão PE-1PBR-01151 - GERIR PERFIL PROFISSIOGRÁFICO PREVIDENCIÁRIO - PPP e seu Manual (Anexo) | N6: PE-1PBR-001151: https://sinpep.petrobras.com.br/SINPEP_Padrao_Web/PadraoEditar?TipoBusca=ONLINE&PadraoId=1530 | O6: Gerir Higiene Ocupacional | P6: Respondida | Q6: Respondida | R6: Walter Motta- F49B | S6: 10/4/2025 | T6: 46003 | V6: Analisado | W6: FALSE | Y6: =VLOOKUP($B6,'Rascunho - PRI'!B5:X607,23,FALSE) -> 0 | Z6: =VLOOKUP($B6,'Rascunho - PRI'!B5:X607,23,FALSE) -> 0
B7: 60217 | D7: A empresa realiza o correto preenchimento do Perfil Profissiográfico Previdenciário - PPP? NOTA 01: A partir do início da obrigatoriedade dos eventos de Segurança e Saúde no Trabalho (SST) no Sistema Simplificado de Escrituração Digital das Obrigações Previdenciárias, Trabalhistas e Fiscais - eSocial, o PPP será emitido exclusivamente em meio eletrônico para os segurados das empresas obrigadas. NOTA 02: O registro da profissiografia relacionada a período anterior deverá ser feito conforme procedimento adotado à época, em meio físico. | E7: PORTARIA MTP Nº 313, DE 22 DE SETEMBRO DE 2021 | F7: Dispõe sobre a implantação do Perfil Profissiográfico Previdenciário (PPP) em meio eletrônico, de que tratam os §§ 3º e 8º do art. 68 do Regulamento da Previdência Social, aprovado pelo Decreto nº 3.048, de 6 de maio de 1999, com redação dada pelo Decreto nº 10.410, de 30 de junho de 2020. | G7: Art. 2º | H7: RISCOS - Promover a redução e prevenção dos riscos no ambiente do trabalho | I7: Conforme | J7: "A emissão via eSocial tem seus dados ambientais extraídos do SIS - Sistema Informatizado de Saúde, para preenchimento automatizado do PPP Digital, e tem seu fluxo descrito no Anexo D.2, do padrão PP-1PBR-00438, gerido pelo SMS/ECES/HOE". _x000D_ Poderia ser adicionado "O registro da profissiografia relacionada ao período anterior segue o disposto no item 7.4, Anexo D - Orientações Corporativas para Preenchimento dos Registros Ambientais do Perfil Profissiográfico Previdenciário ¿ PPP ¿ Itens de SMS"_x000D_ Walter Motta- F49B | K7: Sim. Notas 01 e 02 tem seu fluxo descrito no Anexo D, do padrão PP-1PBR-00438 | L7: PP-1PBR-00438: https://sinpep.petrobras.com.br/SINPEP_Padrao_Web/PadraoEditar?PadraoId=1432# | M7: Sim. Notas 01 e 02 tem seu fluxo descrito no Anexo D, do padrão PP-1PBR-00438 | N7: PP-1PBR-00438: https://sinpep.petrobras.com.br/SINPEP_Padrao_Web/PadraoEditar?PadraoId=1432# | O7: Gerir Higiene Ocupacional | P7: Respondida | Q7: Respondida | R7: Walter Motta- F49B | S7: 9/5/2025 | T7: 46003 | W7: FALSE | Y7: =VLOOKUP($B7,'Rascunho - PRI'!B6:X608,23,FALSE) -> 0 | Z7: =VLOOKUP($B7,'Rascunho - PRI'!B6:X608,23,FALSE) -> 0
B8: 51479 | D8: Os exercícios simulados de emergência são programados periodicamente de forma a contemplar os cenários previstos no Plano de Resposta a Emergência de acordo com os riscos envolvidos e a complexidade do Sistema Submarino; Coordenados com as partes envolvidas e autoridades competentes; Avaliados de forma a identificar as irregularidades e oportunidades de melhoria? | E8: RESOLUÇÃO ANP Nº 41, DE 09 DE OUTUBRO DE 2015 | F8: Aprova o Regulamento Técnico do Sistema de Gerenciamento de Segurança Operacional de Sistemas Submarinos - SGSS. | G8: Anexo Item 18.5.1 | H8: SEGURANÇA OPERACIONAL - Sistemas Submarinos | I8: Conforme | J8: PE-2SMS-00074 GERIR TREINAMENTOS DE CONTINGÊNCIA E SIMULADOS NO E&P UN-BUZ SMS SEG - Documentos\2 - Interna\04 - Contingência, Prontidão e Resposta\01. Simulados\01 - Simulado N1 Sistema: Portal de Gestão / BDoc Sandra Nery- LNGH | O8: Gerir Prontidão, Emergência e Contingência | P8: Não Respondida | Q8: Não Respondida | R8: Walcy Borges- SESM | S8: 30/5/2025 | W8: FALSE | Y8: =VLOOKUP($B8,'Rascunho - PRI'!B7:X609,23,FALSE) -> 0 | Z8: =VLOOKUP($B8,'Rascunho - PRI'!B7:X609,23,FALSE) -> 0
B9: 51481 | D9: Foi elaborado procedimento para emissão de permissão de trabalho, contendo no mínimo, o estabelecimento dos tipos de atividade que possam constituir riscos para a segurança operacional; A necessidade da análise prévia das condições de segurança para execução de tarefas, bem como dos perigos existentes; A inclusão na permissão de trabalho, do seu prazo de validade e de medidas adicionais de precaução e mitigação; Estabelecimento de responsabilidades e atribuições para a Força de Trabalho responsável por emitir e aprovar as permissões de trabalho; necessidade de treinamento; e Definição de metodologia de arquivamento para cada tipo de permissão de trabalho, considerando prazos compatíveis com a relevância do serviço executado? | E9: RESOLUÇÃO ANP Nº 41, DE 09 DE OUTUBRO DE 2015 | F9: Aprova o Regulamento Técnico do Sistema de Gerenciamento de Segurança Operacional de Sistemas Submarinos - SGSS. | G9: Anexo Item 19.2 | H9: SEGURANÇA OPERACIONAL - Sistemas Submarinos | I9: Conforme | J9: PE-1PBR-00210- MS- PERMISSÃO PARA TRABALHO Sistema: Portal de Gestão Sandra Nery- LNGH | O9: Gerir Prontidão, Emergência e Contingência | P9: Não Respondida | Q9: Não Respondida | R9: Walcy Borges- SESM | S9: 30/5/2025 | W9: FALSE | Y9: =VLOOKUP($B9,'Rascunho - PRI'!B8:X610,23,FALSE) -> 0 | Z9: =VLOOKUP($B9,'Rascunho - PRI'!B8:X610,23,FALSE) -> 0
B10: 51639 | D10: O Operador do Contrato define e documenta os valores e a política de segurança operacional, seu comprometimento e obrigações para proteção da vida humana, do meio ambiente e das atividades econômicas próprias e de terceiros, sendo estes documentos aprovados pela alta gerência? | E10: RESOLUÇÃO ANP Nº 46, DE 01 DE NOVEMBRO DE 2016 | F10: Aprova o Regime de Segurança Operacional para Integridade de Poços de Petróleo e Gás Natural, que estabelece os requisitos de segurança operacional e de preservação do meio ambiente para perfuração, completação, avaliação, intervenção, produção e abandono de poços de petróleo e gás natural. | G10: Item 1.2 | H10: SEGURANÇA OPERACIONAL - Integridade de Poços | I10: Conforme | J10: "PL-0SPB-00002 POLÍTICA DE SEGURANÇA, MEIO AMBIENTE E SAÚDE - SMS https://portal.petrobras.com.br/sobre-nos/nossa-estrategia https://portal.petrobras.com.br/sustentabilidade-e-seguranca/seguranca Sistema:Portal de Gestão / Intranet Atendido conforme padrão PL-0SPB-00002 - POLÍTICA DE SEGURANÇA, MEIO AMBIENTE E SAÚDE - SMS disponível no portal de gestão." Sandra Nery-LNGH | O10: Gerir Prontidão, Emergência e Contingência | P10: Não Respondida | Q10: Não Respondida | R10: Walcy Borges- SESM | S10: 30/5/2025 | W10: FALSE | Y10: =VLOOKUP($B10,'Rascunho - PRI'!B9:X611,23,FALSE) -> 0 | Z10: =VLOOKUP($B10,'Rascunho - PRI'!B9:X611,23,FALSE) -> 0
B11: 54316 | D11: Na elaboração do Plano de Emergência Individual foram observadas as diretrizes trazidas pela presente Nota Técnica? | E11: NOTA TÉCNICA CGPEG/DILIC/IBAMA Nº 03, DE 20 DE SETEMBRO DE 2013 | F11: Diretrizes para aprovação dos Planos de Emergência Individual ¿ PEI, nos processos de licenciamento ambiental dos empreendimentos marítimos de exploração e produção de petróleo e gás natural. | G11: Item I | H11: RECURSOS HÍDRICOS - Controle de poluição por óleo e outras substâncias nocivas/perigosas em águas jurisdicionais brasileiras OFFSHORE | I11: Conforme | J11: Conforme procedimentos e obtenção de L.O PE-3BUZ-00219 PEI - PLANO DE EMERGÊNCIA INDIVIDUAL DA PLATAFORMA P-74 PE-3BUZ-00220 PEI - PLANO DE EMERGÊNCIA INDIVIDUAL DA PLATAFORMA P-75 PE-3BUZ-00221 PEI - PLANO DE EMERGÊNCIA INDIVIDUAL DA PLATAFORMA P-76 PE-3BUZ-00222 PEI - PLANO DE EMERGÊNCIA INDIVIDUAL DA PLATAFORMA P-77 Sistema: Portal de Gestão Walcy Borges- SESM | K11: Conforme procedimentos e obtenção de L.O PE-3BUZ-00219 PEI - PLANO DE EMERGÊNCIA INDIVIDUAL DA PLATAFORMA P-74 PE-3BUZ-00220 PEI - PLANO DE EMERGÊNCIA INDIVIDUAL DA PLATAFORMA P-75 PE-3BUZ-00221 PEI - PLANO DE EMERGÊNCIA INDIVIDUAL DA PLATAFORMA P-76 PE-3BUZ-00222 PEI - PLANO DE EMERGÊNCIA INDIVIDUAL DA PLATAFORMA P-77 | L11: Portal de Gestão | M11: Conforme procedimentos e obtenção de L.O PE-3BUZ-00219 PEI - PLANO DE EMERGÊNCIA INDIVIDUAL DA PLATAFORMA P-74 PE-3BUZ-00220 PEI - PLANO DE EMERGÊNCIA INDIVIDUAL DA PLATAFORMA P-75 PE-3BUZ-00221 PEI - PLANO DE EMERGÊNCIA INDIVIDUAL DA PLATAFORMA P-76 PE-3BUZ-00222 PEI - PLANO DE EMERGÊNCIA INDIVIDUAL DA PLATAFORMA P-77 | N11: Portal de Gestão | O11: Gerir Prontidão, Emergência e Contingência | P11: Respondida | Q11: Respondida | R11: Walcy Borges- SESM | S11: 8/5/2025 | T11: 46050 | W11: FALSE | Y11: =VLOOKUP($B11,'Rascunho - PRI'!B10:X612,23,FALSE) -> 0 | Z11: =VLOOKUP($B11,'Rascunho - PRI'!B10:X612,23,FALSE) -> 0
B12: 92186 | D12: Após a realização dos exercícios simulados ou na ocorrência de situações reais, é elaborado relatório, com o objetivo de verificar a eficácia do PRE, detectar possíveis falhas e subsidiar os ajustes necessários? | E12: NR-34 | F12: CONDIÇÕES E MEIO AMBIENTE DE TRABALHO NA INDÚSTRIA DA CONSTRUÇÃO,REPARAÇÃO E DESMONTE NAVAL. | G12: Item 34.17.4.2 | H12: ATIVIDADES OFFSHORE - AMBIENTE NAVAL | I12: Conforme | J12: Sim, Relatórios disponíveis na endereço: UN-BUZ SMS SEG - Documentos\2 - Interna\04 - Contingência, Prontidão e Resposta\01. Simulados\01 - Simulado N1 Sistema: BDOC Walcy Borges- SESM | K12: Sim, após a realização dos simulados ou ocorrências reais são emitidos relatórios | L12: Relatórios disponiveis na endereço UN-BUZ SMS SEG - Documentos\2 - Interna\04 - Contingência, Prontidão e Resposta\01. Simulados\01 - Simulado N1 | M12: Sim, após a realização dos simulados ou ocorrências reais são emitidos relatórios | N12: Relatórios disponiveis na endereço UN-BUZ SMS SEG - Documentos\2 - Interna\04 - Contingência, Prontidão e Resposta\01. Simulados\01 - Simulado N1 | O12: Gerir Prontidão, Emergência e Contingência | P12: Respondida | Q12: Respondida | R12: Walcy Borges- SESM | S12: 8/5/2025 | T12: 46050 | W12: FALSE | Y12: =VLOOKUP($B12,'Rascunho - PRI'!B11:X613,23,FALSE) -> 0 | Z12: =VLOOKUP($B12,'Rascunho - PRI'!B11:X613,23,FALSE) -> 0
B13: 51416 | D13: O Operador do Sistema Submarino criou um banco de dados com os Alertas de Segurança recebidos e emitidos, avalia a aplicabilidade dos Alertas de Segurança recebidos e implementa as ações pertinentes compatíveis com os riscos envolvidos (conforme itens 11.3.3.2 e 11.3.3.3)? | E13: RESOLUÇÃO ANP Nº 41, DE 09 DE OUTUBRO DE 2015 | F13: Aprova o Regulamento Técnico do Sistema de Gerenciamento de Segurança Operacional de Sistemas Submarinos - SGSS. | G13: Anexo Item 11.4 | H13: SEGURANÇA OPERACIONAL - Sistemas Submarinos | I13: Conforme | J13: Sistema: Intranet (https://portal.petrobras.com.br/group/portal-petrobras/sustentabilidade-e-seguranca/seguranca) / Abrange+ Sandra Nery- LNGH | O13: Gerir Prontidão, Emergência e Contingência | P13: Não Respondida | Q13: Não Respondida | R13: Walcy Borges- SESM | S13: 30/5/2025 | W13: FALSE | Y13: =VLOOKUP($B13,'Rascunho - PRI'!B12:X614,23,FALSE) -> 0 | Z13: =VLOOKUP($B13,'Rascunho - PRI'!B12:X614,23,FALSE) -> 0
B14: 51448 | D14: O Plano de Resposta a Emergência é reavaliado periodicamente, sempre que necessário e, no mínimo, nas seguintes situações: sempre que uma análise de riscos assim o indicar; sempre que ocorrerem modificações físicas, operacionais ou organizacionais que afetem os seus procedimentos ou a sua capacidade de resposta; quando a avaliação do desempenho do Plano de Resposta a Emergência, decorrente do seu acionamento por Incidente ou exercício simulado, recomendar; e em outras situações a critério da ANP? | E14: RESOLUÇÃO ANP Nº 41, DE 09 DE OUTUBRO DE 2015 | F14: Aprova o Regulamento Técnico do Sistema de Gerenciamento de Segurança Operacional de Sistemas Submarinos - SGSS. | G14: Anexo Item 18.6 | H14: SEGURANÇA OPERACIONAL - Sistemas Submarinos | I14: Conforme | J14: Conforme sumário de revisões nos padrões ou sistemas definidos._x000D_ _x000D_ Sistema: Portal de Gestão / INFOPAE_x000D_ Sandra Nery- LNGH | O14: Gerir Prontidão, Emergência e Contingência | P14: Não Respondida | Q14: Não Respondida | R14: Walcy Borges- SESM | S14: 30/5/2025 | W14: FALSE | Y14: =VLOOKUP($B14,'Rascunho - PRI'!B13:X615,23,FALSE) -> 0 | Z14: =VLOOKUP($B14,'Rascunho - PRI'!B13:X615,23,FALSE) -> 0
B15: 51463 | D15: O relatório de investigação do Incidente, contém, no mínimo: a Data do Incidente; Data do início da investigação do Incidente; Introdução, contendo dados técnicos do objeto investigado; Composição da equipe de investigação, incluindo a função, empresa e setor de cada membro participante; Técnicas e ferramentas de investigação de Incidente; Descrição do Incidente; Se o Incidente estiver relacionado a vazamento de produtos perigosos, incluir indicação do volume vazado ou descarregado e o comportamento da mancha; sequência em ordem cronológica de eventos associados ao Incidente, fatores Causais e Causas Raiz, demonstrando a relação com a sequência de eventos; recomendações, enfatizando a importância de sua aplicação; e referências, incluindo os documentos utilizados na investigação, mídias digitais de imagens, vídeos e gravações, conforme aplicável? | E15: RESOLUÇÃO ANP Nº 41, DE 09 DE OUTUBRO DE 2015 | F15: Aprova o Regulamento Técnico do Sistema de Gerenciamento de Segurança Operacional de Sistemas Submarinos - SGSS. | G15: Anexo Item 14.5.2 | H15: SEGURANÇA OPERACIONAL - Sistemas Submarinos | I15: Conforme | J15: "PP-1PBR-00150 - GERIR ANOMALIAS DE SMS._x000D_ _x000D_ Sistema: SAP-SMS"_x000D_ Sandra Nery- LNGH | O15: Gerir Prontidão, Emergência e Contingência | P15: Não Respondida | Q15: Não Respondida | R15: Walcy Borges- SESM | S15: 30/5/2025 | W15: FALSE | Y15: =VLOOKUP($B15,'Rascunho - PRI'!B14:X616,23,FALSE) -> 0 | Z15: =VLOOKUP($B15,'Rascunho - PRI'!B14:X616,23,FALSE) -> 0
B16: 55396 | C16: Sim | D16: A empresa possui um Plano de Emergência prevendo a ocorrência de emergências na área de armazenamento de resíduos perigosos? NOTA: O Plano deve conter os seguintes itens: a) informações de possíveis incidentes e das ações a serem tomadas; b) lista atualizada com indicação da pessoa que deve atuar como coordenador e seu substituto, indicando seus telefones e endereços; c) lista de todos os equipamentos de segurança existentes, incluindo localização, descrição do tipo e capacidade. | E16: ABNT NBR 12235:1992 | F16: Armazenamento de resíduos sólidos perigosos - Procedimento. | G16: Item 5.2 | H16: RESÍDUOS PERIGOSOS - Geração de resíduos perigosos (obrigações gerais) | I16: Conforme | J16: 1- O Plano de Resposta a Emergência das unidades de Búzios PE-3BUZ-00100 prevê ocorrências de emergência na área de armazenamento de resíduos perigosos, contempla cenários emergenciais que podem ser associados aos riscos inerentes á área supracitada. Como por exemplo: Liberação produtos químicos no convés da embarcação. a) No item 13 do PE-3BUZ-00100 estão relacionados os cenários de emergências mapeados para as unidades de Búzios. O Anexo E - Estratégias e Procedimentos Operacionais de Resposta contempla o fluxograma das ações a serem realizadas para o controle das emergências. b) No Anexo C é demonstrada a estrutura da EOR - Estrutura Organizacional de Resposta. A comunicação é realizada conforme item 3.2 do PRE. c) A relação dos equipamentos para contenção e limpeza de produtos químicos vazado, bem como as informações associadas a localização estão contempladas no PEI - Plano de Emergência Individual, onde cada unidade de Búzios possui um padrão individual. PE-3BUZ-00219 - PEI - Plano de Emergência Individual para Incidentes de Poluição por Óleo da P-74 PE-3BUZ-00220 - PEI - Plano de Emergência Individual para Incidentes de Poluição por Óleo da P-75 PE-3BUZ-00221 - PEI - Plano de Emergência Individual para Incidentes de Poluição por Óleo da P-76 PE-3BUZ-00222 - PEI - Plano de Emergência Individual para Incidentes de Poluição por Óleo da P-77 (Leandro) | K16: Sim, os cenários de emergência são contemplados no PRE - Plano de Resposta a Emergência das unidades de Búzios (PE-3BUZ-00100 - PLANO DE RESPOSTA A EMERGÊNCIAS NAS PLATAFORMAS) de acordo com as legislações da ANP, IBAMA, MTE e Marinha. | L16: INFOPAE - https://infopae.petrobras.com.br/ipae/?hxid=50c57e2be46b67df#/main?url= Portal de Gestão - SINPEP: https://portalgestao.petrobras.com.br/pges/#/ | O16: Gerir Prontidão, Emergência e Contingência | P16: Respondida | Q16: Respondida | R16: Walcy Borges- SESM | S16: 21/6/2023 | T16: 45945 | V16: Analisado | W16: FALSE | X16: Padrão fala em como acessar o INFOPAE, não fala sobre Plano de Emergência para ocorrências nas áreas de armazenamento de produtos perigosos. Padrão/Resposta está correto? | Z16: =VLOOKUP($B16,'Rascunho - PRI'!B15:X617,23,FALSE) -> Padrão fala em como acessar o INFOPAE, não fala sobre Plano de Emergência para ocorrências nas áreas de armazenamento de produtos perigosos. Padrão/Resposta está correto?
B17: 80409 | D17: Os exercícios simulados envolvem os trabalhadores designados e contemplam os cenários e a periodicidade definidos no PRE? NOTA: Após a realização dos exercícios simulados ou na ocorrência de sinistros a bordo, deve ser avaliado o atendimento do PRE, com o objetivo de se verificar a sua eficácia, detectar possíveis desvios e proceder aos ajustes necessários. | E17: NR-37 | F17: SEGURANÇA E SAÚDE EM PLATAFORMAS DE PETRÓLEO. | G17: Item 37.28.3.1 | H17: ATIVIDADES OFFSHORE - RESPOSTA A EMERGÊNCIA | I17: Conforme | J17: "Conforme procedimento PE-2SMS-00074 PGERIR TREINAMENTOS DE CONTINGÊNCIA E SIMULADOS NO E&P UN-BUZ SMS SEG - Documentos\2 - Interna\04 - Contingência, Prontidão e Resposta\01. Simulados\01 - Simulado N1 Sistema: Portal de Gestão / BDOC Conforme cronograma de Simulado de Búzios (PE-2SMS-00074)" Walcy Borges- SESM | K17: Conforme procedimento PE-2SMS-00074 PGERIR TREINAMENTOS DE CONTINGÊNCIA E SIMULADOS NO E&P | L17: Portal de Gestão BDOC: UN-BUZ SMS SEG - Documentos\2 - Interna\04 - Contingência, Prontidão e Resposta\01. Simulados\01 - Simulado N1 | M17: Conforme procedimento PE-2SMS-00074 PGERIR TREINAMENTOS DE CONTINGÊNCIA E SIMULADOS NO E&P | N17: Portal de Gestão BDOC: UN-BUZ SMS SEG - Documentos\2 - Interna\04 - Contingência, Prontidão e Resposta\01. Simulados\01 - Simulado N1 | O17: Gerir Prontidão, Emergência e Contingência | P17: Respondida | Q17: Respondida | R17: Walcy Borges- SESM | S17: 8/5/2025 | T17: 46050 | W17: FALSE | Y17: =VLOOKUP($B17,'Rascunho - PRI'!B16:X618,23,FALSE) -> 0 | Z17: =VLOOKUP($B17,'Rascunho - PRI'!B16:X618,23,FALSE) -> 0
B18: 80410 | D18: A operadora da instalação mantém em local visível a tabela atualizada de postos de emergência, relacionando nominalmente os trabalhadores integrantes das equipes que compõem o PRE a bordo? | E18: NR-37 | F18: SEGURANÇA E SAÚDE EM PLATAFORMAS DE PETRÓLEO. | G18: Item 37.28.2.1 | H18: ATIVIDADES OFFSHORE - RESPOSTA A EMERGÊNCIA | I18: Conforme | J18: Listagem disponível na sala de briefing_x000D_ Sistema: APLAT _x000D_ _x000D_ _x000D_ Walcy Borges- SESM | K18: Listagem disponível na sala de briefing | L18: APLAT | M18: Listagem disponível na sala de briefing | N18: APLAT | O18: Gerir Prontidão, Emergência e Contingência | P18: Respondida | Q18: Respondida | R18: Walcy Borges- SESM | S18: 8/5/2025 | T18: 46050 | W18: FALSE | Y18: =VLOOKUP($B18,'Rascunho - PRI'!B17:X619,23,FALSE) -> 0 | Z18: =VLOOKUP($B18,'Rascunho - PRI'!B17:X619,23,FALSE) -> 0
B19: 80583 | D19: A proteção contra incêndios nas plataformas foi desenvolvida por meio de uma abordagem estruturada, considerar os riscos existentes para os trabalhadores, possuindo os objetivos constantes do Item 37.25.2? | E19: NR-37 | F19: SEGURANÇA E SAÚDE EM PLATAFORMAS DE PETRÓLEO. | G19: Item 37.25.2 | H19: ATIVIDADES OFFSHORE - COMBATE E PREVENÇÃO A INCÊNDIOS (GERAL) | I19: Conforme | J19: A proteção contra incêndio é realizada pela SRGE com base na analise de risco e requisitos normativos aplicados a estes sistemas. Alterações posteriores são realizadas por GM - Gerenciamento de mudanças pela Operação. Walcy Borges- SESM | O19: Gerir Prontidão, Emergência e Contingência | P19: Transferir | Q19: Transferir | R19: Walcy Borges- SESM | S19: 2/5/2025 | U19: Responsabilidade das Gerências PDP e SRGE | W19: FALSE | Y19: =VLOOKUP($B19,'Rascunho - PRI'!B18:X620,23,FALSE) -> 0 | Z19: =VLOOKUP($B19,'Rascunho - PRI'!B18:X620,23,FALSE) -> 0
B20: 51431 | D20: Foi elaborado, implementado e documentado procedimentos e métodos para monitorar e medir regularmente as características principais das operações e atividades que possam causar acidentes, incluindo o registro das informações, o método de acompanhamento do desempenho, os controles operacionais pertinentes, a conformidade com as metas e objetivos de segurança operacional e a periodicidade de medição e controle? NOTA: É obrigatório a designação de um responsável pelo acompanhamento de cada Indicador de Desempenho. | E20: RESOLUÇÃO ANP Nº 41, DE 09 DE OUTUBRO DE 2015 | F20: Aprova o Regulamento Técnico do Sistema de Gerenciamento de Segurança Operacional de Sistemas Submarinos - SGSS. | G20: Anexo Item 11.3.1 e 11.3.1.1 | H20: SEGURANÇA OPERACIONAL - Sistemas Submarinos | I20: Conforme | J20: DI-1PBR-00125 - DIRETRIZES PARA O GERENCIAMENTO DA INTEGRIDADE DE SISTEMAS SUBMARINOS NA PETROBRAS Sistema: Portal de Gestão Sandra Nery- LNGH | O20: Gerir Prontidão, Emergência e Contingência | P20: Não Respondida | Q20: Não Respondida | R20: Walcy Borges- SESM | S20: 30/5/2025 | W20: FALSE | Y20: =VLOOKUP($B20,'Rascunho - PRI'!B19:X621,23,FALSE) -> 0 | Z20: =VLOOKUP($B20,'Rascunho - PRI'!B19:X621,23,FALSE) -> 0
B21: 51591 | D21: O Plano de Emergência é reavaliado sempre que uma análise de risco assim o indicar; quando a avaliação do desempenho do Plano de Emergência, decorrente do seu acionamento por incidente ou exercício simulado, recomendar; sempre que a instalação sofrer modificações físicas, operacionais ou organizacionais que afetem seus procedimentos ou a sua capacidade de resposta; ou em outras situações a critério da ANP? | E21: RESOLUÇÃO ANP Nº 43, DE 06 DE DEZEMBRO DE 2007 | F21: Institui o Regime de Segurança Operacional para as Instalações de Perfuração e Produção de Petróleo e Gás Natural. | G21: Prática de Gestão 14 - Item 14.7 | H21: SEGURANÇA OPERACIONAL - Atividade de Operação e Produção Marítima | I21: Conforme | J21: Sim. Conforme os padrões PE-3BUZ-00100 - PLANO DE RESPOSTA A EMERGÊNCIAS NAS PLATAFORMAS, PE-3BUZ-00222 - PEI - PLANO DE EMERGÊNCIA INDIVIDUAL DA PLATAFORMA P-77, PE-3BUZ-00220 - PEI - PLANO DE EMERGÊNCIA INDIVIDUAL DA PLATAFORMA P-75, PE-3BUZ-00219 - PEI - PLANO DE EMERGÊNCIA INDIVIDUAL DA PLATAFORMA P-74 e PE-3BUZ-00221 - PEI - PLANO DE EMERGÊNCIA INDIVIDUAL DA PLATAFORMA P-76. _x000D_ Fabio Mota- DXV9 | O21: Gerir Prontidão, Emergência e Contingência | P21: Não Respondida | Q21: Não Respondida | R21: Walcy Borges- SESM | S21: 23/5/2025 | W21: FALSE | Y21: =VLOOKUP($B21,'Rascunho - PRI'!B20:X622,23,FALSE) -> 0 | Z21: =VLOOKUP($B21,'Rascunho - PRI'!B20:X622,23,FALSE) -> 0
B22: 51599 | D22: Operador do Contrato designa a equipe responsável e inicia os trabalhos de investigação tão rapidamente quanto possível, não excedendo 48 horas após o encerramento do incidente, a fim de preservar as evidências, salvo por motivo de força maior devidamente justificado e documentado? | E22: RESOLUÇÃO ANP Nº 46, DE 01 DE NOVEMBRO DE 2016 | F22: Aprova o Regime de Segurança Operacional para Integridade de Poços de Petróleo e Gás Natural, que estabelece os requisitos de segurança operacional e de preservação do meio ambiente para perfuração, completação, avaliação, intervenção, produção e abandono de poços de petróleo e gás natural. | G22: Item 9.4.1 | H22: SEGURANÇA OPERACIONAL - Integridade de Poços | I22: Conforme | J22: Sim, conforme PP-1PBR-00150 GERIR ANOMALIAS DE SMS Sistema: SAP SMS Sandra Nery- LNGH | O22: Gerir Prontidão, Emergência e Contingência | P22: Não Respondida | Q22: Não Respondida | R22: Walcy Borges- SESM | S22: 30/5/2025 | W22: FALSE | Y22: =VLOOKUP($B22,'Rascunho - PRI'!B21:X623,23,FALSE) -> 0 | Z22: =VLOOKUP($B22,'Rascunho - PRI'!B21:X623,23,FALSE) -> 0
B23: 51631 | D23: Foi elaborado procedimentos de controle abordando a identificação de novos perigos introduzidos pelas Operações Simultâneas e verificação da existência de medidas de prevenção e/ou mitigação adequadas para estes perigos; definição das responsabilidades, de modo a assegurar uma adequada coordenação entre todas as organizações envolvidas, incluindo resposta à emergência? | E23: RESOLUÇÃO ANP Nº 43, DE 06 DE DEZEMBRO DE 2007 | F23: Institui o Regime de Segurança Operacional para as Instalações de Perfuração e Produção de Petróleo e Gás Natural. | G23: Prática de Gestão 15 - Item 15.4 | H23: SEGURANÇA OPERACIONAL - Atividade de Operação e Produção Marítima | I23: Conforme | J23: Sim, conforme PE-1PBR-00211 - MS- TRABALHOS E OPERAÇÕES SIMULTÂNEAS.Sistema Portal de Gestão.Sandra Nery | O23: Gerir Prontidão, Emergência e Contingência | P23: Não Respondida | Q23: Não Respondida | R23: Walcy Borges- SESM | S23: 9/6/2025 | W23: FALSE | Y23: =VLOOKUP($B23,'Rascunho - PRI'!B22:X624,23,FALSE) -> 0 | Z23: =VLOOKUP($B23,'Rascunho - PRI'!B22:X624,23,FALSE) -> 0
B24: 52071 | D24: A unidade providenciou para todos os trabalhadores informações sobre: utilização dos equipamentos de combate ao incêndio; procedimentos de resposta aos cenários de emergências e para evacuação dos locais de trabalho com segurança; e dispositivos de alarme existentes? | E24: NR-23 | F24: PROTEÇÃO CONTRA INCÊNDIO. | G24: Item 23.3.2 | H24: INCÊNDIO E EXPLOSÃO / PREVENÇÃO - Obrigações gerais relativas à combate e prevenção a INCÊNDIOS | I24: Conforme | J24: Sim, Através de treinamento básico da NR-37, briefings de segurança para toda a força de trabalho e CBSP. Em treinamentos específicos para atuação na EOR. Sistema: SIRH Walcy Borges- SESM | K24: Através de treinamento básico da NR-37, briefings de segurança para toda a força de trabalho e CBSP | L24: Em treinamentos especificos para atuação na EOR. Sistema: SIRH | M24: Através de treinamento básico da NR-37, briefings de segurança para toda a força de trabalho e CBSP | N24: Em treinamentos especificos para atuação na EOR. Sistema: SIRH | O24: Gerir Prontidão, Emergência e Contingência | P24: Respondida | Q24: Respondida | R24: Walcy Borges- SESM | S24: 8/5/2025 | T24: 46050 | W24: FALSE | Y24: =VLOOKUP($B24,'Rascunho - PRI'!B23:X625,23,FALSE) -> 0 | Z24: =VLOOKUP($B24,'Rascunho - PRI'!B23:X625,23,FALSE) -> 0
B25: 53658 | D25: 1 - A aplicação de dispersantes químicos, como técnica de resposta a incidentes de poluição por óleo, somente é utilizada quando a não intervenção ou a aplicação de técnicas mecânicas de contenção, recolhimento e dispersão se mostrarem não efetivas, inaplicáveis ou insuficientes? 2 - O disposto anteriormente não se aplica quando for necessária a adoção de medidas emergenciais para situações de risco iminente de incêndio ou de salvaguarda da vida humana no mar, envolvendo instalações marítimas ou navios. | E25: RESOLUÇÃO CONAMA Nº 472, DE 27 DE NOVEMBRO DE 2015 | F25: Dispõe sobre o uso de dispersantes químicos em incidentes de poluição por óleo no mar. | G25: Art. 5º | H25: RECURSOS HÍDRICOS - Controle de poluição por óleo e outras substâncias nocivas/perigosas em águas jurisdicionais brasileiras OFFSHORE | I25: Conforme | J25: Conforme procedimento PE-3UBS-00627 PEVO-BS - PLANO DE EMERGÊNCIA PARA VAZAMENTO DE ÓLEO NA ÁREA GEOGRÁFICA DA BACIA DE SANTOS Sistema: Portal de Gestão Walcy Borges- SESM | K25: Conforme procedimento PE-3UBS-00627 PEVO-BS - PLANO DE EMERGÊNCIA PARA VAZAMENTO DE ÓLEO NA ÁREA GEOGRÁFICA DA BACIA DE SANTOS | L25: Portal de Gestão | M25: Conforme procedimento PE-3UBS-00627 PEVO-BS - PLANO DE EMERGÊNCIA PARA VAZAMENTO DE ÓLEO NA ÁREA GEOGRÁFICA DA BACIA DE SANTOS | N25: Portal de Gestão | O25: Gerir Prontidão, Emergência e Contingência | P25: Respondida | Q25: Respondida | R25: Walcy Borges- SESM | S25: 8/5/2025 | T25: 46050 | W25: FALSE | Y25: =VLOOKUP($B25,'Rascunho - PRI'!B24:X626,23,FALSE) -> 0 | Z25: =VLOOKUP($B25,'Rascunho - PRI'!B24:X626,23,FALSE) -> 0
B26: 107203 | D26: Foi elaborado plano de emergência incluindo informações sobre o que fazer no caso de incêndio, acidente, incidentes e emissões e/ou vazamentos de produtos químicos, além das informações mínimas descritas nos itens 7.4.2, 7.4.3, 7.4.4? | E26: ABNT NBR 17160:2024 | F26: Armazenamento seguro de produtos químicos. | G26: Item 7.4 | H26: PRODUTOS QUÍMICOS - Utilizar PRODUTOS QUÍMICOS em geral (obrigações gerais) | I26: Conforme | J26: Sim, as plataformas possuem o Plano de Resposta a Emergência (PRE) contemplando ações em caso de incêndio, acidente, incidentes e emissões e/ou vazamentos de produtos químicos. - Fábio Mota-DXV9 | O26: Gerir Prontidão, Emergência e Contingência | P26: Não Respondida | Q26: Não Respondida | R26: Walcy Borges- SESM | S26: 23/7/2025 | W26: FALSE | Y26: =VLOOKUP($B26,'Rascunho - PRI'!B25:X627,23,FALSE) -> 0 | Z26: =VLOOKUP($B26,'Rascunho - PRI'!B25:X627,23,FALSE) -> 0
B27: 51475 | D27: O Operador do Sistema Submariono definiu equipe multidisciplinar responsável pela elaboração e revisão de Planos de Resposta a Emergência, considerando no mínimo a qualificação e experiência dos membros, a dimensão do(s) cenário(s) acidentais, a complexidade da atividade, do Sistema Submarino, da operação ou do empreendimento a ser analisado? | E27: RESOLUÇÃO ANP Nº 41, DE 09 DE OUTUBRO DE 2015 | F27: Aprova o Regulamento Técnico do Sistema de Gerenciamento de Segurança Operacional de Sistemas Submarinos - SGSS. | G27: Anexo Item 18.2.1 | H27: SEGURANÇA OPERACIONAL - Sistemas Submarinos | I27: Conforme | J27: Conforme Quadro 3 ¿ Lista de participantes, função e disciplina dos responsáveis técnicos - PE-3BUZ-00100 - PLANO DE RESPOSTA A EMERGÊNCIAS NAS PLATAFORMAS. Sistema: Portal de Gestão / INFOPAE Sandra Nery- LNGH | O27: Gerir Prontidão, Emergência e Contingência | P27: Não Respondida | Q27: Não Respondida | R27: Walcy Borges- SESM | S27: 30/5/2025 | W27: FALSE | Y27: =VLOOKUP($B27,'Rascunho - PRI'!B26:X628,23,FALSE) -> 0 | Z27: =VLOOKUP($B27,'Rascunho - PRI'!B26:X628,23,FALSE) -> 0
B28: 51628 | D28: Foi estabelecido pelo Operador da Instalação sistemas confiáveis e eficazes de comunicação e alarme, bem como procedimentos de comunicação interna e externa, incluindo agências reguladoras e demais autoridades governamentais competentes? | E28: RESOLUÇÃO ANP Nº 43, DE 06 DE DEZEMBRO DE 2007 | F28: Institui o Regime de Segurança Operacional para as Instalações de Perfuração e Produção de Petróleo e Gás Natural. | G28: Prática de Gestão 14 - Item 14.5 | H28: SEGURANÇA OPERACIONAL - Atividade de Operação e Produção Marítima | I28: Conforme | J28: Sim, conforme PE-3BUZ-00100- PLANO DE RESPOSTA A EMERGÊNCIAS NAS PLATAFORMAS. Fabio Mota- DXV9 | O28: Gerir Prontidão, Emergência e Contingência | P28: Não Respondida | Q28: Não Respondida | R28: Walcy Borges- SESM | S28: 30/5/2025 | W28: FALSE | Y28: =VLOOKUP($B28,'Rascunho - PRI'!B27:X629,23,FALSE) -> 0 | Z28: =VLOOKUP($B28,'Rascunho - PRI'!B27:X629,23,FALSE) -> 0
B29: 80587 | D29: As plataformas são dotadas de sistemas fixos de extinção de incêndio eficazes, de acordo com as classes de fogo possíveis e o potencial de incêndio na área a ser protegida? | E29: NR-37 | F29: SEGURANÇA E SAÚDE EM PLATAFORMAS DE PETRÓLEO. | G29: Item 37.25.6.2 | H29: ATIVIDADES OFFSHORE - COMBATE E PREVENÇÃO A INCÊNDIOS (GERAL) | I29: Conforme | J29: Conforme Safety Plan _x000D_ I-DE-3010.0F-5400-947-EG7-020 (P-74)_x000D_ I-DE-3010.0G-5400-947-RG1-001 (P-75)_x000D_ I-DE-3010.0H-5423-940-EA9-701 (P-76)_x000D_ I-DE-3010.0J-5400-947-RG1-001 (P-77)_x000D_ Sistema: SINDOTEC_x000D_ _x000D_ _x000D_ Walcy Borges- SESM | K29: Conforme Safety Plan I-DE-3010.0F-5400-947-EG7-020 (P-74) I-DE-3010.0G-5400-947-RG1-001 (P-75) I-DE-3010.0H-5423-940-EA9-701 (P-76) I-DE-3010.0J-5400-947-RG1-001 (P-77) | L29: Sindotec | M29: Conforme Safety Plan I-DE-3010.0F-5400-947-EG7-020 (P-74) I-DE-3010.0G-5400-947-RG1-001 (P-75) I-DE-3010.0H-5423-940-EA9-701 (P-76) I-DE-3010.0J-5400-947-RG1-001 (P-77) | N29: Sindotec | O29: Gerir Prontidão, Emergência e Contingência | P29: Respondida | Q29: Respondida | R29: Walcy Borges- SESM | S29: 8/5/2025 | T29: 46050 | W29: FALSE | Y29: =VLOOKUP($B29,'Rascunho - PRI'!B28:X630,23,FALSE) -> 0 | Z29: =VLOOKUP($B29,'Rascunho - PRI'!B28:X630,23,FALSE) -> 0
B30: 83725 | D30: A empresa assegura a disponibilidade dos serviços de emergência e salvamento, e de simulados, quando da realização de trabalhos em espaços confinados? | E30: NR-33 | F30: SEGURANÇA E SAÚDE NO TRABALHO EM ESPAÇOS CONFINADO. | G30: Item 33.3.1, h | H30: ESPAÇOS CONFINADOS - Executar ou fiscalizar atividades em espaços confinados | I30: Conforme | J30: Simulados de emergência - PE-2SMS-00074 GERIR TREINAMENTOS DE CONTINGÊNCIA E SIMULADOS NO E&P (Cenário CE4) Manual de Segurança - PE-1PBR-00208 MANUAL DE SEGURANÇA (MS) Permissão de Trabalho - PE-1PBR-00210 MS - PERMISSÃO PARA TRABALHO Sistema: Portal de Gestão Walcy Borges- SESM | K30: Simulados de emergência - PE-2SMS-00074 GERIR TREINAMENTOS DE CONTINGÊNCIA E SIMULADOS NO E&P (Cenário CE4) Manual de Segurança - PE-1PBR-00208 MANUAL DE SEGURANÇA (MS) Permissão de Trabalho - PE-1PBR-00210 MS - PERMISSÃO PARA TRABALHO | L30: Portal de Gestão | M30: Simulados de emergência - PE-2SMS-00074 GERIR TREINAMENTOS DE CONTINGÊNCIA E SIMULADOS NO E&P (Cenário CE4) Manual de Segurança - PE-1PBR-00208 MANUAL DE SEGURANÇA (MS) Permissão de Trabalho - PE-1PBR-00210 MS - PERMISSÃO PARA TRABALHO | N30: Portal de Gestão | O30: Gerir Prontidão, Emergência e Contingência | P30: Respondida | Q30: Respondida | R30: Walcy Borges- SESM | S30: 8/5/2025 | T30: 46050 | W30: FALSE | Y30: =VLOOKUP($B30,'Rascunho - PRI'!B29:X631,23,FALSE) -> 0 | Z30: =VLOOKUP($B30,'Rascunho - PRI'!B29:X631,23,FALSE) -> 0
B31: 51443 | D31: Os critérios para a formação da equipe de investigadores consideram a complexidade e o potencial de dano do Incidente; a inclusão de pelo menos um membro da equipe com amplo conhecimento da técnica de investigação a ser utilizada; a necessidade de inclusão de um membro da equipe com conhecimento da tarefa ou ambiente de trabalho relacionado ao Incidente; a necessidade de especialista técnico; e caso o Incidente envolva uma empresa contratada, a necessidade da inclusão de um empregado dessa empresa? | E31: RESOLUÇÃO ANP Nº 41, DE 09 DE OUTUBRO DE 2015 | F31: Aprova o Regulamento Técnico do Sistema de Gerenciamento de Segurança Operacional de Sistemas Submarinos - SGSS. | G31: Anexo Item 14.3.2 | H31: SEGURANÇA OPERACIONAL - Sistemas Submarinos | I31: Conforme | J31: "PP-1PBR-00150 - GERIR ANOMALIAS DE SMS._x000D_ _x000D_ Sistema: SAP-SMS"_x000D_ Sandra Nery- LNGH | O31: Gerir Prontidão, Emergência e Contingência | P31: Não Respondida | Q31: Não Respondida | R31: Walcy Borges- SESM | S31: 30/5/2025 | W31: FALSE | Y31: =VLOOKUP($B31,'Rascunho - PRI'!B30:X632,23,FALSE) -> 0 | Z31: =VLOOKUP($B31,'Rascunho - PRI'!B30:X632,23,FALSE) -> 0
B32: 51480 | D32: São emitidos relatórios de avaliação de desempenho do simulado? | E32: RESOLUÇÃO ANP Nº 41, DE 09 DE OUTUBRO DE 2015 | F32: Aprova o Regulamento Técnico do Sistema de Gerenciamento de Segurança Operacional de Sistemas Submarinos - SGSS. | G32: Anexo Item 18.5.2 | H32: SEGURANÇA OPERACIONAL - Sistemas Submarinos | I32: Conforme | J32: PE-2SMS-00074 GERIR TREINAMENTOS DE CONTINGÊNCIA E SIMULADOS NO E&P_x000D_ _x000D_ UN-BUZ SMS SEG - Documentos\2 - Interna\04 - Contingência, Prontidão e Resposta\01. Simulados\01 - Simulado N1_x000D_ _x000D_ Sistema: Portal de Gestão / BDoc_x000D_ Sandra Nery- LNGH | O32: Gerir Prontidão, Emergência e Contingência | P32: Não Respondida | Q32: Não Respondida | R32: Walcy Borges- SESM | S32: 30/5/2025 | W32: FALSE | Y32: =VLOOKUP($B32,'Rascunho - PRI'!B31:X633,23,FALSE) -> 0 | Z32: =VLOOKUP($B32,'Rascunho - PRI'!B31:X633,23,FALSE) -> 0
B33: 51667 | D33: O Plano de Resposta à Emergência para controle de poço está integrado aos demais planos de emergência? | E33: RESOLUÇÃO ANP Nº 46, DE 01 DE NOVEMBRO DE 2016 | F33: Aprova o Regime de Segurança Operacional para Integridade de Poços de Petróleo e Gás Natural, que estabelece os requisitos de segurança operacional e de preservação do meio ambiente para perfuração, completação, avaliação, intervenção, produção e abandono de poços de petróleo e gás natural. | G33: Item 14.1, 14.2 e 14.3 | H33: SEGURANÇA OPERACIONAL - Integridade de Poços | I33: Conforme | J33: " PE-2POC-00811- PRE POÇOS - PLANO DE RESPOSTA A EMERGÊNCIAS_x000D_ _x000D_ PE-3UBS-00627 PEVO-BS - PLANO DE EMERGÊNCIA PARA VAZAMENTO DE ÓLEO NA ÁREA GEOGRÁFICA DA BACIA DE SANTOS (AGBS)_x000D_ _x000D_ Sistema: Portal de Gestão / INFOPAE"_x000D_ Sandra Nery- LNGH | O33: Gerir Prontidão, Emergência e Contingência | P33: Não Respondida | Q33: Não Respondida | R33: Walcy Borges- SESM | S33: 30/5/2025 | W33: FALSE | Y33: =VLOOKUP($B33,'Rascunho - PRI'!B32:X634,23,FALSE) -> 0 | Z33: =VLOOKUP($B33,'Rascunho - PRI'!B32:X634,23,FALSE) -> 0
B34: 80391 | D34: A operadora da instalação disponibiliza meios de resgate de emergência durante todo o período de pouso e decolagem de aeronaves na plataforma, conforme prescrito na NORMAM/DPC? | E34: NR-37 | F34: SEGURANÇA E SAÚDE EM PLATAFORMAS DE PETRÓLEO. | G34: Item 37.28.3 | H34: ATIVIDADES OFFSHORE - RESPOSTA A EMERGÊNCIA | I34: Conforme | J34: Conforme procedimento PE-3BUZ-00100 PLANO DE RESPOSTA A EMERGÊNCIAS NAS PLATAFORMAS Anexo A Sistema: Portal de Gestão / INFOPAE Walcy Borges- SESM | K34: Conforme procedimento PE-3BUZ-00100 PLANO DE RESPOSTA A EMERGÊNCIAS NAS PLATAFORMAS | L34: Portal de Gestão / INFOPAE | M34: Conforme procedimento PE-3BUZ-00100 PLANO DE RESPOSTA A EMERGÊNCIAS NAS PLATAFORMAS | N34: Portal de Gestão / INFOPAE | O34: Gerir Prontidão, Emergência e Contingência | P34: Respondida | Q34: Respondida | R34: Walcy Borges- SESM | S34: 8/5/2025 | T34: 46050 | U34: Anexo A | W34: FALSE | Y34: =VLOOKUP($B34,'Rascunho - PRI'!B33:X635,23,FALSE) -> 0 | Z34: =VLOOKUP($B34,'Rascunho - PRI'!B33:X635,23,FALSE) -> 0
B35: 80429 | D35: Ao término do seu turno, o operador do equipamento deve consigna, em livro próprio ou em meio eletrônico, as anormalidades observadas em relação ao seu funcionamento? | E35: NR-37 | F35: SEGURANÇA E SAÚDE EM PLATAFORMAS DE PETRÓLEO. | G35: Item 37.20.3.7 | H35: ATIVIDADES OFFSHORE - MOVIMENTAÇÃO DE CARGAS | I35: Conforme | J35: o operador do equipamento consigna, em livro próprio ou em meio eletrônico, as anormalidades observadas em relação ao seu funcionamento conforme anexo e Conforme PE-1PBR-00223. | O35: Gerir Prontidão, Emergência e Contingência | P35: Não Respondida | Q35: Não Respondida | R35: Walcy Borges- SESM | S35: 28/2/2025 | W35: FALSE | Y35: =VLOOKUP($B35,'Rascunho - PRI'!B34:X636,23,FALSE) -> 0 | Z35: =VLOOKUP($B35,'Rascunho - PRI'!B34:X636,23,FALSE) -> 0
B36: 51425 | D36: A organização tem conhecimento de que, visando à consolidação de uma cultura de segurança operacional e ao comprometimento com a melhoria contínua do sistema de gerenciamento da segurança operacional, deve-se executar os requisitos descritos nos subitens 6.1? | E36: RESOLUÇÃO ANP Nº 41, DE 09 DE OUTUBRO DE 2015 | F36: Aprova o Regulamento Técnico do Sistema de Gerenciamento de Segurança Operacional de Sistemas Submarinos - SGSS. | G36: Anexo Item 6.1 | H36: SEGURANÇA OPERACIONAL - Sistemas Submarinos | I36: Conforme | J36: PL-0SPB-00002 - POLÍTICA DE SEGURANÇA, MEIO AMBIENTE E SAÚDE - SMS _x000D_ _x000D_ PE-2E&P-01241 INTERAÇÃO EM SEGURANÇA "INTERAGE" NO E&P_x000D_ _x000D_ PP-3BUZ-00001 PROGRAMA DE GERENCIAMENTO DA INTEGRIDADE DOS SISTEMAS SUBMARINOS DE PRODUÇÃO DE BÚZIOS_x000D_ _x000D_ Sistema: Portal de Gestão / Sistema Interage / https://portal.petrobras.com.br/group/portal-petrobras/sobre-nos/nossa-estrategia_x000D_ Sandra Nery- LNGH | O36: Gerir Prontidão, Emergência e Contingência | P36: Não Respondida | Q36: Não Respondida | R36: Walcy Borges- SESM | S36: 30/5/2025 | W36: FALSE | Y36: =VLOOKUP($B36,'Rascunho - PRI'!B35:X637,23,FALSE) -> 0 | Z36: =VLOOKUP($B36,'Rascunho - PRI'!B35:X637,23,FALSE) -> 0
B37: 51447 | D37: O Operador do Sistema Submarino estabelece, implementa e documenta programa de treinamento para os membros da equipe de resposta a emergência para todos os cenários emergenciais? | E37: RESOLUÇÃO ANP Nº 41, DE 09 DE OUTUBRO DE 2015 | F37: Aprova o Regulamento Técnico do Sistema de Gerenciamento de Segurança Operacional de Sistemas Submarinos - SGSS. | G37: Anexo Item 18.3.3 | H37: SEGURANÇA OPERACIONAL - Sistemas Submarinos | I37: Conforme | J37: PP-1PBR-00474 MANTER ESTADO DE PRONTIDÃO_x000D_ _x000D_ Sistema: Portal de Gestão. Sandra Nery- LNGH | O37: Gerir Prontidão, Emergência e Contingência | P37: Não Respondida | Q37: Não Respondida | R37: Walcy Borges- SESM | S37: 30/5/2025 | W37: FALSE | Y37: =VLOOKUP($B37,'Rascunho - PRI'!B36:X638,23,FALSE) -> 0 | Z37: =VLOOKUP($B37,'Rascunho - PRI'!B36:X638,23,FALSE) -> 0
B38: 51461 | D38: Foi elaborado procedimento para condução da investigação de Incidentes, incluindo a classificação dos Incidentes que deverão ser investigados; dimensionamento e composição da equipe de investigação; responsabilidades da equipe de investigação; procedimentos a serem seguidos pela equipe de investigação; técnicas e ferramentas de investigação a serem utilizadas; critérios para a realização periódica de análise de tendência de um conjunto de Incidentes quanto ao tipo de ocorrência e as Causas raiz, incluindo os registros de quase acidentes? | E38: RESOLUÇÃO ANP Nº 41, DE 09 DE OUTUBRO DE 2015 | F38: Aprova o Regulamento Técnico do Sistema de Gerenciamento de Segurança Operacional de Sistemas Submarinos - SGSS. | G38: Anexo Item 14.3.1 | H38: SEGURANÇA OPERACIONAL - Sistemas Submarinos | I38: Conforme | J38: "PP-1PBR-00150 GERIR ANOMALIAS DE SMS_x000D_ _x000D_ Sistema: Portal de Gestão / SAP-SMS"_x000D_ Sandra Nery-LNGH | O38: Gerir Prontidão, Emergência e Contingência | P38: Não Respondida | Q38: Não Respondida | R38: Walcy Borges- SESM | S38: 30/5/2025 | W38: FALSE | Y38: =VLOOKUP($B38,'Rascunho - PRI'!B37:X639,23,FALSE) -> 0 | Z38: =VLOOKUP($B38,'Rascunho - PRI'!B37:X639,23,FALSE) -> 0
B39: 51464 | D39: Foi elaborado plano de ação com as ações corretivas e preventivas necessárias, com base nas medidas apontadas no relatório de investigação, com prazos compatíveis com a complexidade das ações e os riscos envolvidos? | E39: RESOLUÇÃO ANP Nº 41, DE 09 DE OUTUBRO DE 2015 | F39: Aprova o Regulamento Técnico do Sistema de Gerenciamento de Segurança Operacional de Sistemas Submarinos - SGSS. | G39: Anexo Item 14.6.1, 14.6.1.1 e 14.6.2 | H39: SEGURANÇA OPERACIONAL - Sistemas Submarinos | I39: Conforme | J39: "PP-1PBR-00150 - GERIR ANOMALIAS DE SMS._x000D_ _x000D_ Sistema: SAP-SMS"_x000D_ Sandra Nery-LNGH | O39: Gerir Prontidão, Emergência e Contingência | P39: Não Respondida | Q39: Não Respondida | R39: Walcy Borges- SESM | S39: 30/5/2025 | W39: FALSE | Y39: =VLOOKUP($B39,'Rascunho - PRI'!B38:X640,23,FALSE) -> 0 | Z39: =VLOOKUP($B39,'Rascunho - PRI'!B38:X640,23,FALSE) -> 0
B40: 51476 | D40: O Plano de Resposta a Emergência foi elaborado contendo, no mínimo, a Identificação do Sistema Submarino; Abrangência, contemplando as interfaces com outras instalações; Cenários acidentais; Estrutura organizacional de resposta, Incluindo as funções e responsabilidades; Recursos humanos, equipamentos e materiais; Sistemas de alerta; Procedimentos para resposta; Comunicação do acidente para a Força de Trabalho e para as autoridades competentes; e Critérios para o encerramento da resposta? | E40: RESOLUÇÃO ANP Nº 41, DE 09 DE OUTUBRO DE 2015 | F40: Aprova o Regulamento Técnico do Sistema de Gerenciamento de Segurança Operacional de Sistemas Submarinos - SGSS. | G40: Anexo Item 18.3 | H40: SEGURANÇA OPERACIONAL - Sistemas Submarinos | I40: Conforme | J40: PE-3BUZ-00100 - PLANO DE RESPOSTA A EMERGÊNCIAS NAS PLATAFORMAS_x000D_ _x000D_ Sistema: Portal de Gestão / INFOPAE_x000D_ Sandra Nery- LNGH | O40: Gerir Prontidão, Emergência e Contingência | P40: Não Respondida | Q40: Não Respondida | R40: Walcy Borges- SESM | S40: 30/5/2025 | W40: FALSE | Y40: =VLOOKUP($B40,'Rascunho - PRI'!B39:X641,23,FALSE) -> 0 | Z40: =VLOOKUP($B40,'Rascunho - PRI'!B39:X641,23,FALSE) -> 0
B41: 51588 | D41: O Operador da Instalação definiu equipe para elaboração de plano de emergência, considerando a qualificação e experiência da equipe em função da dimensão do cenário considerado e a complexidade da atividade, instalação, operação ou empreendimento a ser analisado? | E41: RESOLUÇÃO ANP Nº 43, DE 06 DE DEZEMBRO DE 2007 | F41: Institui o Regime de Segurança Operacional para as Instalações de Perfuração e Produção de Petróleo e Gás Natural. | G41: Prática de Gestão 14 - Item 14.2 | H41: SEGURANÇA OPERACIONAL - Atividade de Operação e Produção Marítima | I41: Conforme | J41: Conforme Quadro 3 ¿ Lista de participantes, função e disciplina dos responsáveis técnicos - PE-3BUZ-00100 - PLANO DE RESPOSTA A EMERGÊNCIAS NAS PLATAFORMAS._x000D_ Sistema: Portal de Gestão / INFOPAE._x000D_ Sandra Nery | O41: Gerir Prontidão, Emergência e Contingência | P41: Não Respondida | Q41: Não Respondida | R41: Walcy Borges- SESM | S41: 9/6/2025 | W41: FALSE | Y41: =VLOOKUP($B41,'Rascunho - PRI'!B40:X642,23,FALSE) -> 0 | Z41: =VLOOKUP($B41,'Rascunho - PRI'!B40:X642,23,FALSE) -> 0
B42: 51629 | D42: São realizados os exercícios simulados periódicos abrangendo todos os cenários previstos no Plano de Emergência, sendo coordenados com todas as organizações e autoridades reguladoras, quando aplicável; analisados de forma a verificar a necessidade de revisão do Plano de Emergência; devidamente documentados; e programados de forma a todos os cenários previstos no Plano de Emergência da Instalação serem contemplados? | E42: RESOLUÇÃO ANP Nº 43, DE 06 DE DEZEMBRO DE 2007 | F42: Institui o Regime de Segurança Operacional para as Instalações de Perfuração e Produção de Petróleo e Gás Natural. | G42: Prática de Gestão 14 - Item 14.6 | H42: SEGURANÇA OPERACIONAL - Atividade de Operação e Produção Marítima | I42: Conforme | J42: Sim, conforme o padrão PE-3BUZ - 00071- Realizar Simulados de Emergência. Os relatórios de simulados ficam arquivados nas unidades. Fabio Mota- DXV9 | O42: Gerir Prontidão, Emergência e Contingência | P42: Não Respondida | Q42: Não Respondida | R42: Walcy Borges- SESM | S42: 23/5/2025 | W42: FALSE | Y42: =VLOOKUP($B42,'Rascunho - PRI'!B41:X643,23,FALSE) -> 0 | Z42: =VLOOKUP($B42,'Rascunho - PRI'!B41:X643,23,FALSE) -> 0
B43: 80392 | D43: A operadora da instalação, a partir dos cenários das análises de riscos e das informações constantes no PGR, elaborou, implementou e disponibilizou a bordo o Plano de Resposta a Emergências - PRE, que contemple ações específicas a serem adotadas na ocorrência de eventos que configurem situações de riscos grave e iminente à segurança e à saúde dos trabalhadores, considerando os requisitos mínimos do Item 37.28.2? | E43: NR-37 | F43: SEGURANÇA E SAÚDE EM PLATAFORMAS DE PETRÓLEO. | G43: Item 37.28.1 | H43: ATIVIDADES OFFSHORE - RESPOSTA A EMERGÊNCIA | I43: Conforme | J43: Conforme procedimento PE-3BUZ-00100 PLANO DE RESPOSTA A EMERGÊNCIAS NAS PLATAFORMAS Sistema: Portal de Gestão / INFOPAE Walcy Borges- SESM | K43: Conforme procedimento PE-3BUZ-00100 PLANO DE RESPOSTA A EMERGÊNCIAS NAS PLATAFORMAS | L43: Portal de Gestão / INFOPAE | M43: Conforme procedimento PE-3BUZ-00100 PLANO DE RESPOSTA A EMERGÊNCIAS NAS PLATAFORMAS | N43: Portal de Gestão / INFOPAE | O43: Gerir Prontidão, Emergência e Contingência | P43: Respondida | Q43: Respondida | R43: Walcy Borges- SESM | S43: 8/5/2025 | T43: 46050 | W43: FALSE | Y43: =VLOOKUP($B43,'Rascunho - PRI'!B42:X644,23,FALSE) -> 0 | Z43: =VLOOKUP($B43,'Rascunho - PRI'!B42:X644,23,FALSE) -> 0
B44: 80549 | D44: A operadora da instalação continuamente implementa medidas, desde a fase de projeto, para prevenir e controlar vazamentos, derramamentos, incêndios e explosões? NOTA 1: As medidas devem contemplar os meios necessários para minimizar a ocorrência e mitigar as suas consequências, em caso de falhas nos sistemas de prevenção e controle. NOTA 2: Para as emissões fugitivas, o projeto original da plataforma e suas alterações, modificações nas condições de processo, manutenção e reparo devem incluir procedimentos para minimizar os riscos, de acordo com a viabilidade técnica, após a identificação das suas fontes. | E44: NR-37 | F44: SEGURANÇA E SAÚDE EM PLATAFORMAS DE PETRÓLEO. | G44: Item 37.24.1 | H44: ATIVIDADES OFFSHORE - COMBATE E PREVENÇÃO A INCÊNDIOS (GERAL) | I44: Conforme | J44: Atendem aos projetos de instalação. Segurança de processo. _x000D_ Na fase de projeto é de responsabilidade SRGE. Walcy Borges- SESM | O44: Gerir Prontidão, Emergência e Contingência | P44: Transferir | Q44: Transferir | R44: Walcy Borges- SESM | S44: 2/5/2025 | U44: Responsabilidade das Gerências PDP e SRGE | W44: FALSE | Y44: =VLOOKUP($B44,'Rascunho - PRI'!B43:X645,23,FALSE) -> 0 | Z44: =VLOOKUP($B44,'Rascunho - PRI'!B43:X645,23,FALSE) -> 0
B45: 80563 | D45: As medidas de prevenção e controle de vazamentos, derramamentos, incêndios e explosões são revisadas, após as análises críticas das medidas adotadas em decorrência desses eventos ou quando ocorrer alguma das situações previstas no Item 37.24.3? | E45: NR-37 | F45: SEGURANÇA E SAÚDE EM PLATAFORMAS DE PETRÓLEO. | G45: Item 37.24.3 | H45: ATIVIDADES OFFSHORE - COMBATE E PREVENÇÃO A INCÊNDIOS (GERAL) | I45: Conforme | J45: Contam no sumário de revisões dos procedimentos _x000D_ PE-3BUZ-00219 PEI - PLANO DE EMERGÊNCIA INDIVIDUAL DA PLATAFORMA P-74_x000D_ PE-3BUZ-00220 PEI - PLANO DE EMERGÊNCIA INDIVIDUAL DA PLATAFORMA P-75_x000D_ PE-3BUZ-00221 PEI - PLANO DE EMERGÊNCIA INDIVIDUAL DA PLATAFORMA P-76_x000D_ PE-3BUZ-00222 PEI - PLANO DE EMERGÊNCIA INDIVIDUAL DA PLATAFORMA P-77_x000D_ Sistema: Portal de Gestão_x000D_ _x000D_ PE-3BUZ-00100 PLANO DE RESPOSTA A EMERGÊNCIAS NAS PLATAFORMAS_x000D_ Sistema: Portal de Gestão / INFOPAE_x000D_ _x000D_ Walcy Borges- SESM | K45: Contam no sumário de revisões dos procedimentos PE-3BUZ-00219 PEI - PLANO DE EMERGÊNCIA INDIVIDUAL DA PLATAFORMA P-74 PE-3BUZ-00220 PEI - PLANO DE EMERGÊNCIA INDIVIDUAL DA PLATAFORMA P-75 PE-3BUZ-00221 PEI - PLANO DE EMERGÊNCIA INDIVIDUAL DA PLATAFORMA P-76 PE-3BUZ-00222 PEI - PLANO DE EMERGÊNCIA INDIVIDUAL DA PLATAFORMA P-77 PE-3BUZ-00100 PLANO DE RESPOSTA A EMERGÊNCIAS NAS PLATAFORMAS | L45: Portal de Gestão Infopae | M45: Contam no sumário de revisões dos procedimentos PE-3BUZ-00219 PEI - PLANO DE EMERGÊNCIA INDIVIDUAL DA PLATAFORMA P-74 PE-3BUZ-00220 PEI - PLANO DE EMERGÊNCIA INDIVIDUAL DA PLATAFORMA P-75 PE-3BUZ-00221 PEI - PLANO DE EMERGÊNCIA INDIVIDUAL DA PLATAFORMA P-76 PE-3BUZ-00222 PEI - PLANO DE EMERGÊNCIA INDIVIDUAL DA PLATAFORMA P-77 PE-3BUZ-00100 PLANO DE RESPOSTA A EMERGÊNCIAS NAS PLATAFORMAS | N45: Portal de Gestão Infopae | O45: Gerir Prontidão, Emergência e Contingência | P45: Respondida | Q45: Respondida | R45: Walcy Borges- SESM | S45: 8/5/2025 | T45: 46050 | W45: FALSE | Y45: =VLOOKUP($B45,'Rascunho - PRI'!B44:X646,23,FALSE) -> 0 | Z45: =VLOOKUP($B45,'Rascunho - PRI'!B44:X646,23,FALSE) -> 0
B46: 80575 | D46: As plataformas possuem sistema de acionamento remoto a bordo para comandar a parada de emergência de equipamentos e sistemas que possam propagar ou alimentar o incêndio com material combustível ou inflamável? | E46: NR-37 | F46: SEGURANÇA E SAÚDE EM PLATAFORMAS DE PETRÓLEO. | G46: Item 37.25.4.3 | H46: ATIVIDADES OFFSHORE - COMBATE E PREVENÇÃO A INCÊNDIOS (GERAL) | I46: Conforme | J46: " Conforme Filosofia de Segurança das Unidades de Búzios _x000D_ item 10. SISTEMA DE PARADA DE EMERGÊNCIA (SHUTDOWN) _x000D_ Sistema: Gaudi"_x000D_ _x000D_ Walcy Borges- SESM | K46: Conforme Filosofia de Segurança das Unidades de Búzios item 10. SISTEMA DE PARADA DE EMERGÊNCIA (SHUTDOWN) | L46: Sistema Gaudi | M46: Conforme Filosofia de Segurança das Unidades de Búzios item 10. SISTEMA DE PARADA DE EMERGÊNCIA (SHUTDOWN) | N46: Sistema Gaudi | O46: Gerir Prontidão, Emergência e Contingência | P46: Respondida | Q46: Respondida | R46: Walcy Borges- SESM | S46: 8/5/2025 | T46: 46050 | W46: FALSE | Y46: =VLOOKUP($B46,'Rascunho - PRI'!B45:X647,23,FALSE) -> 0 | Z46: =VLOOKUP($B46,'Rascunho - PRI'!B45:X647,23,FALSE) -> 0
B47: 80606 | D47: Os locais de trabalho e as áreas de vivência dispõem de rotas de fuga e saídas para áreas externas, em número suficiente, e dispostas de modo a conduzir os trabalhadores até um local seguro ou para o posto de abandono da plataforma com rapidez e segurança? | E47: NR-37 | F47: SEGURANÇA E SAÚDE EM PLATAFORMAS DE PETRÓLEO. | G47: Item 37.25.8.1 | H47: ATIVIDADES OFFSHORE - COMBATE E PREVENÇÃO A INCÊNDIOS (GERAL) | I47: Conforme | J47: Conforme Escape Route Plan_x000D_ I-DE-3010.0F-5433-940-EA9-502 (P-74)_x000D_ I-DE-3010.0G-5433-940-EA9-502 (P-75)_x000D_ I-DE-3010.0H-5433-940-EA9-502 (P-76)_x000D_ I-DE-3010.0J-1200-942-RG1-001 (P-77)_x000D_ I-DE-3010.2G-5433-947-KES-001 (P-78)_x000D_ Sistema: SINDOTEC_x000D_ _x000D_ Walcy Borges-SEAM | K47: Conforme Escape Route Plan I-DE-3010.0F-5433-940-EA9-502 (P-74) I-DE-3010.0G-5433-940-EA9-502 (P-75) I-DE-3010.0H-5433-940-EA9-502 (P-76) I-DE-3010.0J-1200-942-RG1-001 (P-77) I-DE-3010.2G-5433-947-KES-001 (P-78) | L47: Sindotec | M47: Conforme Escape Route Plan I-DE-3010.0F-5433-940-EA9-502 (P-74) I-DE-3010.0G-5433-940-EA9-502 (P-75) I-DE-3010.0H-5433-940-EA9-502 (P-76) I-DE-3010.0J-1200-942-RG1-001 (P-77) I-DE-3010.2G-5433-947-KES-001 (P-78) | N47: Sindotec | O47: Gerir Prontidão, Emergência e Contingência | P47: Respondida | Q47: Respondida | R47: Walcy Borges- SESM | S47: 8/5/2025 | T47: 46050 | W47: FALSE | Y47: =VLOOKUP($B47,'Rascunho - PRI'!B46:X648,23,FALSE) -> 0 | Z47: =VLOOKUP($B47,'Rascunho - PRI'!B46:X648,23,FALSE) -> 0
B48: 51462 | D48: A equipe de investigação é mobilizada prontamente e inicia os trabalhos de investigação em até às 48 horas após o encerramento do Incidente, considerando no mínimo a Inspeção, com registro de imagem do local onde ocorreu o Incidente; a Inspeção, com registro de imagem, de toda área afetada pelo Incidente, ressaltando os danos à vida humana, ao meio ambiente e ao patrimônio; Levantamento de dados, informações e eventos registrados nos sistemas de supervisão e controle; Entrevistas com testemunhas e outras pessoas relacionadas com as circunstâncias do Incidente; e histórico de operação, inspeção e manutenção, incluindo modificações provisórias ou definitivas no Sistema Submarino, anteriores ao Incidente? | E48: RESOLUÇÃO ANP Nº 41, DE 09 DE OUTUBRO DE 2015 | F48: Aprova o Regulamento Técnico do Sistema de Gerenciamento de Segurança Operacional de Sistemas Submarinos - SGSS. | G48: Anexo Item 14.4 | H48: SEGURANÇA OPERACIONAL - Sistemas Submarinos | I48: Conforme | J48: "PP-1PBR-00150 - GERIR ANOMALIAS DE SMS._x000D_ _x000D_ Sistema: SAP-SMS"_x000D_ Sandra Nery-LNGH | O48: Gerir Prontidão, Emergência e Contingência | P48: Não Respondida | Q48: Não Respondida | R48: Walcy Borges- SESM | S48: 30/5/2025 | W48: FALSE | Y48: =VLOOKUP($B48,'Rascunho - PRI'!B47:X649,23,FALSE) -> 0 | Z48: =VLOOKUP($B48,'Rascunho - PRI'!B47:X649,23,FALSE) -> 0
B49: 51465 | D49: Foi elaborado procedimento para analisar a abrangência da implementação das ações corretivas e preventivas para as suas instalações pertinentes? | E49: RESOLUÇÃO ANP Nº 41, DE 09 DE OUTUBRO DE 2015 | F49: Aprova o Regulamento Técnico do Sistema de Gerenciamento de Segurança Operacional de Sistemas Submarinos - SGSS. | G49: Anexo Item 14.7.1 | H49: SEGURANÇA OPERACIONAL - Sistemas Submarinos | I49: Conforme | J49: PE-1PBR-00894 - REALIZAR ABRANGÊNCIA DE ANOMALIAS_x000D_ _x000D_ Sistema: Portal de Gestão_x000D_ _x000D_ Sandra Nery- LNGH | O49: Gerir Prontidão, Emergência e Contingência | P49: Não Respondida | Q49: Não Respondida | R49: Walcy Borges- SESM | S49: 30/5/2025 | W49: FALSE | Y49: =VLOOKUP($B49,'Rascunho - PRI'!B48:X650,23,FALSE) -> 0 | Z49: =VLOOKUP($B49,'Rascunho - PRI'!B48:X650,23,FALSE) -> 0
B50: 51477 | D50: O Operador do Sistema Submarino identifica todos os recursos de resposta, incluindo os materiais, sistemas e equipamentos de emergência, bem como as empresas contratadas e órgãos públicos de apoio na resposta a emergência, certificando-se de sua adequação, funcionamento e disponibilidade? | E50: RESOLUÇÃO ANP Nº 41, DE 09 DE OUTUBRO DE 2015 | F50: Aprova o Regulamento Técnico do Sistema de Gerenciamento de Segurança Operacional de Sistemas Submarinos - SGSS. | G50: Anexo Item 18.3.2 | H50: SEGURANÇA OPERACIONAL - Sistemas Submarinos | I50: Conforme | J50: "PE-3BUZ-00100 - PLANO DE RESPOSTA A EMERGÊNCIAS NAS PLATAFORMAS_x000D_ _x000D_ PE-2SMS-00074 GERIR TREINAMENTOS DE CONTINGÊNCIA E SIMULADOS NO E&P_x000D_ _x000D_ Sistema: Portal de Gestão / INFOPAE"_x000D_ _x000D_ Sandra Nery- LNGH | O50: Gerir Prontidão, Emergência e Contingência | P50: Não Respondida | Q50: Não Respondida | R50: Walcy Borges- SESM | S50: 30/5/2025 | W50: FALSE | Y50: =VLOOKUP($B50,'Rascunho - PRI'!B49:X651,23,FALSE) -> 0 | Z50: =VLOOKUP($B50,'Rascunho - PRI'!B49:X651,23,FALSE) -> 0
B51: 53741 | D51: O Plano de Emergência Individual da instalação é elaborado conforme conteúdo mínimo estabelecido no Anexo I; com base nas informações referenciais estabelecidas no Anexo II; com base nos resultados da análise de risco da instalação; conforme os critérios de dimensionamento da capacidade mínima de resposta estabelecidos no Anexo III; e de forma integrada com o Plano de Área correspondente? | E51: RESOLUÇÃO CONAMA Nº 398, DE 11 DE JUNHO DE 2008 | F51: Dispõe sobre o conteúdo mínimo do Plano de Emergência Individual para incidentes de poluição por óleo em águas sob jurisdição nacional, originados em portos organizados, instalações portuárias, terminais, dutos, sondas terrestres, plataformas e suas instalações de apoio, refinarias, estaleiros, marinas, clubes náuticos e instalações similares, e orienta a sua elaboração. | G51: Art. 5º | H51: RECURSOS HÍDRICOS - Controle de poluição por óleo e outras substâncias nocivas/perigosas em águas jurisdicionais brasileiras OFFSHORE | I51: Conforme | J51: Conforme procedimentos e obtenção de L.O_x000D_ PE-3BUZ-00219 PEI - PLANO DE EMERGÊNCIA INDIVIDUAL DA PLATAFORMA P-74_x000D_ PE-3BUZ-00220 PEI - PLANO DE EMERGÊNCIA INDIVIDUAL DA PLATAFORMA P-75_x000D_ PE-3BUZ-00221 PEI - PLANO DE EMERGÊNCIA INDIVIDUAL DA PLATAFORMA P-76_x000D_ PE-3BUZ-00222 PEI - PLANO DE EMERGÊNCIA INDIVIDUAL DA PLATAFORMA P-77_x000D_ Sistema: Portal de Gestão_x000D_ _x000D_ Ponto focal Walcy Borges | K51: Conforme procedimentos e obtenção de L.O PE-3BUZ-00219 PEI - PLANO DE EMERGÊNCIA INDIVIDUAL DA PLATAFORMA P-74 PE-3BUZ-00220 PEI - PLANO DE EMERGÊNCIA INDIVIDUAL DA PLATAFORMA P-75 PE-3BUZ-00221 PEI - PLANO DE EMERGÊNCIA INDIVIDUAL DA PLATAFORMA P-76 PE-3BUZ-00222 PEI - PLANO DE EMERGÊNCIA INDIVIDUAL DA PLATAFORMA P-77 | L51: Portal de Gestão | M51: Conforme procedimentos e obtenção de L.O PE-3BUZ-00219 PEI - PLANO DE EMERGÊNCIA INDIVIDUAL DA PLATAFORMA P-74 PE-3BUZ-00220 PEI - PLANO DE EMERGÊNCIA INDIVIDUAL DA PLATAFORMA P-75 PE-3BUZ-00221 PEI - PLANO DE EMERGÊNCIA INDIVIDUAL DA PLATAFORMA P-76 PE-3BUZ-00222 PEI - PLANO DE EMERGÊNCIA INDIVIDUAL DA PLATAFORMA P-77 | N51: Portal de Gestão | O51: Gerir Prontidão, Emergência e Contingência | P51: Respondida | Q51: Respondida | R51: Walcy Borges- SESM | S51: 8/5/2025 | T51: 46050 | W51: FALSE | Y51: =VLOOKUP($B51,'Rascunho - PRI'!B50:X652,23,FALSE) -> 0 | Z51: =VLOOKUP($B51,'Rascunho - PRI'!B50:X652,23,FALSE) -> 0
B52: 74842 | D52: A organização estabelece, implementa e mantém procedimentos de resposta a emergências, de acordo com os riscos, as características e as circunstâncias das atividades, prevendo, no mínimo os meios, responsáveis e recursos necessários para os primeiros socorros, encaminhamento de acidentados e abandono de locais afetados; e as medidas necessárias para emergências de grande magnitude, quando aplicável? | E52: NR-01 | F52: Disposições Gerais e Gerenciamento de Riscos Ocupacionais. | G52: Item 1.5.6.1 e 1.5.6.2 | H52: RISCOS - Promover a redução e prevenção dos riscos no ambiente do trabalho | I52: Conforme | J52: Conforme procedimento PE-3BUZ-00100 PLANO DE RESPOSTA A EMERGÊNCIAS NAS PLATAFORMAS Sistema: Portal de Gestão. Walcy Borges- SESM | K52: Conforme procedimento PE-3BUZ-00100 PLANO DE RESPOSTA A EMERGÊNCIAS NAS PLATAFORMAS | L52: Portal de Gestão | M52: Conforme procedimento PE-3BUZ-00100 PLANO DE RESPOSTA A EMERGÊNCIAS NAS PLATAFORMAS | N52: Portal de Gestão | O52: Gerir Prontidão, Emergência e Contingência | P52: Respondida | Q52: Respondida | R52: Walcy Borges- SESM | S52: 8/5/2025 | T52: 46050 | W52: FALSE | Y52: =VLOOKUP($B52,'Rascunho - PRI'!B51:X653,23,FALSE) -> 0 | Z52: =VLOOKUP($B52,'Rascunho - PRI'!B51:X653,23,FALSE) -> 0
B53: 80577 | D53: A operadora da instalação realiza exercícios de combate a incêndio e treinamento específico para a brigada de incêndio dentro da periodicidade e com conteúdo determinados pela Autoridade Marítima (NORMAM-01/DPC)? | E53: NR-37 | F53: SEGURANÇA E SAÚDE EM PLATAFORMAS DE PETRÓLEO. | G53: Item 37.25.5 | H53: ATIVIDADES OFFSHORE - COMBATE E PREVENÇÃO A INCÊNDIOS (GERAL) | I53: Conforme | J53: Treinamento de CACI _x000D_ Sistema: SIRH_x000D_ _x000D_ _x000D_ Walcy Borges- SESM | K53: Treinamento de CACI | L53: SIRH | M53: Treinamento de CACI | N53: SIRH | O53: Gerir Prontidão, Emergência e Contingência | P53: Respondida | Q53: Respondida | R53: Walcy Borges- SESM | S53: 8/5/2025 | T53: 46050 | W53: FALSE | Y53: =VLOOKUP($B53,'Rascunho - PRI'!B52:X654,23,FALSE) -> 0 | Z53: =VLOOKUP($B53,'Rascunho - PRI'!B52:X654,23,FALSE) -> 0
B54: 80585 | D54: As plataformas são dotadas de sistemas de combate a incêndio, com água pressurizada, que assegure a resposta à emergência em tempo suficiente para preservar a segurança dos trabalhadores? NOTA: As especificações das bombas, redes, tomadas de incêndio, mangueiras e demais acessórios devem atender ao disposto na NORMAM-01/DPC. | E54: NR-37 | F54: SEGURANÇA E SAÚDE EM PLATAFORMAS DE PETRÓLEO. | G54: Item 37.25.6.1 | H54: ATIVIDADES OFFSHORE - COMBATE E PREVENÇÃO A INCÊNDIOS (GERAL) | I54: Conforme | J54: Conforme Safety Plan _x000D_ I-DE-3010.0F-5400-947-EG7-020 (P-74)_x000D_ I-DE-3010.0G-5400-947-RG1-001 (P-75)_x000D_ I-DE-3010.0H-5423-940-EA9-701 (P-76)_x000D_ I-DE-3010.0J-5400-947-RG1-001 (P-77)_x000D_ Sistema: SINDOTEC_x000D_ _x000D_ Walcy Borges- SESM | K54: Conforme Safety Plan I-DE-3010.0F-5400-947-EG7-020 (P-74) I-DE-3010.0G-5400-947-RG1-001 (P-75) I-DE-3010.0H-5423-940-EA9-701 (P-76) I-DE-3010.0J-5400-947-RG1-001 (P-77) | L54: Sindotec | M54: Conforme Safety Plan I-DE-3010.0F-5400-947-EG7-020 (P-74) I-DE-3010.0G-5400-947-RG1-001 (P-75) I-DE-3010.0H-5423-940-EA9-701 (P-76) I-DE-3010.0J-5400-947-RG1-001 (P-77) | N54: Sindotec | O54: Gerir Prontidão, Emergência e Contingência | P54: Respondida | Q54: Respondida | R54: Walcy Borges- SESM | S54: 8/5/2025 | T54: 46050 | W54: FALSE | Y54: =VLOOKUP($B54,'Rascunho - PRI'!B53:X655,23,FALSE) -> 0 | Z54: =VLOOKUP($B54,'Rascunho - PRI'!B53:X655,23,FALSE) -> 0
B55: 107204 | D55: Os simulados de emergências nas áreas de armazenamento de produtos químicos perigos nos armazéns são realizados em intervalos regulares para treinar trabalhadores, envolvendo exercício em primeiros socorros, segurança no resgate, vazamento de produtos químicos, incêndio ou qualquer incidente que possa ter impacto à saúde, à segurança e ao meio ambiente? NOTA: Os intervalos dos exercícios e simulações de emergência devem ser determinados na análise de risco. | E55: ABNT NBR 17160:2024 | F55: Armazenamento seguro de produtos químicos. | G55: Item 7.4.5 | H55: PRODUTOS QUÍMICOS - Utilizar PRODUTOS QUÍMICOS em geral (obrigações gerais) | I55: Conforme | J55: São realizados simulados com frequência, de acordo com cronograma estabelecido, constante no Plano de Resposta a Emergência - PRE das Plataformas, envolvendo exercício em primeiros socorros, segurança no resgate, vazamento de produtos químicos, incêndio ou qualquer incidente que possa ter impacto à saúde, à segurança e ao meio ambiente. Fabio Mota -DXV9 | O55: Gerir Prontidão, Emergência e Contingência | P55: Não Respondida | Q55: Não Respondida | R55: Walcy Borges- SESM | S55: 23/7/2025 | W55: FALSE | Y55: =VLOOKUP($B55,'Rascunho - PRI'!B54:X656,23,FALSE) -> 0 | Z55: =VLOOKUP($B55,'Rascunho - PRI'!B54:X656,23,FALSE) -> 0
B56: 51478 | D56: Os procedimentos para resposta abrangem no mínimo os requisitos do item 18.4.1? | E56: RESOLUÇÃO ANP Nº 41, DE 09 DE OUTUBRO DE 2015 | F56: Aprova o Regulamento Técnico do Sistema de Gerenciamento de Segurança Operacional de Sistemas Submarinos - SGSS. | G56: Anexo Item 18.4.1 | H56: SEGURANÇA OPERACIONAL - Sistemas Submarinos | I56: Conforme | J56: PE-3BUZ-00100 PLANO DE RESPOSTA A EMERGÊNCIAS NAS PLATAFORMAS_x000D_ _x000D_ Sistema: Portal de Gestão / INFOPAE_x000D_ Sandra Nery- LNGH | O56: Gerir Prontidão, Emergência e Contingência | P56: Não Respondida | Q56: Não Respondida | R56: Walcy Borges- SESM | S56: 30/5/2025 | W56: FALSE | Y56: =VLOOKUP($B56,'Rascunho - PRI'!B55:X657,23,FALSE) -> 0 | Z56: =VLOOKUP($B56,'Rascunho - PRI'!B55:X657,23,FALSE) -> 0
B57: 51482 | D57: A força de trabalho recebeu treinamento no procedimento de acordo com a responsabilidade na sistemática de permissão de trabalho? NOTA: Nenhuma atividade que requer permissão de trabalho pode ser executada sem que antes seja aprovada a permissão de trabalho. | E57: RESOLUÇÃO ANP Nº 41, DE 09 DE OUTUBRO DE 2015 | F57: Aprova o Regulamento Técnico do Sistema de Gerenciamento de Segurança Operacional de Sistemas Submarinos - SGSS. | G57: Anexo Item 19.2.3 | H57: SEGURANÇA OPERACIONAL - Sistemas Submarinos | I57: Conforme | J57: Conforme registros disponíveis no sistema._x000D_ _x000D_ Sistema: APLAT_x000D_ Sandra Nery- LNGH | O57: Gerir Prontidão, Emergência e Contingência | P57: Não Respondida | Q57: Não Respondida | R57: Walcy Borges- SESM | S57: 30/5/2025 | W57: FALSE | Y57: =VLOOKUP($B57,'Rascunho - PRI'!B56:X658,23,FALSE) -> 0 | Z57: =VLOOKUP($B57,'Rascunho - PRI'!B56:X658,23,FALSE) -> 0
B58: 51589 | D58: O Operador da Instalação identifica as grandes emergências e os cenários acidentais associados de acordo com os termos da Prática de Gestão no 12 (Identificação e Análise de Riscos), avalia a capacidade de resposta à cada cenário acidental e apresenta as ações efetivas de resposta a emergências? | E58: RESOLUÇÃO ANP Nº 43, DE 06 DE DEZEMBRO DE 2007 | F58: Institui o Regime de Segurança Operacional para as Instalações de Perfuração e Produção de Petróleo e Gás Natural. | G58: Prática de Gestão 14 - Item 14.2.3 | H58: SEGURANÇA OPERACIONAL - Atividade de Operação e Produção Marítima | I58: Conforme | J58: Sim. Conforme os padrões PE-3BUZ-00100 - PLANO DE RESPOSTA A EMERGÊNCIAS NAS PLATAFORMAS, PE-3BUZ-00222 - PEI - PLANO DE EMERGÊNCIA INDIVIDUAL DA PLATAFORMA P-77, PE-3BUZ-00220 - PEI - PLANO DE EMERGÊNCIA INDIVIDUAL DA PLATAFORMA P-75, PE-3BUZ-00219 - PEI - PLANO DE EMERGÊNCIA INDIVIDUAL DA PLATAFORMA P-74 e PE-3BUZ-00221 - PEI - PLANO DE EMERGÊNCIA INDIVIDUAL DA PLATAFORMA P-76._x000D_ Fabio Mota- DXV9 | O58: Gerir Prontidão, Emergência e Contingência | P58: Não Respondida | Q58: Não Respondida | R58: Walcy Borges- SESM | S58: 23/5/2025 | W58: FALSE | Y58: =VLOOKUP($B58,'Rascunho - PRI'!B57:X659,23,FALSE) -> 0 | Z58: =VLOOKUP($B58,'Rascunho - PRI'!B57:X659,23,FALSE) -> 0
B59: 51627 | D59: O Operador da Instalação identifica todos os recursos de resposta, incluindo os sistemas e equipamentos de emergência, bem como as empresas contratadas prestadoras de serviços de apoio na resposta a emergência, certificando-se de sua adequação e disponibilidade? | E59: RESOLUÇÃO ANP Nº 43, DE 06 DE DEZEMBRO DE 2007 | F59: Institui o Regime de Segurança Operacional para as Instalações de Perfuração e Produção de Petróleo e Gás Natural. | G59: Prática de Gestão 14 - Item 14.4 | H59: SEGURANÇA OPERACIONAL - Atividade de Operação e Produção Marítima | I59: Conforme | J59: Sim, os recursos são definidos conforme o padrão - PE-3BUZ-00100 - PLANO DE RESPOSTA A EMERGÊNCIAS NAS PLATAFORMAS disponível no portal de gestão. Fabio Mota- DXV9 | O59: Gerir Prontidão, Emergência e Contingência | P59: Não Respondida | Q59: Não Respondida | R59: Walcy Borges- SESM | S59: 23/5/2025 | W59: FALSE | Y59: =VLOOKUP($B59,'Rascunho - PRI'!B58:X660,23,FALSE) -> 0 | Z59: =VLOOKUP($B59,'Rascunho - PRI'!B58:X660,23,FALSE) -> 0
B60: 51656 | D60: O Operador do Contrato garante a proteção da vida humana, do meio ambiente, do patrimônio e o atendimento às exigências legais nos eventos de emergência de controle de poço e estabelece, documenta e implementa plano de resposta à emergência para controle de poço? | E60: RESOLUÇÃO ANP Nº 46, DE 01 DE NOVEMBRO DE 2016 | F60: Aprova o Regime de Segurança Operacional para Integridade de Poços de Petróleo e Gás Natural, que estabelece os requisitos de segurança operacional e de preservação do meio ambiente para perfuração, completação, avaliação, intervenção, produção e abandono de poços de petróleo e gás natural. | G60: Item 14.1, 14.2 e 14.3 | H60: SEGURANÇA OPERACIONAL - Integridade de Poços | I60: Conforme | J60: "PE-2POC-00811 - PRE POCOS - PLANO DE RESPOSTA A EMERGÊNCIAS_x000D_ _x000D_ PE-1PBR-00032 - PLANO DE ATENDIMENTO AO BLOWOUT NO MAR_x000D_ _x000D_ PE-2SMS-00074 GERIR TREINAMENTOS DE CONTINGÊNCIA E SIMULADOS NO E&P_x000D_ _x000D_ Sistema: Portal de Gestão / INFOPAE_x000D_ _x000D_ Atendido através do padrões:PE-3BUZ-00100 - PLANO DE RESPOSTA A EMERGÊNCIAS NAS PLATAFORMAS, PE-3BUZ-00219 - PEI- PLANO DE EMERGÊNCIA INDIVIDUAL DA PLATAFORMA P-74, PE-3BUZ-00220 - PEI- PLANO DE EMERGÊNCIA INDIVIDUAL DA PLATAFORMA P-75, PE-3BUZ-00221 - PEI- PLANO DE EMERGÊNCIA INDIVIDUAL DA PLATAFORMA P-76, PE-3BUZ-00222 - PEI- PLANO DE EMERGÊNCIA INDIVIDUAL DA PLATAFORMA P-77 e PE-2POC-00811- PRE POÇOS - PLANO DE RESPOSTA A EMERGÊNCIAS."_x000D_ Sandra Nery- LNGH | O60: Gerir Prontidão, Emergência e Contingência | P60: Não Respondida | Q60: Não Respondida | R60: Walcy Borges- SESM | S60: 30/5/2025 | W60: FALSE | Y60: =VLOOKUP($B60,'Rascunho - PRI'!B59:X661,23,FALSE) -> 0 | Z60: =VLOOKUP($B60,'Rascunho - PRI'!B59:X661,23,FALSE) -> 0
B61: 51668 | D61: Operador do Contrato programa periodicamente exercícios simulados dos cenários previstos no Plano de Resposta à Emergência para controle de poço envolvendo toda a Força de Trabalho pertinente? | E61: RESOLUÇÃO ANP Nº 46, DE 01 DE NOVEMBRO DE 2016 | F61: Aprova o Regime de Segurança Operacional para Integridade de Poços de Petróleo e Gás Natural, que estabelece os requisitos de segurança operacional e de preservação do meio ambiente para perfuração, completação, avaliação, intervenção, produção e abandono de poços de petróleo e gás natural. | G61: Item 14.1, 14.2 e 14.3 | H61: SEGURANÇA OPERACIONAL - Integridade de Poços | I61: Conforme | J61: "_x000D_ _x000D_ PE-2SMS-00074 GERIR TREINAMENTOS DE CONTINGÊNCIA E SIMULADOS NO E&P _x000D_ _x000D_ PE-2POC-00821 - EXERCICIOS SIMULADOS DO PRE POÇOS._x000D_ _x000D_ Sistema: Portal de Gestão_x000D_ _x000D_ Evidenciado durante a VCL o cronograma de simulados da UN-BÚZIOS."_x000D_ Sandra Nery- LNGH | O61: Gerir Prontidão, Emergência e Contingência | P61: Não Respondida | Q61: Não Respondida | R61: Walcy Borges- SESM | S61: 30/5/2025 | W61: FALSE | Y61: =VLOOKUP($B61,'Rascunho - PRI'!B60:X662,23,FALSE) -> 0 | Z61: =VLOOKUP($B61,'Rascunho - PRI'!B60:X662,23,FALSE) -> 0
B62: 53690 | D62: 1 - A aplicação de dispersantes químicos em superfície é acompanhada de monitoramento aéreo, com aeronaves ou com veículos aéreos remotamente pilotados e, ainda, de monitoramento marítimo, desde que não comprometa a segurança da tripulação, visando maximizar a efetividade de seu emprego e evitar a contaminação de áreas não afetadas pelo óleo? 2 - O monitoramento aéreo ou marítimo identifica extensão, largura e aspecto das manchas, registrando seu posicionamento em coordenadas geográficas; registra os dados de distância da costa, informando sobre as condições meteorológicas e oceanográficas; e verifica a tendência do deslocamento das manchas visando orientar a aplicação dos dispersantes químicos? | E62: RESOLUÇÃO CONAMA Nº 472, DE 27 DE NOVEMBRO DE 2015 | F62: Dispõe sobre o uso de dispersantes químicos em incidentes de poluição por óleo no mar. | G62: Art. 12 | H62: RECURSOS HÍDRICOS - Controle de poluição por óleo e outras substâncias nocivas/perigosas em águas jurisdicionais brasileiras OFFSHORE | I62: Conforme | J62: Conforme procedimento PE-3UBS-00627 PEVO-BS - PLANO DE EMERGÊNCIA PARA VAZAMENTO DE ÓLEO NA ÁREA GEOGRÁFICA DA BACIA DE SANTOS_x000D_ Sistema: Portal de Gestão_x000D_ _x000D_ Walcy Borges- SESM | K62: Conforme procedimento PE-3UBS-00627 PEVO-BS - PLANO DE EMERGÊNCIA PARA VAZAMENTO DE ÓLEO NA ÁREA GEOGRÁFICA DA BACIA DE SANTOS | L62: Portal de Gestão | M62: Conforme procedimento PE-3UBS-00627 PEVO-BS - PLANO DE EMERGÊNCIA PARA VAZAMENTO DE ÓLEO NA ÁREA GEOGRÁFICA DA BACIA DE SANTOS | N62: Portal de Gestão | O62: Gerir Prontidão, Emergência e Contingência | P62: Respondida | Q62: Respondida | R62: Walcy Borges- SESM | S62: 8/5/2025 | T62: 46050 | W62: FALSE | Y62: =VLOOKUP($B62,'Rascunho - PRI'!B61:X663,23,FALSE) -> 0 | Z62: =VLOOKUP($B62,'Rascunho - PRI'!B61:X663,23,FALSE) -> 0
B63: 80411 | D63: A operadora da instalação capacita os trabalhadores que tiverem suas atribuições alteradas pela revisão do PRE, cumprindo o descrito no Capítulo 37.9 desta NR? | E63: NR-37 | F63: SEGURANÇA E SAÚDE EM PLATAFORMAS DE PETRÓLEO. | G63: Item 37.28.1.1 | H63: ATIVIDADES OFFSHORE - RESPOSTA A EMERGÊNCIA | I63: Conforme | J63: Conforme procedimento PE-2SMS-00074 GERIR TREINAMENTOS DE CONTINGÊNCIA E SIMULADOS NO E&P Sistema: Portal de Gestão Wlcy Borges- SESM | K63: Conforme procedimento PE-2SMS-00074 GERIR TREINAMENTOS DE CONTINGÊNCIA E SIMULADOS NO E&P | L63: Portal de Gestão | M63: Conforme procedimento PE-2SMS-00074 GERIR TREINAMENTOS DE CONTINGÊNCIA E SIMULADOS NO E&P | N63: Portal de Gestão | O63: Gerir Prontidão, Emergência e Contingência | P63: Respondida | Q63: Respondida | R63: Walcy Borges- SESM | S63: 8/5/2025 | T63: 46050 | W63: FALSE | Y63: =VLOOKUP($B63,'Rascunho - PRI'!B62:X664,23,FALSE) -> 0 | Z63: =VLOOKUP($B63,'Rascunho - PRI'!B62:X664,23,FALSE) -> 0
B64: 80496 | D64: As botoeiras de acionamento do alarme de incêndio são do tipo "Quebre o vidro e aperte o botão" ou sistema similar, ambos sinalizados na cor vermelha? | E64: NR-37 | F64: SEGURANÇA E SAÚDE EM PLATAFORMAS DE PETRÓLEO. | G64: Item 37.23.3 | H64: ATIVIDADES OFFSHORE - DETECÇÃO E ALARMES | I64: Conforme | J64: Filosofia de Segurança das Unidades de Búzios _x000D_ Item 9.2 Rotas de Fuga _x000D_ Sistema: Gaudi_x000D_ _x000D_ Walcy Borges: SESM | K64: Filosofia de Segurança das Unidades de Búzios Item 9.2 Rotas de Fuga | L64: Sistema Gaudi | M64: Filosofia de Segurança das Unidades de Búzios Item 9.2 Rotas de Fuga | N64: Sistema Gaudi | O64: Gerir Prontidão, Emergência e Contingência | P64: Respondida | Q64: Respondida | R64: Walcy Borges- SESM | S64: 8/5/2025 | T64: 46050 | W64: FALSE | Y64: =VLOOKUP($B64,'Rascunho - PRI'!B63:X665,23,FALSE) -> 0 | Z64: =VLOOKUP($B64,'Rascunho - PRI'!B63:X665,23,FALSE) -> 0
B65: 80498 | D65: O projeto do sistema de detecção e alarme de incêndio e gases leva em conta o estudo de dispersão de gases e vapores tóxicos ou inflamáveis no meio ambiente laboral, para a seleção do tipo, quantidade, distribuição e sensibilidade dos detectores? NOTA: Em caso da ausência de estudo de dispersão de gases, a operadora da instalação deve adotar a quantidade e o posicionamento de detectores e alarmes previstos em norma técnica nacional ou internacional. | E65: NR-37 | F65: SEGURANÇA E SAÚDE EM PLATAFORMAS DE PETRÓLEO. | G65: Item 37.23.4 | H65: ATIVIDADES OFFSHORE - DETECÇÃO E ALARMES | I65: Conforme | J65: Filosofia de Segurança das Unidades de Búzios_x000D_ Item 4.2.1 Geral _x000D_ Sistema: Gaudi_x000D_ _x000D_ _x000D_ Walcy Borges- SESM | K65: Filosofia de Segurança das Unidades de Búzios Item 4.2.1 Geral | L65: Sistema Gaudi | M65: Filosofia de Segurança das Unidades de Búzios Item 4.2.1 Geral | N65: Sistema Gaudi | O65: Gerir Prontidão, Emergência e Contingência | P65: Respondida | Q65: Respondida | R65: Walcy Borges- SESM | S65: 8/5/2025 | T65: 46050 | W65: FALSE | Y65: =VLOOKUP($B65,'Rascunho - PRI'!B64:X666,23,FALSE) -> 0 | Z65: =VLOOKUP($B65,'Rascunho - PRI'!B64:X666,23,FALSE) -> 0
B66: 92209 | C66: Sim | D66: O Relatório da Inspeção contém os requisitos elencados no Item 5.2.3 da presente Norma Técnica? NOTA: a) nome do cliente e endereço; b) data da inspeção e identificação da empresa executante; c) identificação do extintor de incêndio; d) as condições do ambiente a que está exposto o extintor de incêndio, quando aplicável; e) conferência, por pesagem, da carga de cilindro do extintor incêndio carregado com dióxido de carbono (CO2); f) registros das não conformidades e determinação do nível de manutenção a ser executado no extintor de incêndio. | E66: ABNT NBR 12962:2016 | F66: Extintores de incêndio Inspeção e manutenção. | G66: Item 5.2.3 | H66: INCÊNDIO E EXPLOSÃO / PREVENÇÃO - Obrigações gerais relativas à combate e prevenção a INCÊNDIOS | I66: Conforme | J66: O certificado emitido pela empresa contratada apresenta todos os itens elencados conforme norma. Anexos NM 14338089 / NM 15123793 | K66: O certificado emitido pela empresa contratada apresenta todos os itens elencados conforme norma. | L66: Certificados de Pesagem e Inspeção Anual dos Extintores P-74 = https://petrobrasbr.sharepoint.com/:b:/r/teams/bdoc_20240301023456/Documentos%20Compartilhados/2%20-%20Interna/05%20-%20Equipamentos%20de%20Seguran%C3%A7a/02.%20Controle%20de%20Equipamentos/02.%20Ativo%201/01.%20Plataforma%20P74/02.%20Cilindros%20CO2%2045kg/3.%20Controle%20de%20Certificados/2.%20Pesagem/2025/2025.08.29%20Cert%20REL%2047.2025%20-%20PESAGEM%20DOS%20CILINDROS%20DE%20CO2%20P74.pdf?csf=1&web=1&e=EHwj8V P-75 = https://petrobrasbr.sharepoint.com/:b:/r/teams/bdoc_20240301023456/Documentos%20Compartilhados/2%20-%20Interna/05%20-%20Equipamentos%20de%20Seguran%C3%A7a/02.%20Controle%20de%20Equipamentos/02.%20Ativo%201/02.%20Plataforma%20P75/02.%20Cilindros%20CO2%2045kg/3.%20Controle%20de%20Certificados/2.%20Pesagem/2025/CertificadoP-7505-25_20251007190724.004_X.pdf?csf=1&web=1&e=I4jA7Z P-76 = https://petrobrasbr.sharepoint.com/:b:/r/teams/bdoc_20240301023456/Documentos%20Compartilhados/2%20-%20Interna/05%20-%20Equipamentos%20de%20Seguran%C3%A7a/02.%20Controle%20de%20Equipamentos/02.%20Ativo%201/03.%20Plataforma%20P76/02.%20Cilindros%20CO2%2045kg/3.%20Controle%20de%20Certificados/2.%20Inspe%C3%A7%C3%A3o%20Anual%20e%20Pesagem/2025/Inspe%C3%A7%C3%A3o%20Anual%20e%20Pesagem/Certificado%20de%20Inpe%C3%A7%C3%A3o%20e%20Pesagem%20P-76%20-%2003-2025.pdf?csf=1&web=1&e=0ZNM7R P-77 = https://petrobrasbr.sharepoint.com/:b:/r/teams/bdoc_20240301023456/Documentos%20Compartilhados/2%20-%20Interna/05%20-%20Equipamentos%20de%20Seguran%C3%A7a/02.%20Controle%20de%20Equipamentos/02.%20Ativo%201/04.%20Plataforma%20P77/02.%20Cilindros%20CO2%2045kg/3.%20Controle%20de%20Certificados/2.%20Pesagem/2025/Rel%20055.2025%20Certificado%20de%20Pesagem%2009-2025.pdf?csf=1&web=1&e=WcjFZ9 | O66: Gerir M&I de Equipamentos de Segurança | P66: Respondida | Q66: Respondida | R66: Luciana Santos-URFU | S66: 17/7/2024 | T66: 45952 | V66: Analisado | W66: TRUE | X66: Verificado certificado 2025.08.29 Cert REL 47.2025 - PESAGEM DOS CILINDROS DE CO2 P74 da P-74 | Z66: =VLOOKUP($B66,'Rascunho - PRI'!B65:X667,23,FALSE) -> Verificado certificado 2025.08.29 Cert REL 47.2025 - PESAGEM DOS CILINDROS DE CO2 P74 da P-74
B67: 92285 | C67: Sim | D67: O serviço de inspeção e manutenção é realizado por empresa capacitada? | E67: ABNT NBR 12779:2009 | F67: Mangueira de Incêndio - Inspeção, Manutenção e Cuidados | G67: Item 4.3 | H67: INCÊNDIO E EXPLOSÃO / PREVENÇÃO - Obrigações gerais relativas à combate e prevenção a INCÊNDIOS | I67: Conforme | J67: O serviço de manutenção e inspeção de mangueiras é realizado pela Empresa CM Couto através do contrato 4600675765 | K67: O serviço de manutenção e inspeção de mangueiras é realizado pela Empresa CM Couto através do contrato 4600675765 | L67: Certificados da Mangueiras: P-74 = https://petrobrasbr.sharepoint.com/:f:/r/teams/bdoc_20240301023456/Documentos%20Compartilhados/2%20-%20Interna/05%20-%20Equipamentos%20de%20Seguran%C3%A7a/02.%20Controle%20de%20Equipamentos/02.%20Ativo%201/01.%20Plataforma%20P74/04.%20Arm%C3%A1rio%20de%20Equipamentos%20de%20Combate%20a%20Inc%C3%AAndio/3.%20Controle%20de%20Certificados/1.%20TH%20Teste%20Hidrost%C3%A1tico?csf=1&web=1&e=HAga4G P-75 = https://petrobrasbr.sharepoint.com/:f:/r/teams/bdoc_20240301023456/Documentos%20Compartilhados/2%20-%20Interna/05%20-%20Equipamentos%20de%20Seguran%C3%A7a/02.%20Controle%20de%20Equipamentos/02.%20Ativo%201/02.%20Plataforma%20P75/04.%20Arm%C3%A1rio%20de%20Equipamentos%20de%20Combate%20a%20Inc%C3%AAndio/3.%20Controle%20de%20Certificados/1.%20TH%20Teste%20Hidrost%C3%A1tico?csf=1&web=1&e=VaycSR P-76 = https://petrobrasbr.sharepoint.com/:f:/r/teams/bdoc_20240301023456/Documentos%20Compartilhados/2%20-%20Interna/05%20-%20Equipamentos%20de%20Seguran%C3%A7a/02.%20Controle%20de%20Equipamentos/02.%20Ativo%201/03.%20Plataforma%20P76/04.%20Arm%C3%A1rio%20de%20Equipamentos%20de%20Combate%20a%20Inc%C3%AAndio/3.%20Controle%20de%20Certificados/1.%20TH%20Teste%20Hidrost%C3%A1tico?csf=1&web=1&e=l5kKZl P-77 = https://petrobrasbr.sharepoint.com/:f:/r/teams/bdoc_20240301023456/Documentos%20Compartilhados/2%20-%20Interna/05%20-%20Equipamentos%20de%20Seguran%C3%A7a/02.%20Controle%20de%20Equipamentos/02.%20Ativo%201/04.%20Plataforma%20P77/04.%20Arm%C3%A1rio%20de%20Equipamentos%20de%20Combate%20a%20Inc%C3%AAndio/3.%20Controle%20de%20Certificados/1.%20TH%20Teste%20Hidrost%C3%A1tico?csf=1&web=1&e=ye3mn2 | O67: Gerir M&I de Equipamentos de Segurança | P67: Respondida | Q67: Respondida | R67: Luciana Santos-URFU | S67: 17/7/2024 | T67: 45952 | V67: Analisado | W67: TRUE | X67: Verificado certificado NM 15.799.535 - Certificado 93.819 da P-75. Verificado site CM COUTO | Z67: =VLOOKUP($B67,'Rascunho - PRI'!B66:X668,23,FALSE) -> Verificado certificado NM 15.799.535 - Certificado 93.819 da P-75. Verificado site CM COUTO
B68: 54586 | D68: É realizada a inspeção da mangueira de incêndio a cada 6 meses e a manutenção a cada 12 meses? | E68: ABNT NBR 12779:2009 | F68: Mangueira de Incêndio - Inspeção, Manutenção e Cuidados | G68: Item 4.1 | H68: INCÊNDIO E EXPLOSÃO / PREVENÇÃO - Obrigações gerais relativas à combate e prevenção a INCÊNDIOS | I68: Conforme | J68: As inspeções são realizadas pelos Técnicos de segurança mensalmente de acordo com o padrão PE-3BUZ-00115 S e o TH é realizado por empresa contratada - CM Couto contrato 4600675765. Luciana Santos-URFU | K68: As inspeções são realizadas pelos Técnicos de segurança mensalmente de acordo com o padrão PE-3BUZ-00115 (INSPEÇÕES DE SEGURANÇA NAS PLATAFORMAS DE BÚZIOS) e o TH é realizado anualmente por empresa contratada - CM Couto contrato 4600675765 | L68: Certificados da Mangueiras: P-74 = https://petrobrasbr.sharepoint.com/:f:/r/teams/bdoc_20240301023456/Documentos%20Compartilhados/2%20-%20Interna/05%20-%20Equipamentos%20de%20Seguran%C3%A7a/02.%20Controle%20de%20Equipamentos/02.%20Ativo%201/01.%20Plataforma%20P74/04.%20Arm%C3%A1rio%20de%20Equipamentos%20de%20Combate%20a%20Inc%C3%AAndio/3.%20Controle%20de%20Certificados/1.%20TH%20Teste%20Hidrost%C3%A1tico?csf=1&web=1&e=HAga4G P-75 = https://petrobrasbr.sharepoint.com/:f:/r/teams/bdoc_20240301023456/Documentos%20Compartilhados/2%20-%20Interna/05%20-%20Equipamentos%20de%20Seguran%C3%A7a/02.%20Controle%20de%20Equipamentos/02.%20Ativo%201/02.%20Plataforma%20P75/04.%20Arm%C3%A1rio%20de%20Equipamentos%20de%20Combate%20a%20Inc%C3%AAndio/3.%20Controle%20de%20Certificados/1.%20TH%20Teste%20Hidrost%C3%A1tico?csf=1&web=1&e=VaycSR P-76 = https://petrobrasbr.sharepoint.com/:f:/r/teams/bdoc_20240301023456/Documentos%20Compartilhados/2%20-%20Interna/05%20-%20Equipamentos%20de%20Seguran%C3%A7a/02.%20Controle%20de%20Equipamentos/02.%20Ativo%201/03.%20Plataforma%20P76/04.%20Arm%C3%A1rio%20de%20Equipamentos%20de%20Combate%20a%20Inc%C3%AAndio/3.%20Controle%20de%20Certificados/1.%20TH%20Teste%20Hidrost%C3%A1tico?csf=1&web=1&e=l5kKZl P-77 = https://petrobrasbr.sharepoint.com/:f:/r/teams/bdoc_20240301023456/Documentos%20Compartilhados/2%20-%20Interna/05%20-%20Equipamentos%20de%20Seguran%C3%A7a/02.%20Controle%20de%20Equipamentos/02.%20Ativo%201/04.%20Plataforma%20P77/04.%20Arm%C3%A1rio%20de%20Equipamentos%20de%20Combate%20a%20Inc%C3%AAndio/3.%20Controle%20de%20Certificados/1.%20TH%20Teste%20Hidrost%C3%A1tico?csf=1&web=1&e=ye3mn2 | O68: Gerir M&I de Equipamentos de Segurança | P68: Respondida | Q68: Respondida | R68: Luciana Santos-URFU | S68: 13/6/2025 | W68: FALSE | Z68: =VLOOKUP($B68,'Rascunho - PRI'!B67:X669,23,FALSE) -> Apesar do Padrão citado falar da periodicidade das inspeções, em seu item 3.3.1 Inspeção de equipamentos - São inspeções detectivas realizadas em equipamentos de segurança e combate a incêndio, fixos e portáteis da Unidade Marítima sob responsabilidade do Profissional de Segurança de bordo.
B69: 80589 | D69: Os serviços de inspeção e manutenção de primeiro, segundo e terceiro níveis de extintores de incêndio são realizados conforme requisitos do INMETRO? NOTA: O extintor de incêndio que for retirado para manutenção deve ser substituído, no ato da sua retirada, por outro extintor de características idênticas ou superiores. | E69: NR-37 | F69: SEGURANÇA E SAÚDE EM PLATAFORMAS DE PETRÓLEO. | G69: Item 37.25.7.5.1 | H69: ATIVIDADES OFFSHORE - COMBATE E PREVENÇÃO A INCÊNDIOS (GERAL) | I69: Conforme | J69: Inspeções de primeiro nível são realizadas pelos técnicos de segurança offshore conforme padrão PE-3BUZ-00115; Inspeções de segundo e terceiro nível são realizadas por empresa especializada. Búzios utiliza extintores tipo pó ABC com validade de 5 anos inspecionados anualmente de modo a garantir sua validade. Extintores que apresentam desvios são subtituídos imediatamente por outro disponível em reserva técnica da unidade. Luciana Santos - URFU | K69: Inspeções de primeiro nível são realizadas pelos técnicos de segurança offshore conforme padrão PE-3BUZ-00115; Inspeções de segundo e terceiro nível são realizadas por empresa especializada. Búzios utiliza extintores tipo pó ABC com validade de 5 anos inspecionados anualmente, por empresa contratada e certificada por INmetro, de modo a garantir sua validade. Extintores que apresentam desvios são subtituídos imediatamente por outro disponível em reserva técnica da unidade. | O69: Gerir M&I de Equipamentos de Segurança | P69: Respondida | Q69: Respondida | R69: Luciana Santos-URFU | S69: 3/6/2025 | W69: FALSE | Z69: =VLOOKUP($B69,'Rascunho - PRI'!B68:X670,23,FALSE) -> Responsabilidade e comprovação in loco. 3.2.2 Compete à BUZ/SMS/SMS-ATP-BUZ e BUZ/SMS/SMS-ATP-BUZ-II realizar as inspeções, registrar e tratar os desvios identificados sob sua responsabilidade nas rotas de inspeção de equipamentos e de áreas.
B70: 81682 | D70: A empresa realiza o ensaio hidrostático em um intervalo máximo de 5 anos (manutenção 3º nível) nos recipientes, cilindros e ampolas de seus extintores de incêndio, devendo, no entanto, ser realizado o ensaio imediatamente nas hipóteses listadas no Item 6.2.4.3, sendo emitido relatório nos termos do Item 6.2.4.13? NOTA 1: Observar os procedimentos constantes nos Itens 6.2.4.1 e 6.2.4.2 durante a realização da manutenção de 3º nível. NOTA 2: Quando o extintor de incêndio for identificado como de aplicação marítima, o intervalo máximo para submissão ao ensaio hidrostático será o especificado na norma ABNT NBR 12274. Porém, os recipientes, cilindros e ampolas devem ser submetidos imediatamente a este ensaio quando o extintor apresentar qualquer uma das situações descritas no Item 6.2.4.3. | E70: PORTARIA INMETRO Nº 58, DE 16 DE FEVEREIRO DE 2022 | F70: Aprova o Regulamento Técnico da Qualidade e os Requisitos de Avaliação da Conformidade para a Inspeção Técnica e Manutenção de Extintores de Incêndio - Consolidado. | G70: Anexo I, Item 6.2.4.3 | H70: INCÊNDIO E EXPLOSÃO / PREVENÇÃO - Obrigações gerais relativas à combate e prevenção a INCÊNDIOS | I70: Conforme | J70: Sim. Evidência 6 | K70: Validar com Sandra resposta De acordo com a IMO-MSC1: Circular 1432 de 31 de maio de 2012, o ensaio hidrostático (TH) pode ser realizado a cada 10 anos, de acordo com as inspeções anuais IMO= Internancional, de acordo com as bandeiras das Plataformas INMETRO = Nacional A circular da IMO somente é válida se as inspeções forem realizadas anualmente. A periodicidade de ensaio foi alterada em 2024, conforme consultoria/ estudo técnico realizado com Tantalo de Oliveira Campos | O70: Gerir M&I de Equipamentos de Segurança | P70: Respondida | Q70: Respondida | R70: Luciana Santos-URFU | S70: 18/5/2023 | T70: 45952 | V70: Validar com Sandra | W70: FALSE | Z70: =VLOOKUP($B70,'Rascunho - PRI'!B69:X671,23,FALSE) -> 0
B71: 92207 | C71: Sim | D71: Na Inspeção são verificadas as obrigações listadas no Item 5.2.1 da presente Norma Técnica, sendo as mesmas realizada na periodicidade de 6 meses para extintores de incêndio com carga de CO2 (Dióxido de Carbono), cilindros para o gás expelente e extintores de pressurização indireta (ampola) e 12 meses para os demais extintores? | E71: ABNT NBR 12962:2016 | F71: Extintores de incêndio Inspeção e manutenção. | G71: Item 5.2.1 e 5.2.4 | H71: INCÊNDIO E EXPLOSÃO / PREVENÇÃO - Obrigações gerais relativas à combate e prevenção a INCÊNDIOS | I71: Conforme | J71: As inspeções em extintores de CO2 estão sendo feitas dentro do prazo de 6 meses conforme as evidências em anexo: NM 14338089 / NM 15123793. | K71: As inspeções em extintores de CO2 estão sendo feitas dentro do prazo estipulado pela norma | L71: Certificados de Pesagem e Inspeção Anual dos Extintores P-74 = https://petrobrasbr.sharepoint.com/:f:/r/teams/bdoc_20240301023456/Documentos%20Compartilhados/2%20-%20Interna/05%20-%20Equipamentos%20de%20Seguran%C3%A7a/02.%20Controle%20de%20Equipamentos/02.%20Ativo%201/01.%20Plataforma%20P74/02.%20Cilindros%20CO2%2045kg/3.%20Controle%20de%20Certificados/2.%20Pesagem?csf=1&web=1&e=iEteUT P-75 = https://petrobrasbr.sharepoint.com/:f:/r/teams/bdoc_20240301023456/Documentos%20Compartilhados/2%20-%20Interna/05%20-%20Equipamentos%20de%20Seguran%C3%A7a/02.%20Controle%20de%20Equipamentos/02.%20Ativo%201/02.%20Plataforma%20P75/02.%20Cilindros%20CO2%2045kg/3.%20Controle%20de%20Certificados/2.%20Pesagem?csf=1&web=1&e=h5NkLY P-76 = https://petrobrasbr.sharepoint.com/:f:/r/teams/bdoc_20240301023456/Documentos%20Compartilhados/2%20-%20Interna/05%20-%20Equipamentos%20de%20Seguran%C3%A7a/02.%20Controle%20de%20Equipamentos/02.%20Ativo%201/03.%20Plataforma%20P76/02.%20Cilindros%20CO2%2045kg/3.%20Controle%20de%20Certificados/2.%20Inspe%C3%A7%C3%A3o%20Anual%20e%20Pesagem?csf=1&web=1&e=RWDe2U P-77 = https://petrobrasbr.sharepoint.com/:f:/r/teams/bdoc_20240301023456/Documentos%20Compartilhados/2%20-%20Interna/05%20-%20Equipamentos%20de%20Seguran%C3%A7a/02.%20Controle%20de%20Equipamentos/02.%20Ativo%201/04.%20Plataforma%20P77/02.%20Cilindros%20CO2%2045kg/3.%20Controle%20de%20Certificados/2.%20Pesagem?csf=1&web=1&e=6ZYHfu | O71: Gerir M&I de Equipamentos de Segurança | P71: Respondida | Q71: Respondida | R71: Luciana Santos-URFU | S71: 17/7/2024 | T71: 45952 | V71: Analisado | W71: TRUE | X71: Observados certificados de Inspeção de CO2 da P-74 de 14/02/2025 e 29/08/2025 | Z71: =VLOOKUP($B71,'Rascunho - PRI'!B70:X672,23,FALSE) -> Observados certificados de Inspeção de CO2 da P-74 de 14/02/2025 e 29/08/2025
B72: 80588 | D72: Os extintores de incêndio são certificados pelo INMETRO, possuindo o respectivo selo de marca de conformidade e estão instalados em locais de fácil visualização e acesso? | E72: NR-37 | F72: SEGURANÇA E SAÚDE EM PLATAFORMAS DE PETRÓLEO. | G72: Item 37.25.7.3 e 37.25.7.4 | H72: ATIVIDADES OFFSHORE - COMBATE E PREVENÇÃO A INCÊNDIOS (GERAL) | I72: Conforme | J72: Conforme. Localização, sinalização seguem plano de segurança das unidades.Requisitos dos equipamentos seguem normas.A rotina de inspeção e manutenção periódica é controlada por planilhas sob responsabilidade de Luciana Silva Santos URFU | K72: Sim, os extintores de incêndio são certificados pelo INMETRO | O72: Gerir M&I de Equipamentos de Segurança | P72: Respondida | Q72: Respondida | R72: Luciana Santos-URFU | S72: 14/2/2025 | W72: FALSE | Z72: =VLOOKUP($B72,'Rascunho - PRI'!B71:X673,23,FALSE) -> Responsabilidade e comprovação in loco. 3.2.2 Compete à BUZ/SMS/SMS-ATP-BUZ e BUZ/SMS/SMS-ATP-BUZ-II realizar as inspeções, registrar e tratar os desvios identificados sob sua responsabilidade nas rotas de inspeção de equipamentos e de áreas.
B73: 83756 | D73: Os equipamentos de sondagem inicial e de monitoramento contínuo da atmosfera utilizados nos trabalhos em espaço confinado são calibrados e testados antes do seu uso, e adequados para o trabalho em áreas potencialmente explosivas, caso estas áreas sejam reconhecidas? | E73: ABNT NBR 16577:2017 Versão Corrigida:2017 | F73: Espaço confinado - Prevenção de acidentes, procedimentos e medidas de proteção. | G73: Item 6.2.1.1 | H73: ESPAÇOS CONFINADOS - Executar ou fiscalizar atividades em espaços confinados | I73: Conforme | J73: "Nas unidades de Búzios é realizado bump teste do equipamento antes do início da atividade conforme item 3.8.5.5 do MS, indicado no padrão PE-1PBR-00874 Evidência: Dados extraído da estação de teste e resposta disponível nas unidade de Búzios (data log), link: https://petrobrasbr.sharepoint.com/:f:/r/teams/bdoc_20240306071106/Documentos%20Compartilhados/2%20-%20Interna%20(NP-2)/18%20-%20Datalog_Detectores?csf=1&web=1&e=sJ9dsN " Luciana Santos- URFU | K73: Nas unidades de Búzios é realizado bump teste do equipamento antes do início da atividade conforme item 3.8.5.5 do MS, indicado no padrão PE-1PBR-00874 | L73: Verificar link do data log dos detectores com Josias | O73: Gerir M&I de Equipamentos de Segurança | P73: Não Respondida | Q73: Não Respondida | R73: Luciana Santos-URFU | S73: 6/5/2025 | W73: FALSE | Y73: =VLOOKUP($B73,'Rascunho - PRI'!B72:X674,23,FALSE) -> 0 | Z73: =VLOOKUP($B73,'Rascunho - PRI'!B72:X674,23,FALSE) -> 0
B74: 82286 | C74: Sim | D74: Os extintores de incêndio da empresa possuem certificação compulsória, realizada por Organismo de Certificação de Produto - OCP acreditado pelo INMETRO, no âmbito do Sistema Brasileiro de Avaliação da Conformidade - SBAC? | E74: PORTARIA INMETRO Nº 108, DE 17 DE MARÇO DE 2022 | F74: Aprova os Requisitos de Avaliação da Conformidade para Extintores de Incêndio - Consolidado. | G74: Art. 6º | H74: INCÊNDIO E EXPLOSÃO / PREVENÇÃO - Obrigações gerais relativas à combate e prevenção a INCÊNDIOS | I74: Conforme | J74: Os extintores de incêndios são adquiridos e mantidos por empresas credenciadas no INMETRO | K74: Os extintores de incêndios são adquiridos e mantidos por empresas credenciadas no INMETRO | O74: Gerir M&I de Equipamentos de Segurança | P74: Respondida | Q74: Respondida | R74: Luciana Santos-URFU | S74: 26/3/2023 | T74: 45952 | V74: Analisado | W74: FALSE | X74: Sem evidências | Z74: =VLOOKUP($B74,'Rascunho - PRI'!B73:X675,23,FALSE) -> Sem evidências
B75: 83790 | D75: O detector do tipo multigás convencional (denominado "multigás) utilizado nos trabalhos em espaço confinado monitora quatro variáveis, (conforme sua configuração), como: concentração de oxigênio (O2); limite inferior de explosividade (LIE) ou lower explosive limit (LEL) para gases e vapores combustíveis ou inflamáveis; concentração de monóxido de carbono (CO); e concentração de gás sulfídrico ou sulfeto de hidrogênio (H2S)? NOTA: Para qualquer outro tipo de gás, que seja identificado no ambiente perigoso, sensores dedicados devem ser configurados de forma complementar ou com o uso de instrumento para o gás identificado (detector do tipo monogás). | E75: ABNT NBR 16577:2017 Versão Corrigida:2017 | F75: Espaço confinado - Prevenção de acidentes, procedimentos e medidas de proteção. | G75: Item 6.2.1.3 | H75: ESPAÇOS CONFINADOS - Executar ou fiscalizar atividades em espaços confinados | I75: Conforme | J75: "Há equipamentos do tipo multigás com bomba ativa em conformidade com a aferição da quatro variáveis como: Concentração de oxigênio (O2); limite inferior de explosividade (LIE) ou lower explosive limit (LEL) para gases e vapores combustíveis ou inflamáveis; concentração de monóxido de carbono (CO); e concentração de gás sulfídrico ou sulfeto de hidrogênio (H2S) Evidência: Manual do equipamento usado e EC nas unidades de Búzios. Link: https://petrobrasbr.sharepoint.com/:b:/r/teams/bdoc_20240301023456/Documentos%20Compartilhados/2%20-%20Interna/05%20-%20Equipamentos%20de%20Seguran%C3%A7a/02.%20Controle%20de%20Equipamentos/05.%20Base/07.%20Detectores%20de%20G%C3%A1s/03%20-%20Instru%C3%A7%C3%B5es,%20passso%20a%20passo,%20manuais,%20treinamento%20e%20reuni%C3%A3o%20de%20instru%C3%A7%C3%A3o/01%20-%20MMG/Guias%20e%20manuais-%20Equipamentos%20MMG%20-%207004292512/Item%2010%20-%20GasAlertMax%20XT%20II%20-%20Manual.pdf?csf=1&web=1&e=HAzYBR" Luciana Santos- URFU | K75: Há equipamentos do tipo multigás com bomba ativa em conformidade com a aferição de cinco variáveis como: Concentração de oxigênio (O2); limite inferior de explosividade (LIE) ou lower explosive limit (LEL) para gases e vapores combustíveis ou inflamáveis; concentração de monóxido de carbono (CO); e concentração de gás sulfídrico ou sulfeto de hidrogênio (H2S) | L75: P-74 = https://petrobrasbr.sharepoint.com/:f:/r/teams/bdoc_20240301023456/Documentos%20Compartilhados/2%20-%20Interna/05%20-%20Equipamentos%20de%20Seguran%C3%A7a/02.%20Controle%20de%20Equipamentos/02.%20Ativo%201/01.%20Plataforma%20P74/07.%20Detectores%20de%20G%C3%A1s/3.%20Controle%20de%20Certificados/1.%20Calibra%C3%A7%C3%A3o/Certificado%20dos%20equipamentos%20do%20contrato%20MMG?csf=1&web=1&e=7P2UPk P-75 = https://petrobrasbr.sharepoint.com/:f:/r/teams/bdoc_20240301023456/Documentos%20Compartilhados/2%20-%20Interna/05%20-%20Equipamentos%20de%20Seguran%C3%A7a/02.%20Controle%20de%20Equipamentos/02.%20Ativo%201/02.%20Plataforma%20P75/07.%20Detectores%20de%20G%C3%A1s/3.%20Controle%20de%20Certificados/1.%20Calibra%C3%A7%C3%A3o/Certificados%20Detectores%20Alugados%20(MMG)?csf=1&web=1&e=jCXPl7 P-76 = https://petrobrasbr.sharepoint.com/:f:/r/teams/bdoc_20240301023456/Documentos%20Compartilhados/2%20-%20Interna/05%20-%20Equipamentos%20de%20Seguran%C3%A7a/02.%20Controle%20de%20Equipamentos/02.%20Ativo%201/02.%20Plataforma%20P75/07.%20Detectores%20de%20G%C3%A1s/3.%20Controle%20de%20Certificados/1.%20Calibra%C3%A7%C3%A3o/Certificados%20Detectores%20Alugados%20(MMG)?csf=1&web=1&e=jCXPl7 P-77 = https://petrobrasbr.sharepoint.com/:f:/r/teams/bdoc_20240301023456/Documentos%20Compartilhados/2%20-%20Interna/05%20-%20Equipamentos%20de%20Seguran%C3%A7a/02.%20Controle%20de%20Equipamentos/02.%20Ativo%201/02.%20Plataforma%20P75/07.%20Detectores%20de%20G%C3%A1s/3.%20Controle%20de%20Certificados/1.%20Calibra%C3%A7%C3%A3o/Certificados%20Detectores%20Alugados%20(MMG)?csf=1&web=1&e=jCXPl7 | O75: Gerir M&I de Equipamentos de Segurança | P75: Respondida | Q75: Respondida | R75: Luciana Santos-URFU | S75: 6/5/2025 | W75: FALSE | Z75: =VLOOKUP($B75,'Rascunho - PRI'!B74:X676,23,FALSE) -> Procede conforme ABNT no item 6.2.1.3 O detector do tipo multigás convencional (denominado “multigás”) monitora quatro variáveis, (conforme sua configuração), como: concentração de oxigênio (O2); limite inferior de explosividade (LIE) ou lower explosive limit (LEL) para gases e vapores combustíveis ou inflamáveis; concentração de monóxido de carbono (CO); e concentração de gás sulfídrico ou sulfeto de hidrogênio (H2S). Para qualquer outro tipo de gás, que seja identificado no ambiente perigoso, sensores dedicados devem ser configurados de forma complementar ou com o uso de instrumento para o gás identificado (detector do tipo monogás).
B76: 81681 | C76: Sim | D76: A empresa realiza a manutenção de 2º nível em seus extintores de incêndio a cada 12 meses, sendo observados os procedimentos constantes do Item 6.2.3.4 e realizada a emissão de relatório contemplando as informações constantes do Item 6.2.3.9? NOTA 1: Quando o extintor de incêndio for afetado pela submissão a condições adversas ou severas ou, ainda, for indicado por uma inspeção técnica, esse intervalo de manutenção pode ser reduzido. NOTA 2: A primeira manutenção de 2º nível deverá ser executada após 12 meses da data de sua fabricação ou ao final da garantia/prazo de validade para a primeira manutenção dada pelo fabricante. A qualquer tempo, caso haja perda superior a 10 % da carga nominal declarada ou caso a pressão interna do extintor esteja fora da faixa de operação, a manutenção de 2º nível deve ser efetuada. NOTA 3: A partir da primeira manutenção de 2º nível, fica a critério e responsabilidade do fornecedor a realização da manutenção de 2º nível nos extintores de incêndio de dióxido de carbono (CO2) num prazo maior do que 12 meses, nesse caso, deverá sem mantido o Anel de Identificação da Manutenção e o Selo de Identificação da Conformidade da manutenção de 2º ou 3º nível anterior, sendo reavaliada a garantia do serviço pela fixação de uma nova Etiqueta de Garantia Autoadesiva. | E76: PORTARIA INMETRO Nº 58, DE 16 DE FEVEREIRO DE 2022 | F76: Aprova o Regulamento Técnico da Qualidade e os Requisitos de Avaliação da Conformidade para a Inspeção Técnica e Manutenção de Extintores de Incêndio - Consolidado. | G76: Anexo I, Item 6.2.3.1 | H76: INCÊNDIO E EXPLOSÃO / PREVENÇÃO - Obrigações gerais relativas à combate e prevenção a INCÊNDIOS | I76: Conforme | J76: 1- Sim. Nos relatórios emitidos pela contratada. (Evidencia 1) | K76: Sim, a manutenção de 2º nível é realizada de acordo com a periodicidade determinada pela portaria | L76: Extintores Heliponto: P-74 = https://petrobrasbr.sharepoint.com/:f:/r/teams/bdoc_20240301023456/Documentos%20Compartilhados/2%20-%20Interna/05%20-%20Equipamentos%20de%20Seguran%C3%A7a/02.%20Controle%20de%20Equipamentos/02.%20Ativo%201/01.%20Plataforma%20P74/01.%20Extintores%20Port%C3%A1teis/3.%20Controle%20de%20Certificados/2.%20TH%20Teste%20Hidrost%C3%A1tico?csf=1&web=1&e=hkseMux P-75 = https://petrobrasbr.sharepoint.com/:f:/r/teams/bdoc_20240301023456/Documentos%20Compartilhados/2%20-%20Interna/05%20-%20Equipamentos%20de%20Seguran%C3%A7a/02.%20Controle%20de%20Equipamentos/02.%20Ativo%201/02.%20Plataforma%20P75/01.%20Extintores%20Port%C3%A1teis/3.%20Controle%20de%20Certificados/2.%20TH%20Teste%20Hidrost%C3%A1tico%20e%20recarga?csf=1&web=1&e=Egsq4D P-76 = https://petrobrasbr.sharepoint.com/:f:/r/teams/bdoc_20240301023456/Documentos%20Compartilhados/2%20-%20Interna/05%20-%20Equipamentos%20de%20Seguran%C3%A7a/02.%20Controle%20de%20Equipamentos/02.%20Ativo%201/03.%20Plataforma%20P76/01.%20Extintores%20Port%C3%A1teis/3.%20Controle%20de%20Certificados/2.%20TH%20Teste%20Hidrost%C3%A1tico?csf=1&web=1&e=i28Owk P-77 = https://petrobrasbr.sharepoint.com/:f:/r/teams/bdoc_20240301023456/Documentos%20Compartilhados/2%20-%20Interna/05%20-%20Equipamentos%20de%20Seguran%C3%A7a/02.%20Controle%20de%20Equipamentos/02.%20Ativo%201/04.%20Plataforma%20P77/01.%20Extintores%20Port%C3%A1teis/3.%20Controle%20de%20Certificados/2.%20TH%20Teste%20Hidrost%C3%A1tico?csf=1&web=1&e=2osEgD | O76: Gerir M&I de Equipamentos de Segurança | P76: Respondida | Q76: Respondida | R76: Luciana Santos-URFU | S76: 18/5/2023 | T76: 45952 | V76: Analisado | W76: FALSE | X76: Observados certificados da P-76 Verificado que os certificados são datados apenas com mês/ano Verificado que no certificado de 2025, os extintores com selo 315659522 e 315659523 fabricados em 2023 e 2022, respectivamente, só possuíam o certificado 2025 | Z76: =VLOOKUP($B76,'Rascunho - PRI'!B75:X677,23,FALSE) -> Observados certificados da P-76 Verificado que os certificados são datados apenas com mês/ano Verificado que no certificado de 2025, os extintores com selo 315659522 e 315659523 fabricados em 2023 e 2022, respectivamente, só possuíam o certificado 2025
B77: 83788 | D77: Os equipamentos utilizados para avaliações atmosféricas nos trabalhos em espaço confinado atendem as obrigações listadas abaixo? a) atender o disposto nas normas técnicas nacionais ou, na sua ausência, normas técnicas internacionais aplicáveis; b) efetuar leitura instantânea; c) ser intrinsecamente seguro, d) ser protegido contra interferências eletromagnéticas de radiofrequência, devendo suportar campo de 10 V/m (dez Volts por metro); e) possuir alarme sonoro, visual e vibratório, acionados simultaneamente; f) possuir grau de proteção contra o ingresso de poeira e água adequado; e g) possuir manual em português. | E77: NR-33 | F77: SEGURANÇA E SAÚDE NO TRABALHO EM ESPAÇOS CONFINADO. | G77: Item 33.5.15.4 | H77: ESPAÇOS CONFINADOS - Executar ou fiscalizar atividades em espaços confinados | I77: Conforme | J77: " Os equipamentos disponibilizados para avaliações atmosféricas nos trabalhos em espaço confinado nas unidades de Búzios atendem as obrigações questionadas. Segue o link do manual em português evidenciando as obrigações: Link: https://product.rikenkeiki.co.jp/assets/img/products/59/man/%E2%97%8FPT0pt-1191%E3%80%80RX-8000.pdf" Luciana Santos-UFRU | K77: Os equipamentos disponibilizados para avaliações atmosféricas nos trabalhos em espaço confinado nas unidades de Búzios atendem as obrigações questionadas. | L77: Link do manual em português: https://product.rikenkeiki.co.jp/assets/img/products/59/man/%E2%97%8FPT0pt-1191%E3%80%80RX-8000.pdf | O77: Gerir M&I de Equipamentos de Segurança | P77: Respondida | Q77: Respondida | R77: Luciana Santos-URFU | S77: 6/5/2025 | W77: FALSE | Z77: =VLOOKUP($B77,'Rascunho - PRI'!B76:X678,23,FALSE) -> Link validado.
B78: 83789 | D78: Os equipamentos de medição que forem utilizados no interior dos espaços confinados, com risco de explosão, são intrinsecamente seguros (do tipo Ex i) e protegidos contra interferência eletromagnética de radiofrequência? NOTA: Assim como os equipamentos posicionados próximos à parte externa e no entorno dos espaços confinados considerados como áreas classificadas. | E78: ABNT NBR 16577:2017 Versão Corrigida:2017 | F78: Espaço confinado - Prevenção de acidentes, procedimentos e medidas de proteção. | G78: Item 6.2.1.2 | H78: ESPAÇOS CONFINADOS - Executar ou fiscalizar atividades em espaços confinados | I78: Conforme | J78: "Item em conformidade com item d, do anexo H do MS indicado no padrão PE-1PBR-00214 Link: https://rjln202.petrobras.com.br/SINPEP/REST/sinp_ptrl_p.nsf/xp_padrao_portal.xsp?urlpadrao=http%3A%2F%2FRJLN202.petrobras.com.br%2FSINPEP%2FREST%5CPETROBRAS%5CSINP_MODP_R_P_PETROBRAS.NSF&23FB7671AF5BFA188325812B004DADA0". Luciana Santos- UFRU | K78: Sim, conforme padrão PE-1PBR-00214 - MS - TRABALHOS EM ESPAÇO CONFINADO (item d - Anexo H) | O78: Gerir M&I de Equipamentos de Segurança | P78: Respondida | Q78: Respondida | R78: Luciana Santos-URFU | S78: 6/5/2025 | W78: FALSE | Z78: =VLOOKUP($B78,'Rascunho - PRI'!B77:X679,23,FALSE) -> ABNT NBR 16577:2017 procede com as solicitações.
B79: 92325 | C79: Sim | D79: O relatório contém as seguintes informações mínimas: identificação, fabricante, diâmetro, comprimento, tipo, inspeção ou manutenção, data de execução, data da próxima inspeção e/ou manutenção, nome e assinatura do responsável pela inspeção e/ou manutenção e a declaração de conformidade com a presente Norma? | E79: ABNT NBR 12779:2009 | F79: Mangueira de Incêndio - Inspeção, Manutenção e Cuidados | G79: Item 4.8 | H79: INCÊNDIO E EXPLOSÃO / PREVENÇÃO - Obrigações gerais relativas à combate e prevenção a INCÊNDIOS | I79: Conforme | J79: Os certificados de manutenção e inspeção de mangueiras de incêndio estão de acordo com a NBR 12779 conforme anexo ¿ NM 15060093 | K79: Os certificados de manutenção e inspeção de mangueiras de incêndio estão de acordo com a NBR 12779 | L79: Certificados da Mangueiras: P-74 = https://petrobrasbr.sharepoint.com/:f:/r/teams/bdoc_20240301023456/Documentos%20Compartilhados/2%20-%20Interna/05%20-%20Equipamentos%20de%20Seguran%C3%A7a/02.%20Controle%20de%20Equipamentos/02.%20Ativo%201/01.%20Plataforma%20P74/04.%20Arm%C3%A1rio%20de%20Equipamentos%20de%20Combate%20a%20Inc%C3%AAndio/3.%20Controle%20de%20Certificados/1.%20TH%20Teste%20Hidrost%C3%A1tico?csf=1&web=1&e=HAga4G P-75 = https://petrobrasbr.sharepoint.com/:f:/r/teams/bdoc_20240301023456/Documentos%20Compartilhados/2%20-%20Interna/05%20-%20Equipamentos%20de%20Seguran%C3%A7a/02.%20Controle%20de%20Equipamentos/02.%20Ativo%201/02.%20Plataforma%20P75/04.%20Arm%C3%A1rio%20de%20Equipamentos%20de%20Combate%20a%20Inc%C3%AAndio/3.%20Controle%20de%20Certificados/1.%20TH%20Teste%20Hidrost%C3%A1tico?csf=1&web=1&e=VaycSR P-76 = https://petrobrasbr.sharepoint.com/:f:/r/teams/bdoc_20240301023456/Documentos%20Compartilhados/2%20-%20Interna/05%20-%20Equipamentos%20de%20Seguran%C3%A7a/02.%20Controle%20de%20Equipamentos/02.%20Ativo%201/03.%20Plataforma%20P76/04.%20Arm%C3%A1rio%20de%20Equipamentos%20de%20Combate%20a%20Inc%C3%AAndio/3.%20Controle%20de%20Certificados/1.%20TH%20Teste%20Hidrost%C3%A1tico?csf=1&web=1&e=l5kKZl P-77 = https://petrobrasbr.sharepoint.com/:f:/r/teams/bdoc_20240301023456/Documentos%20Compartilhados/2%20-%20Interna/05%20-%20Equipamentos%20de%20Seguran%C3%A7a/02.%20Controle%20de%20Equipamentos/02.%20Ativo%201/04.%20Plataforma%20P77/04.%20Arm%C3%A1rio%20de%20Equipamentos%20de%20Combate%20a%20Inc%C3%AAndio/3.%20Controle%20de%20Certificados/1.%20TH%20Teste%20Hidrost%C3%A1tico?csf=1&web=1&e=ye3mn2 | O79: Gerir M&I de Equipamentos de Segurança | P79: Respondida | Q79: Respondida | R79: Luciana Santos-URFU | S79: 17/7/2024 | T79: 45952 | V79: Analisado | W79: TRUE | X79: Analisado certificado 16193431 2 1.2 GTM 94319 da P-77 | Z79: =VLOOKUP($B79,'Rascunho - PRI'!B78:X680,23,FALSE) -> Analisado certificado 16193431 2 1.2 GTM 94319 da P-77
B80: 80605 | D80: As plataformas são providas de extintores para permitir o combate a incêndio em sua fase inicial? NOTA 1: O número, distribuição, tipo e carga dos extintores devem estar relacionados com a sua capacidade extintora, as classes de fogo possíveis a bordo e o potencial de incêndio na área a ser protegida, conforme a NORMAM-01/DPC, ou, na sua omissão, as normas técnicas nacionais. NOTA 2: O extintor de incêndio sobre rodas só é contabilizado na capacidade extintora quando o seu agente puder atingir a área a ser protegida. | E80: NR-37 | F80: SEGURANÇA E SAÚDE EM PLATAFORMAS DE PETRÓLEO. | G80: Item 37.25.7.1 | H80: ATIVIDADES OFFSHORE - COMBATE E PREVENÇÃO A INCÊNDIOS (GERAL) | I80: Conforme | J80: Sim as plataformas estão providas de extintores para combate a incêndio em sua fase inicial de acordo com o Safety plan de cada unidade.Luciana Santos - URFU | K80: Sim, as plataformas estão providas de extintores para combate a incêndio em sua fase inicial de acordo com o Safety plan de cada unidade. | O80: Gerir M&I de Equipamentos de Segurança | P80: Respondida | Q80: Respondida | R80: Luciana Santos-URFU | S80: 3/6/2025 | W80: FALSE | Z80: =VLOOKUP($B80,'Rascunho - PRI'!B79:X681,23,FALSE) -> Responsabilidade e comprovação in loco. 3.2.2 Compete à BUZ/SMS/SMS-ATP-BUZ e BUZ/SMS/SMS-ATP-BUZ-II realizar as inspeções, registrar e tratar os desvios identificados sob sua responsabilidade nas rotas de inspeção de equipamentos e de áreas.
B81: 82140 | C81: Sim | D81: Os indicadores de pressão para extintores de incêndio possuem possuem Selo de Identificação da Conformidade emitido pelo INMETRO? | E81: PORTARIA INMETRO Nº 109, DE 17 DE MARÇO DE 2022 | F81: Aprova os Requisitos de Avaliação da Conformidade para Indicador de Pressão para Extintores de Incêndio - Consolidado. | G81: Art. 6º | H81: INCÊNDIO E EXPLOSÃO / PREVENÇÃO - Obrigações gerais relativas à combate e prevenção a INCÊNDIOS | I81: Conforme | J81: Todos os indicadores de pressão são fornecidos por empresas credenciadas junto ao INMETRO e atendem tais conformidades. Evidenciado durante a VCL o atendimento a obrigação legal. | K81: Todos os indicadores de pressão são fornecidos por empresas credenciadas junto ao INMETRO e atendem tais conformidades. | O81: Gerir M&I de Equipamentos de Segurança | P81: Respondida | Q81: Respondida | R81: Luciana Santos-URFU | S81: 21/6/2023 | T81: 45952 | V81: Analisado | W81: FALSE | X81: Sem evidências | Z81: =VLOOKUP($B81,'Rascunho - PRI'!B80:X682,23,FALSE) -> Sem evidências
B82: 55342 | D82: A inspeção, que define o nível de manutenção a ser efetuado, é realizada somente por empresa de serviço de inspeção e manutenção de extintor de incêndio, por meio de profissionais capacitados para essa função? | E82: ABNT NBR 12962:2016 | F82: Extintores de incêndio Inspeção e manutenção. | G82: Item 5.2 | H82: INCÊNDIO E EXPLOSÃO / PREVENÇÃO - Obrigações gerais relativas à combate e prevenção a INCÊNDIOS | I82: Conforme | J82: 1- Sim. Nos relatórios emitidos pela contratada. (Evidencia 1) _x000D_ 2- Sim. Através de relátório e planilhas de controle (Evidência 1 e 2)._x000D_ 3- Sim. A não conformidade é evidenciado no Intelatrac e o tratamento é evidenciado no auditor plus._x000D_ 4- Sim. (Evidência 1) | K82: Validar com Sandra resposta São realizadas 2 inspeções: - Anual: por empresa contratada - Mensal: pelos técnicos de segurança | L82: Evidência 1 - Certificados de Pesagem e Inspeção Anual dos Extintores P-74 = https://petrobrasbr.sharepoint.com/:b:/r/teams/bdoc_20240301023456/Documentos%20Compartilhados/2%20-%20Interna/05%20-%20Equipamentos%20de%20Seguran%C3%A7a/02.%20Controle%20de%20Equipamentos/02.%20Ativo%201/01.%20Plataforma%20P74/02.%20Cilindros%20CO2%2045kg/3.%20Controle%20de%20Certificados/2.%20Pesagem/2025/2025.08.29%20Cert%20REL%2047.2025%20-%20PESAGEM%20DOS%20CILINDROS%20DE%20CO2%20P74.pdf?csf=1&web=1&e=EHwj8V P-75 = https://petrobrasbr.sharepoint.com/:b:/r/teams/bdoc_20240301023456/Documentos%20Compartilhados/2%20-%20Interna/05%20-%20Equipamentos%20de%20Seguran%C3%A7a/02.%20Controle%20de%20Equipamentos/02.%20Ativo%201/02.%20Plataforma%20P75/02.%20Cilindros%20CO2%2045kg/3.%20Controle%20de%20Certificados/2.%20Pesagem/2025/CertificadoP-7505-25_20251007190724.004_X.pdf?csf=1&web=1&e=I4jA7Z P-76 = https://petrobrasbr.sharepoint.com/:b:/r/teams/bdoc_20240301023456/Documentos%20Compartilhados/2%20-%20Interna/05%20-%20Equipamentos%20de%20Seguran%C3%A7a/02.%20Controle%20de%20Equipamentos/02.%20Ativo%201/03.%20Plataforma%20P76/02.%20Cilindros%20CO2%2045kg/3.%20Controle%20de%20Certificados/2.%20Inspe%C3%A7%C3%A3o%20Anual%20e%20Pesagem/2025/Inspe%C3%A7%C3%A3o%20Anual%20e%20Pesagem/Certificado%20de%20Inpe%C3%A7%C3%A3o%20e%20Pesagem%20P-76%20-%2003-2025.pdf?csf=1&web=1&e=0ZNM7R P-77 = https://petrobrasbr.sharepoint.com/:b:/r/teams/bdoc_20240301023456/Documentos%20Compartilhados/2%20-%20Interna/05%20-%20Equipamentos%20de%20Seguran%C3%A7a/02.%20Controle%20de%20Equipamentos/02.%20Ativo%201/04.%20Plataforma%20P77/02.%20Cilindros%20CO2%2045kg/3.%20Controle%20de%20Certificados/2.%20Pesagem/2025/Rel%20055.2025%20Certificado%20de%20Pesagem%2009-2025.pdf?csf=1&web=1&e=WcjFZ9 Evidência 2: Check list Mensal P-74 = https://petrobrasbr.sharepoint.com/:f:/r/teams/bdoc_20240301023456/Documentos%20Compartilhados/2%20-%20Interna/05%20-%20Equipamentos%20de%20Seguran%C3%A7a/02.%20Controle%20de%20Equipamentos/02.%20Ativo%201/01.%20Plataforma%20P74/01.%20Extintores%20Port%C3%A1teis/2.%20Evid%C3%AAncias%20de%20inspe%C3%A7%C3%B5es?csf=1&web=1&e=plVrNd P-75 = https://petrobrasbr.sharepoint.com/:f:/r/teams/bdoc_20240301023456/Documentos%20Compartilhados/2%20-%20Interna/05%20-%20Equipamentos%20de%20Seguran%C3%A7a/02.%20Controle%20de%20Equipamentos/02.%20Ativo%201/02.%20Plataforma%20P75/01.%20Extintores%20Port%C3%A1teis/2.%20Evid%C3%AAncias%20de%20inspe%C3%A7%C3%B5es?csf=1&web=1&e=lPQOeE P-76 = https://petrobrasbr.sharepoint.com/:f:/r/teams/bdoc_20240301023456/Documentos%20Compartilhados/2%20-%20Interna/05%20-%20Equipamentos%20de%20Seguran%C3%A7a/02.%20Controle%20de%20Equipamentos/02.%20Ativo%201/03.%20Plataforma%20P76/01.%20Extintores%20Port%C3%A1teis/2.%20Evid%C3%AAncias%20de%20inspe%C3%A7%C3%B5es?csf=1&web=1&e=qoCbrY P-77 = https://petrobrasbr.sharepoint.com/:f:/r/teams/bdoc_20240301023456/Documentos%20Compartilhados/2%20-%20Interna/05%20-%20Equipamentos%20de%20Seguran%C3%A7a/02.%20Controle%20de%20Equipamentos/02.%20Ativo%201/04.%20Plataforma%20P77/01.%20Extintores%20Port%C3%A1teis/2.%20Evid%C3%AAncias%20de%20inspe%C3%A7%C3%B5es?csf=1&web=1&e=Jidrqf | O82: Gerir M&I de Equipamentos de Segurança | P82: Respondida | Q82: Respondida | R82: Luciana Santos-URFU | S82: 18/5/2023 | T82: 45952 | V82: Validar com Sandra | W82: FALSE | Y82: =VLOOKUP($B82,'Rascunho - PRI'!B81:X683,23,FALSE) -> 0 | Z82: =VLOOKUP($B82,'Rascunho - PRI'!B81:X683,23,FALSE) -> 0
B83: 55361 | D83: As manutenções são realizadas somente por profissionais capacitados da empresa de serviços de Inspeção e Manutenção de extintor de incêndio sendo realizada conforme nível de manutenção definido em função da situação encontrada na inspeção técnica de acordo com a Tabela 1 da presente Norma Técnica? | E83: ABNT NBR 12962:2016 | F83: Extintores de incêndio Inspeção e manutenção. | G83: Item 5.3 | H83: INCÊNDIO E EXPLOSÃO / PREVENÇÃO - Obrigações gerais relativas à combate e prevenção a INCÊNDIOS | I83: Conforme | J83: Sim, conforme Avaliação de Conformidade emitida pelo INMETRO para empresa que nos presta serviços de manutenção | K83: Revisar resposta com ponto focal Sim, conforme Avaliação de Conformidade emitida pelo INMETRO para empresa que nos presta serviços de manutenção | O83: Gerir M&I de Equipamentos de Segurança | P83: Respondida | Q83: Respondida | R83: Luciana Santos-URFU | S83: 30/5/2023 | T83: 45952 | V83: Retornar com Ponto Focal | W83: FALSE | Y83: =VLOOKUP($B83,'Rascunho - PRI'!B82:X684,23,FALSE) -> 0 | Z83: =VLOOKUP($B83,'Rascunho - PRI'!B82:X684,23,FALSE) -> 0
B84: 80543 | D84: Ao menos dois instrumentos portáteis estão disponíveis a bordo para detecção de CH4, H2S, O2, CO e Compostos Orgânicos Voláteis ¿ COV? | E84: NR-37 | F84: SEGURANÇA E SAÚDE EM PLATAFORMAS DE PETRÓLEO. | G84: Item 37.23.11 | H84: ATIVIDADES OFFSHORE - DETECÇÃO E ALARMES | I84: Conforme | J84: Há 2 detectores a bordo de cada unidade de Búzios para detecção de CH4, H2S, O2, CO e Compostos Orgânicos Voláteis COV, modelo Altair 5x PID do fabricante MSA.Luciana Santos-URFU | K84: Há 2 detectores a bordo de cada unidade de Búzios para detecção de CH4, H2S, O2, CO e Compostos Orgânicos Voláteis COV, modelo Altair 5x PID do fabricante MSA. | O84: Gerir M&I de Equipamentos de Segurança | P84: Respondida | Q84: Respondida | R84: Luciana Santos-URFU | S84: 3/6/2025 | W84: FALSE | Z84: =VLOOKUP($B84,'Rascunho - PRI'!B83:X685,23,FALSE) -> Verificação dos detectores disponiveis deverão ficar sobre responsabilidade da equipe a bordo.
B85: 80578 | D85: Os hidrantes são facilmente visíveis e acessíveis? NOTA: Os abrigos das mangueiras e demais acessórios não podem estar trancados à chave. | E85: NR-37 | F85: SEGURANÇA E SAÚDE EM PLATAFORMAS DE PETRÓLEO. | G85: Item 37.25.6.1.2 | H85: ATIVIDADES OFFSHORE - COMBATE E PREVENÇÃO A INCÊNDIOS (GERAL) | I85: Conforme | J85: Hidrante são facilmente visível e com suas alocações conforme Safety Plan. | K85: Hidrante são facilmente visível e com suas alocações conforme Safety Plan. | O85: Gerir M&I de Equipamentos de Segurança | P85: Respondida | Q85: Respondida | R85: Luciana Santos-URFU | S85: 27/3/2025 | W85: FALSE | Z85: =VLOOKUP($B85,'Rascunho - PRI'!B84:X686,23,FALSE) -> Deverá ser confirmado in loco. Responsabilidade do Ativo.
B86: 81657 | D86: Após a realização da inspeção técnica dos seus extintores de incêndio, a empresa recebe relatório de inspeção contendo: nome do cliente e endereço; data da inspeção técnica e identificação do fornecedor; identificação do extintor de incêndio; as condições do ambiente a que está exposto o extintor de incêndio, quando aplicável; conferência por pesagem, da carga de cilindro ou ampola do extintor de incêndio carregado/a com dióxido de carbono (CO2) e registros das não conformidades, com relação à inspeção realizada conforme o estabelecido nos itens 6.1.1 e 6.1.2 desta Portaria e, quando aplicável, determinação do nível de manutenção a ser executadas no extintor de incêndio? NOTA: Quando executada a manutenção de 2º ou 3º níveis, não será necessário efetuar o preenchimento do relatório de inspeção técnica. | E86: PORTARIA INMETRO Nº 58, DE 16 DE FEVEREIRO DE 2022 | F86: Aprova o Regulamento Técnico da Qualidade e os Requisitos de Avaliação da Conformidade para a Inspeção Técnica e Manutenção de Extintores de Incêndio - Consolidado. | G86: Anexo I, Item 6.1.4 | H86: INCÊNDIO E EXPLOSÃO / PREVENÇÃO - Obrigações gerais relativas à combate e prevenção a INCÊNDIOS | I86: Conforme | J86: 1- Sim. Nos relatórios emitidos pela contratada. (Evidencia 1) | K86: Revisar resposta com ponto focal- pendente link dos relatórios Sim. Os relatórios são emitidos pela empresa contratada responsável pela inspeção. | O86: Gerir M&I de Equipamentos de Segurança | P86: Respondida | Q86: Respondida | R86: Luciana Santos-URFU | S86: 18/5/2023 | T86: 45952 | V86: Retornar com Ponto Focal | W86: FALSE | Y86: =VLOOKUP($B86,'Rascunho - PRI'!B85:X687,23,FALSE) -> 0 | Z86: =VLOOKUP($B86,'Rascunho - PRI'!B85:X687,23,FALSE) -> 0
B87: 80534 | D87: Os detectores portáteis são calibrados, aprovados e certificados por laboratório acreditado pelo INMETRO? | E87: NR-37 | F87: SEGURANÇA E SAÚDE EM PLATAFORMAS DE PETRÓLEO. | G87: Item 37.23.12 | H87: ATIVIDADES OFFSHORE - DETECÇÃO E ALARMES | I87: Conforme | J87: Sim, os detectores portáteis são calibrados, aprovados e certificados por laboratório acreditado pelo INMETRO, conforme evidencia em anexo. Luciana Santos- URFU | K87: Sim, os detectores portáteis são calibrados, aprovados e certificados por laboratório acreditado pelo INMETRO | L87: P-74 - https://petrobrasbr.sharepoint.com/:f:/r/teams/bdoc_20240301023456/Documentos%20Compartilhados/2%20-%20Interna/05%20-%20Equipamentos%20de%20Seguran%C3%A7a/02.%20Controle%20de%20Equipamentos/02.%20Ativo%201/01.%20Plataforma%20P74/07.%20Detectores%20de%20G%C3%A1s/3.%20Controle%20de%20Certificados/1.%20Calibra%C3%A7%C3%A3o/Certificado%20dos%20equipamentos%20do%20contrato%20MMG?csf=1&web=1&e=7P2UPk P-75 - https://petrobrasbr.sharepoint.com/:f:/r/teams/bdoc_20240301023456/Documentos%20Compartilhados/2%20-%20Interna/05%20-%20Equipamentos%20de%20Seguran%C3%A7a/02.%20Controle%20de%20Equipamentos/02.%20Ativo%201/02.%20Plataforma%20P75/07.%20Detectores%20de%20G%C3%A1s/3.%20Controle%20de%20Certificados/1.%20Calibra%C3%A7%C3%A3o/Certificados%20Detectores%20Alugados%20(MMG)?csf=1&web=1&e=jCXPl7 P-76 - https://petrobrasbr.sharepoint.com/:f:/r/teams/bdoc_20240301023456/Documentos%20Compartilhados/2%20-%20Interna/05%20-%20Equipamentos%20de%20Seguran%C3%A7a/02.%20Controle%20de%20Equipamentos/02.%20Ativo%201/02.%20Plataforma%20P75/07.%20Detectores%20de%20G%C3%A1s/3.%20Controle%20de%20Certificados/1.%20Calibra%C3%A7%C3%A3o/Certificados%20Detectores%20Alugados%20(MMG)?csf=1&web=1&e=jCXPl7 P-77 - https://petrobrasbr.sharepoint.com/:f:/r/teams/bdoc_20240301023456/Documentos%20Compartilhados/2%20-%20Interna/05%20-%20Equipamentos%20de%20Seguran%C3%A7a/02.%20Controle%20de%20Equipamentos/02.%20Ativo%201/02.%20Plataforma%20P75/07.%20Detectores%20de%20G%C3%A1s/3.%20Controle%20de%20Certificados/1.%20Calibra%C3%A7%C3%A3o/Certificados%20Detectores%20Alugados%20(MMG)?csf=1&web=1&e=jCXPl7 | O87: Gerir M&I de Equipamentos de Segurança | P87: Respondida | Q87: Respondida | R87: Luciana Santos-URFU | S87: 25/4/2025 | W87: FALSE | Z87: =VLOOKUP($B87,'Rascunho - PRI'!B86:X688,23,FALSE) -> Sem acesso para verificação das evidências
B88: 81680 | C88: Sim | D88: A empresa realiza a manutenção de 1º nível, sempre que for requerida por uma inspeção técnica, sendo realizado os procedimentos constantes do Item 6.2.2.2 e emitido o relatório contendo as informações elencadas no Item 6.2.2.3? NOTA: Pode ser realizada no local onde o extintor de incêndio se encontra instalado, desde que não haja justificativa para a remoção do extintor de incêndio para o fornecedor. | E88: PORTARIA INMETRO Nº 58, DE 16 DE FEVEREIRO DE 2022 | F88: Aprova o Regulamento Técnico da Qualidade e os Requisitos de Avaliação da Conformidade para a Inspeção Técnica e Manutenção de Extintores de Incêndio - Consolidado. | G88: Anexo I, Item 6.2.2 | H88: INCÊNDIO E EXPLOSÃO / PREVENÇÃO - Obrigações gerais relativas à combate e prevenção a INCÊNDIOS | I88: Conforme | J88: Realizada inspeções mensais pelos Técnicos de segurança de bordo através de rotas pre definidas e registradas no Intelatrac | K88: Os extintores de incêndio tipo ABC Premium não requer manutenção de 1º nível, somente inspeção e troca | O88: Gerir M&I de Equipamentos de Segurança | P88: Respondida | Q88: Respondida | R88: Luciana Santos-URFU | S88: 18/5/2023 | T88: 45952 | V88: Analisado | W88: FALSE | X88: Sem evidências | Z88: =VLOOKUP($B88,'Rascunho - PRI'!B87:X689,23,FALSE) -> Sem evidências
B89: 83812 | D89: O auto-zero ou ajuste de ar limpo e o teste de resposta do equipamento de avaliação, quando utilizados são realizados diariamente antes do início das avaliações? NOTA 1: Quando o auto-zero ou teste de resposta falharem, o equipamento de avaliação deve ser ajustado ou parametrizado pelo trabalhador, desde que devidamente capacitado (Item 33.5.15.5.1). NOTA 2: A calibração do equipamento de avaliação deve ser realizada por laboratório de calibração acreditado pelo INMETRO (Item 33.5.15.6). | E89: NR-33 | F89: SEGURANÇA E SAÚDE NO TRABALHO EM ESPAÇOS CONFINADO. | G89: Item 33.5.15.5 | H89: ESPAÇOS CONFINADOS - Executar ou fiscalizar atividades em espaços confinados | I89: Conforme | J89: "Os equipamentos disponibilizados nas unidades de Búzios, possibilitam o ajuste de Auto-Zero, com cilindro específico a finalidade. Equipamentos são calibrados em laboratório de calibração acreditado pelo INMETRO (Item 33.5.15.6). Evidência: Certificado de calibração LINK: https://petrobrasbr.sharepoint.com/:b:/r/teams/bdoc_20240301023456/Documentos%20Compartilhados/2%20-%20Interna/05%20-%20Equipamentos%20de%20Seguran%C3%A7a/02.%20Controle%20de%20Equipamentos/05.%20Base/07.%20Detectores%20de%20G%C3%A1s/Inspe%C3%A7%C3%A3o%20e%20certificados/Certificados%20de%20calibra%C3%A7%C3%A3o/Max%20XT/P-74-%20MA224-614235-%20CERT.%20MMG2024-11585.pdf?csf=1&web=1&e=0EIcHt" Luciana Santos-URFU | K89: "Os equipamentos disponibilizados nas unidades de Búzios, possibilitam o ajuste de Auto-Zero, com cilindro específico a finalidade. Equipamentos são calibrados em laboratório de calibração acreditado pelo INMETRO (Item 33.5.15.6). | L89: P-74 - https://petrobrasbr.sharepoint.com/:f:/r/teams/bdoc_20240301023456/Documentos%20Compartilhados/2%20-%20Interna/05%20-%20Equipamentos%20de%20Seguran%C3%A7a/02.%20Controle%20de%20Equipamentos/02.%20Ativo%201/01.%20Plataforma%20P74/07.%20Detectores%20de%20G%C3%A1s/3.%20Controle%20de%20Certificados/1.%20Calibra%C3%A7%C3%A3o/Certificado%20dos%20equipamentos%20do%20contrato%20MMG?csf=1&web=1&e=7P2UPk P-75 - https://petrobrasbr.sharepoint.com/:f:/r/teams/bdoc_20240301023456/Documentos%20Compartilhados/2%20-%20Interna/05%20-%20Equipamentos%20de%20Seguran%C3%A7a/02.%20Controle%20de%20Equipamentos/02.%20Ativo%201/02.%20Plataforma%20P75/07.%20Detectores%20de%20G%C3%A1s/3.%20Controle%20de%20Certificados/1.%20Calibra%C3%A7%C3%A3o/Certificados%20Detectores%20Alugados%20(MMG)?csf=1&web=1&e=jCXPl7 P-76 - https://petrobrasbr.sharepoint.com/:f:/r/teams/bdoc_20240301023456/Documentos%20Compartilhados/2%20-%20Interna/05%20-%20Equipamentos%20de%20Seguran%C3%A7a/02.%20Controle%20de%20Equipamentos/02.%20Ativo%201/02.%20Plataforma%20P75/07.%20Detectores%20de%20G%C3%A1s/3.%20Controle%20de%20Certificados/1.%20Calibra%C3%A7%C3%A3o/Certificados%20Detectores%20Alugados%20(MMG)?csf=1&web=1&e=jCXPl7 P-77 - https://petrobrasbr.sharepoint.com/:f:/r/teams/bdoc_20240301023456/Documentos%20Compartilhados/2%20-%20Interna/05%20-%20Equipamentos%20de%20Seguran%C3%A7a/02.%20Controle%20de%20Equipamentos/02.%20Ativo%201/02.%20Plataforma%20P75/07.%20Detectores%20de%20G%C3%A1s/3.%20Controle%20de%20Certificados/1.%20Calibra%C3%A7%C3%A3o/Certificados%20Detectores%20Alugados%20(MMG)?csf=1&web=1&e=jCXPl7 | O89: Gerir M&I de Equipamentos de Segurança | P89: Respondida | Q89: Respondida | R89: Luciana Santos-URFU | S89: 6/5/2025 | W89: FALSE | Z89: =VLOOKUP($B89,'Rascunho - PRI'!B88:X690,23,FALSE) -> Sem acesso para verificação das evidências
B90: 92305 | C90: Sim | D90: Após a manutenção das mangueiras, a empresa responsável emite um relatório que comprove ou não a aprovação? NOTA: Quando realizadas, simultaneamente, a inspeção e a manutenção, pode ser emitido um único relatório aprovando diversas mangueiras, desde que cada uma delas esteja relacionada no relatório. | E90: ABNT NBR 12779:2009 | F90: Mangueira de Incêndio - Inspeção, Manutenção e Cuidados | G90: Item 4.7 | H90: INCÊNDIO E EXPLOSÃO / PREVENÇÃO - Sistemas de Hidrantes e/ou de Mangotinhos | I90: Conforme | J90: A empresa emite relatório contendo as informações solicitadas na coluna sobre Informações sobre o Ensaio/Resultado do Ensaio Hidrostático, em que a letra A representa mangueiras Aprovadas, a letra C representa mangueiras condenadas e a letra R, mangueiras reempatadas conforme legenda da última página do anexo NM 15060093 | K90: A empresa emite relatório contendo as informações solicitadas na coluna sobre Informações sobre o Ensaio/Resultado do Ensaio Hidrostático. | L90: Certificados da Mangueiras: P-74 = https://petrobrasbr.sharepoint.com/:f:/r/teams/bdoc_20240301023456/Documentos%20Compartilhados/2%20-%20Interna/05%20-%20Equipamentos%20de%20Seguran%C3%A7a/02.%20Controle%20de%20Equipamentos/02.%20Ativo%201/01.%20Plataforma%20P74/04.%20Arm%C3%A1rio%20de%20Equipamentos%20de%20Combate%20a%20Inc%C3%AAndio/3.%20Controle%20de%20Certificados/1.%20TH%20Teste%20Hidrost%C3%A1tico?csf=1&web=1&e=HAga4G P-75 = https://petrobrasbr.sharepoint.com/:f:/r/teams/bdoc_20240301023456/Documentos%20Compartilhados/2%20-%20Interna/05%20-%20Equipamentos%20de%20Seguran%C3%A7a/02.%20Controle%20de%20Equipamentos/02.%20Ativo%201/02.%20Plataforma%20P75/04.%20Arm%C3%A1rio%20de%20Equipamentos%20de%20Combate%20a%20Inc%C3%AAndio/3.%20Controle%20de%20Certificados/1.%20TH%20Teste%20Hidrost%C3%A1tico?csf=1&web=1&e=VaycSR P-76 = https://petrobrasbr.sharepoint.com/:f:/r/teams/bdoc_20240301023456/Documentos%20Compartilhados/2%20-%20Interna/05%20-%20Equipamentos%20de%20Seguran%C3%A7a/02.%20Controle%20de%20Equipamentos/02.%20Ativo%201/03.%20Plataforma%20P76/04.%20Arm%C3%A1rio%20de%20Equipamentos%20de%20Combate%20a%20Inc%C3%AAndio/3.%20Controle%20de%20Certificados/1.%20TH%20Teste%20Hidrost%C3%A1tico?csf=1&web=1&e=l5kKZl P-77 = https://petrobrasbr.sharepoint.com/:f:/r/teams/bdoc_20240301023456/Documentos%20Compartilhados/2%20-%20Interna/05%20-%20Equipamentos%20de%20Seguran%C3%A7a/02.%20Controle%20de%20Equipamentos/02.%20Ativo%201/04.%20Plataforma%20P77/04.%20Arm%C3%A1rio%20de%20Equipamentos%20de%20Combate%20a%20Inc%C3%AAndio/3.%20Controle%20de%20Certificados/1.%20TH%20Teste%20Hidrost%C3%A1tico?csf=1&web=1&e=ye3mn2 | O90: Gerir M&I de Equipamentos de Segurança | P90: Respondida | Q90: Respondida | R90: Luciana Santos-URFU | S90: 17/7/2024 | T90: 45952 | V90: Analisado | W90: TRUE | X90: Verificado o certificado de inspeção NM16335976- Certificado 008.2025 TH da P-76 | Z90: =VLOOKUP($B90,'Rascunho - PRI'!B89:X691,23,FALSE) -> Verificado o certificado de inspeção NM16335976- Certificado 008.2025 TH da P-76
B91: 68568 | D91: (CALOR) Se as informações obtidas na avaliação preliminar não forem suficientes para permitir a tomada de decisão quanto à necessidade de implementação de medidas de prevenção, a organização realizou a avaliação quantitativa de modo a atender as situações abaixo? a) comprovar o controle da exposição ou a inexistência de riscos identificados na etapa de avaliação preliminar; b) dimensionar a exposição dos trabalhadores; e c) subsidiar o equacionamento das medidas de prevenção. | E91: NR-09 | F91: Avaliação e Controle das Exposições Ocupacionais a Agentes Físicos, Químicos e Biológicos. | G91: Anexo III, Item 3.2.1.1 | H91: RISCOS AMBIENTAIS - Exposição ocupacional a agentes físicos - CALOR | I91: Conforme | J91: Sim, para as situações em que é possível enquadrar a exposição ocupacional ao Calor, à concepção do Limite de Exposição (Condição mais crítica em um ciclo de trabalho de 60 minutos), é feita a avaliação quantitativa do Grupo Homogêneo de Exposição. | K91: Sim, para as situações em que é possível enquadrar a exposição ocupacional ao Calor, à concepção do Limite de Exposição (Condição mais crítica em um ciclo de trabalho de 60 minutos), é feita a avaliação quantitativa do Grupo Homogêneo de Exposição. | L91: PGRs do Ativo 1: https://app.powerbi.com/groups/me/apps/14321397-e31d-4829-86b1-741d704a5a18/reports/c7614387-e6e4-45ae-af53-79ce251d7935/b3729538142d9e5117c5?ctid=5b6f6241-9a57-4be4-8e50-1dfa72e79a57&experience=power-bi | M91: Sim, para as situações em que é possível enquadrar a exposição ocupacional ao Calor, à concepção do Limite de Exposição (Condição mais crítica em um ciclo de trabalho de 60 minutos), é feita a avaliação quantitativa do Grupo Homogêneo de Exposição. | N91: n/a | O91: Gerir Higiene Ocupacional | P91: Respondida | Q91: Respondida | R91: LEONARDO MEDINA - CSQE | S91: 18/3/2025 | T91: 46003 | W91: FALSE | Y91: =VLOOKUP($B91,'Rascunho - PRI'!B90:X692,23,FALSE) -> 0 | Z91: =VLOOKUP($B91,'Rascunho - PRI'!B90:X692,23,FALSE) -> 0
B92: 68621 | D92: (Benzeno) A empresa, caso produza, transporte, armazene, utilize ou manipule benzeno e suas misturas líquidas contendo 1% (um por cento) ou mais de volume, efetivou o seu cadastramento junto ao Departamento de Segurança e Saúde no Trabalho - DSST? | E92: NR-15 | F92: Atividades e Operações Insalubres. | G92: Anexo 13-A, item 4 | H92: RISCOS AMBIENTAIS - Exposição ocupacional a agentes químicos - BENZENO | I92: Conforme | J92: Não temos necessidade de realizar o referido cadastro, pois as avaliações de Benzeno nas Correntes de Petróleo das Unidades Marítimas da UN-BUZ deram valores inferiores a 1%. | K92: Não aplicável. Não temos necessidade de realizar o referido cadastro, pois as avaliações de Benzeno nas Correntes de Petróleo das Plataformas de BUZ deram valores inferiores a 1%. | L92: n/a | M92: n/a | N92: n/a | O92: Gerir Higiene Ocupacional | P92: Respondida | Q92: Respondida | R92: LEONARDO MEDINA - CSQE | S92: 18/3/2025 | T92: 46003 | W92: FALSE | Y92: =VLOOKUP($B92,'Rascunho - PRI'!B91:X693,23,FALSE) -> 0 | Z92: =VLOOKUP($B92,'Rascunho - PRI'!B91:X693,23,FALSE) -> 0
B93: 80665 | D93: O tipo de queimador (flare) e as descargas dos suspiros (vents) de alta velocidade e suas respectivas localizações assegura, em todas as áreas da plataforma, níveis aceitáveis de exposição à vibração, ao ruído e ao calor, conforme limites estabelecidos na NR 09, exceto durante as operações de despressurização? NOTA: O queimador (flare) deve ser dotado de acendimento remoto e de sistema de detecção de piloto apagado para proceder à parada controlada da planta industrial que o utiliza. | E93: NR-37 | F93: SEGURANÇA E SAÚDE EM PLATAFORMAS DE PETRÓLEO. | G93: Item 37.27.5.1 | H93: ATIVIDADES OFFSHORE - OPERACIONAL | I93: Conforme | J93: Nos estudos preditivos das UEP de Búzios foram contemplados os riscos ocupacionais Calor, Ruído e Vibração oriundos do flare e do vent post. Evidências: Estudos preditivos de ruído e vibração; APR (Trabalhos no Flare Operacional) - análise do Calor. | K93: Ruído e Vibração contemplados nos estudos preditivos das UEP de Búzios. Análise do Calor realizada para a P-74 e P-75 (APR - Trabalhos no Flare Operacional) através de relatório do CENPES. | L93: Evidências: Estudos preditivos de ruído e vibração no SIGEM, Calor: (CT_TIS_006_2024-Estudo_Radiação_ Térmica_Manutenção_Flare_P-75_Rev_0) | M93: Não conforme. Nenhum estudo foi encaminhado pela IPO. | N93: n/a | O93: Gerir Higiene Ocupacional | P93: Respondida | Q93: Respondida | R93: LEONARDO MEDINA - CSQE | S93: 22/4/2025 | T93: 46003 | W93: FALSE | Y93: =VLOOKUP($B93,'Rascunho - PRI'!B92:X694,23,FALSE) -> 0 | Z93: =VLOOKUP($B93,'Rascunho - PRI'!B92:X694,23,FALSE) -> 0
B94: 68570 | D94: (CALOR) Para os ambientes fechados ou com fontes artificiais de calor, além de observar o disposto no subitem 4.1.1, o empregador fornece vestimentas de trabalho adaptadas ao tipo de exposição e à natureza da atividade? | E94: NR-09 | F94: Avaliação e Controle das Exposições Ocupacionais a Agentes Físicos, Químicos e Biológicos. | G94: Anexo III, Item 4.1.2 | H94: RISCOS AMBIENTAIS - Exposição ocupacional a agentes físicos - CALOR | I94: Conforme | J94: Nas atividades habituais das plataformas não houve necessidade de adoção de vestimentas específicas para o calor. | K94: Nas atividades habituais das plataformas não houve necessidade de adoção de vestimentas específicas para o calor. | L94: n/a | M94: Nas atividades habituais das plataformas não houve necessidade de adoção de vestimentas específicas para o calor. | N94: n/a | O94: Gerir Higiene Ocupacional | P94: Respondida | Q94: Respondida | R94: LEONARDO MEDINA - CSQE | S94: 18/3/2025 | T94: 46003 | W94: FALSE | Y94: =VLOOKUP($B94,'Rascunho - PRI'!B93:X695,23,FALSE) -> 0 | Z94: =VLOOKUP($B94,'Rascunho - PRI'!B93:X695,23,FALSE) -> 0
B95: 68616 | D95: VIBRAÇÃO) A empresa, para fins de caracterização da condição insalubre decorrente da exposição às Vibrações de Mãos e Braços (VMB) e Vibrações de Corpo Inteiro (VCI), comprova a avaliação dos parâmetros previstos nos itens 2.1 e 2.2 do Anexo 8 da presente NR, sendo o laudo técnico da caracterização da exposição emitido conforme exigências constantes do Anexo 8, item 2.5, da presente NR? | E95: NR-15 | F95: Atividades e Operações Insalubres. | G95: Anexo 8 | H95: RISCOS AMBIENTAIS - Exposição ocupacional a agentes físicos - VIBRAÇÃO | I95: Conforme | J95: Laudos de insalubridade são elaborados por demandas judiciais. | K95: Sim. A empresa inclusive está iniciando nova Campanha de avaliações quantitativas, com objetivo de acompanhar a exposição através de relatórios conclusivos | L95: n/a | M95: Sim. A empresa inclusive está iniciando nova Campanha de avaliações quantitativas, com objetivo de acompanhar a exposição através de relatórios conclusivos | N95: n/a | O95: Gerir Higiene Ocupacional | P95: Respondida | Q95: Respondida | R95: LEONARDO MEDINA - CSQE | S95: 18/3/2025 | T95: 46003 | W95: FALSE | Y95: =VLOOKUP($B95,'Rascunho - PRI'!B94:X696,23,FALSE) -> 0 | Z95: =VLOOKUP($B95,'Rascunho - PRI'!B94:X696,23,FALSE) -> 0
B96: 52913 | D96: Além do disposto no subitem 1.5.4.4.6 na NR-01, o PGR é reavaliadonas situações a seguir: a) sempre que se produza uma mudança nas condições de trabalho, que possa alterar a exposição aos agentes biológicos; b) quando a análise dos acidentes e incidentes assim o determinar? | E96: NR-32 | F96: Segurança e Saúde no Trabalho em Serviços de Saúde. | G96: Item 32.2.2.2 | H96: RISCOS - Promover a redução e prevenção dos riscos no ambiente do trabalho | I96: Conforme | J96: Sim,o item é atendido integralmente. Responsável Leonardo Medina._x000D_ Segue link no BDOC do documento:_x000D_ _x000D_ https://petrobrasbr.sharepoint.com/teams/bdoc_20240301023456/Documentos%20Compartilhados/Forms/AllItems.aspx?id=%2Fteams%2Fbdoc%5F20240301023456%2FDocumentos%20Compartilhados%2F2%20%2D%20Interna%2F03%20%2D%20Higiene%20Ocupacional%2FPrograma%20de%20Gerenciamento%20de%20Riscos%20%2D%20PGR&viewid=896b9af3%2D5ce1%2D4466%2Da4b4%2Dc44427d25b4d | K96: Sim. Item atendido integralmente. | L96: PGRs do Ativo 1: https://app.powerbi.com/groups/me/apps/14321397-e31d-4829-86b1-741d704a5a18/reports/c7614387-e6e4-45ae-af53-79ce251d7935/b3729538142d9e5117c5?ctid=5b6f6241-9a57-4be4-8e50-1dfa72e79a57&experience=power-bi | M96: Sim. Item atendido integralmente. | N96: PGRs do Ativo 2: https://app.powerbi.com/groups/me/apps/14321397-e31d-4829-86b1-741d704a5a18/reports/c7614387-e6e4-45ae-af53-79ce251d7935/b3729538142d9e5117c5?ctid=5b6f6241-9a57-4be4-8e50-1dfa72e79a57&experience=power-bi | O96: Gerir Higiene Ocupacional | P96: Respondida | Q96: Respondida | R96: LEONARDO MEDINA - CSQE | S96: 25/3/2025 | T96: 46009 | W96: FALSE | Y96: =VLOOKUP($B96,'Rascunho - PRI'!B95:X697,23,FALSE) -> 0 | Z96: =VLOOKUP($B96,'Rascunho - PRI'!B95:X697,23,FALSE) -> 0
B97: 53476 | D97: (EXPOSIÇÃO AO CALOR) A avaliação quantitativa do calor foi realizada com base na metodologia e procedimentos descritos na Norma de Higiene Ocupacional NHO 06 (2ª edição - 2017) da FUNDACENTRO nos seguintes aspectos: a) determinação de sobrecarga térmica por meio do índice IBUTG - Índice de Bulbo Úmido Termômetro de Globo; b) equipamentos de medição e formas de montagem, posicionamento e procedimentos de uso dos mesmos nos locais avaliados; c) procedimentos quanto à conduta do avaliador; e d) medições e cálculos? | E97: NR-15 | F97: Atividades e Operações Insalubres. | G97: Anexo 3, Item 2.1 | H97: RISCOS AMBIENTAIS - Exposição ocupacional a agentes físicos - CALOR | I97: Conforme | J97: Sim. Evidências salvas no site do PGR-HO | K97: Sim. Aspectos atendidos integralmente. | L97: PGRs do Ativo 1: https://app.powerbi.com/groups/me/apps/14321397-e31d-4829-86b1-741d704a5a18/reports/c7614387-e6e4-45ae-af53-79ce251d7935/b3729538142d9e5117c5?ctid=5b6f6241-9a57-4be4-8e50-1dfa72e79a57&experience=power-bi | M97: Parcialmente atendido. A exposição ao Calor terá seus aspectos avaliados na Campanha de HO, iniciando em Janeiro/2026. | N97: n/a | O97: Gerir Higiene Ocupacional | P97: Respondida | Q97: Respondida | R97: LEONARDO MEDINA - CSQE | S97: 18/3/2025 | T97: 46009 | W97: FALSE | Y97: =VLOOKUP($B97,'Rascunho - PRI'!B96:X698,23,FALSE) -> 0 | Z97: =VLOOKUP($B97,'Rascunho - PRI'!B96:X698,23,FALSE) -> 0
B98: 68563 | D98: (VIBRAÇÃO) A avaliação da exposição ocupacional à vibração em mãos e braços utiliza sistemas de medição que permitam a obtenção da aceleração resultante de exposição normalizada - Aren, parâmetro representativo da exposição diária do trabalhador? | E98: NR-09 | F98: Avaliação e Controle das Exposições Ocupacionais a Agentes Físicos, Químicos e Biológicos. | G98: Anexo I, Item 5.2.1 | H98: RISCOS AMBIENTAIS - Exposição ocupacional a agentes físicos - VIBRAÇÃO | I98: Conforme | J98: Avaliações previstas para a próxima Campanha de Higiene Ocupacional de Búzios, cujo contrato e especificação técnica estão sob a gestão da gerência SEG/OFF, com cópia na Bdoc. | K98: Avaliações previstas para a próxima Campanha de Higiene Ocupacional de Búzios, cujo contrato e especificação técnica estão sob a gestão da gerência SEG/OFF, com cópia na Bdoc. | L98: Link para a E.T. da Campanha de Higiene Ocupacional: https://petrobrasbr.sharepoint.com/:b:/r/teams/bdoc_20240301023456/Documentos%20Compartilhados/2%20-%20Interna/03%20-%20Higiene%20Ocupacional/Material%20de%20apoio/Contrato%20HO%20SEG-OFF/Documentos%20Grupo%20Teams%20SESI-HO/ICJ%20N%20%205900.0131652.25.2%20-%20Documento%20original%20com%20relat%C3%B3rio%20da%20Petronect%20(1).pdf?csf=1&web=1&e=BKfBDa | M98: Avaliações previstas para a próxima Campanha de Higiene Ocupacional de Búzios, cujo contrato e especificação técnica estão sob a gestão da gerência SEG/OFF, com cópia na Bdoc. | N98: Link para a E.T. da Campanha de Higiene Ocupacional: https://petrobrasbr.sharepoint.com/:b:/r/teams/bdoc_20240301023456/Documentos%20Compartilhados/2%20-%20Interna/03%20-%20Higiene%20Ocupacional/Material%20de%20apoio/Contrato%20HO%20SEG-OFF/Documentos%20Grupo%20Teams%20SESI-HO/ICJ%20N%20%205900.0131652.25.2%20-%20Documento%20original%20com%20relat%C3%B3rio%20da%20Petronect%20(1).pdf?csf=1&web=1&e=BKfBDa | O98: Gerir Higiene Ocupacional | P98: Respondida | Q98: Respondida | R98: LEONARDO MEDINA - CSQE | S98: 18/3/2025 | T98: 46009 | W98: FALSE | Y98: =VLOOKUP($B98,'Rascunho - PRI'!B97:X699,23,FALSE) -> 0 | Z98: =VLOOKUP($B98,'Rascunho - PRI'!B97:X699,23,FALSE) -> 0
B99: 102522 | D99: Quando na fase de levantamento preliminar de perigos e riscos, o perigo não puder ser evitado ou eliminado, a organização implementa o processo de identificação de perigos e avaliação de riscos ocupacionais, conforme disposto nos subitens 1.5.4.3 e 1.5.4.4 e na caso nesta fase não for possível adotar medidas imediatas para reduzir ou controlar o risco ocupacional evidente, as medidas são inseridas no plano de ação e o risco registrado no inventário de riscos? | E99: NR-01 | F99: Disposições Gerais e Gerenciamento de Riscos Ocupacionais. | G99: Item 1.5.4.2.1.2 e 1.5.4.2.1.3 | H99: RISCOS - Promover a redução e prevenção dos riscos no ambiente do trabalho | I99: Conforme | J99: O processo de identificação de perigos e avaliação de riscos ocupacionais está implementado no inventário de riscos e plano de ação do PGR-HO. Para os agentes de riscos com avaliações superiores ao nível de ação são fornecidos EPI adequados ao nível de exposição. São realizados também estudos para implementação de ações de controle no plano de ação do PGR-HO, visando minimizar a necessidade de uso de EPI. Evidência: https://petrobrasbr.sharepoint.com/teams/bdoc_20240301023456/Documentos%20Compartilhados/Forms/AllItems.aspx?id=%2Fteams%2Fbdoc%5F20240301023456%2FDocumentos%20Compartilhados%2F2%20%2D%20Interna%2F03%20%2D%20Higiene%20Ocupacional%2FPrograma%20de%20Gerenciamento%20de%20Riscos%20%2D%20PGR&viewid=896b9af3%2D5ce1%2D4466%2Da4b4%2Dc44427d25b4d | K99: Sim. Aspectos atendidos integralmente. | L99: PGRs do Ativo 1: https://app.powerbi.com/groups/me/apps/14321397-e31d-4829-86b1-741d704a5a18/reports/c7614387-e6e4-45ae-af53-79ce251d7935/b3729538142d9e5117c5?ctid=5b6f6241-9a57-4be4-8e50-1dfa72e79a57&experience=power-bi | M99: Sim. Item atendido através da gestão dos riscos em todas as etapas de cada Plataforma, a saber: Estaleiro, Locação, 1º Óleo e Produção. | N99: PGRs do Ativo 2: https://app.powerbi.com/groups/me/apps/14321397-e31d-4829-86b1-741d704a5a18/reports/c7614387-e6e4-45ae-af53-79ce251d7935/b3729538142d9e5117c5?ctid=5b6f6241-9a57-4be4-8e50-1dfa72e79a57&experience=power-bi | O99: Gerir Higiene Ocupacional | P99: Respondida | Q99: Respondida | R99: LEONARDO MEDINA - CSQE | S99: 22/4/2025 | T99: 46009 | W99: FALSE | Y99: =VLOOKUP($B99,'Rascunho - PRI'!B98:X700,23,FALSE) -> 0 | Z99: =VLOOKUP($B99,'Rascunho - PRI'!B98:X700,23,FALSE) -> 0
B100: 107212 | D100: Os limites de exposição ocupacional são monitorados por trabalhadores e segundo avaliação médica, encontram-se aptos para trabalhos com exposição ao calor, e recebem reposição de água e sais perdidos durante sua atividade e que trabalhem com vestimentas tradicionais, compostas por calça e camisa de manga longa ou macacão de tecido simples? NOTA: A reposição de água e sais deve ser feita mediante orientação e controle médico. | E100: NORMA DE HIGIENE OCUPACIONAL - NHO 06, DE 31 DE MARÇO DE 2025 | F100: Avaliação da Exposição Ocupacional ao Calor - 3ª edição. | G100: Item 5.3 | H100: RISCOS AMBIENTAIS - Exposição ocupacional a agentes físicos - CALOR | I100: Conforme | J100: "Monitoramos o ambiente, levando-se em conta as atividades exercidas pelos trabalhadores, visando o atendimento aos limites de exposição ocupacional; Quanto à avaliação médica dos trabalhadores monitorados ou orientação para a questão de reposição de água e sais perdidos, isto deve ser respondido pela Coordenação do PCMSO; É feita a reposição de água e sais perdidos durante as atividades dos trabalhadores com vestimentas tradicionais (compostas por calça e camisa de manga longa ou macacão de tecido simples), através do TS de Bordo." Leonardo Medina- CSQE | K100: Os limites de exposição ocupacional são monitorados, levando-se em conta as atividades exercidas pelos trabalhadores (periodicamente, nas atividades de rotina, visando o atendimento aos limites de exposição ocupacional e pontualmente, antes da liberação de atividades específicas, através do TS de Bordo). É considerado o tipo de vestimenta no cálculo, conforme o Anexo H do Padrão PE-1PBR-00214. Quanto à avaliação médica dos trabalhadores monitorados ou orientação para a questão de reposição de água e sais perdidos, isto deve ser respondido pela Coordenação do PCMSO. | L100: Avaliações exposição ao Calor, conforme PGRs do Ativo 1: https://app.powerbi.com/groups/me/apps/14321397-e31d-4829-86b1-741d704a5a18/reports/c7614387-e6e4-45ae-af53-79ce251d7935/b3729538142d9e5117c5?ctid=5b6f6241-9a57-4be4-8e50-1dfa72e79a57&experience=power-bi. Avaliações pontuais, realizadas pelos TS de Bordo: Seguem conforme o Anexo H, do Padrão PE-1PBR-00214 - MS TRABALHOS EM ESPAÇO CONFINADO: https://sinpep.petrobras.com.br/SINPEP_Padrao_Web/PadraoEditar?PadraoId=1339 | M100: A exposição ao Calor nas atividades de rotina será avaliada nas próximas Campanhas de Higiene Ocupacional, com início em janeiro/2026. | N100: n/a | O100: Gerir Higiene Ocupacional | P100: Respondida | Q100: Respondida | R100: LEONARDO MEDINA - CSQE | S100: 22/7/2025 | T100: 46009 | W100: FALSE | Y100: =VLOOKUP($B100,'Rascunho - PRI'!B99:X701,23,FALSE) -> 0 | Z100: =VLOOKUP($B100,'Rascunho - PRI'!B99:X701,23,FALSE) -> 0
...

Sheet Resumo - Pri
A3: Rótulos de Linha | B3: Contagem de Observações - Priscila | C3: Contagem de Ok?
A4: FALSO | B4: 49 | C4: 557 | D4: =GETPIVOTDATA("Contagem de Ok?",$A$3,"Ok?",FALSE)-GETPIVOTDATA("Contagem de Observações - Priscila",$A$3,"Ok?",FALSE) -> 508 | E4: Análises Pendentes
A5: VERDADEIRO | B5: 145 | C5: 146 | D5: =GETPIVOTDATA("Contagem de Observações - Priscila",$A$3,"Ok?",TRUE)+GETPIVOTDATA("Contagem de Observações - Priscila",$A$3,"Ok?",FALSE) -> 194 | E5: Análises Realizadas
A6: Total Geral | B6: 194 | C6: 703

Sheet Extração - Setembro.2025
A1: Código Obrigação | B1: Obrigação | C1: Requisito de SMS | D1: Ementa | E1: Artigo/Item | F1: Assunto | G1: Situação Obrigação | H1: RESPOSTA | I1: Responsável pela resposta no Ciclo | J1: Data Atualização Gestor
A2: 51479 | B2: Os exercícios simulados de emergência são programados periodicamente de forma a contemplar os cenários previstos no Plano de Resposta a Emergência de acordo com os riscos envolvidos e a complexidade do Sistema Submarino; Coordenados com as partes envolvidas e autoridades competentes; Avaliados de forma a identificar as irregularidades e oportunidades de melhoria? | C2: RESOLUÇÃO ANP Nº 41, DE 09 DE OUTUBRO DE 2015 | D2: Aprova o Regulamento Técnico do Sistema de Gerenciamento de Segurança Operacional de Sistemas Submarinos - SGSS. | E2: Anexo Item 18.5.1 | F2: SEGURANÇA OPERACIONAL - Sistemas Submarinos | G2: Conforme | H2: PE-2SMS-00074 GERIR TREINAMENTOS DE CONTINGÊNCIA E SIMULADOS NO E&P UN-BUZ SMS SEG - Documentos\2 - Interna\04 - Contingência, Prontidão e Resposta\01. Simulados\01 - Simulado N1 Sistema: Portal de Gestão / BDoc Sandra Nery- LNGH | I2: Walcy Borges- SESM | J2: 30/5/2025
A3: 51481 | B3: Foi elaborado procedimento para emissão de permissão de trabalho, contendo no mínimo, o estabelecimento dos tipos de atividade que possam constituir riscos para a segurança operacional; A necessidade da análise prévia das condições de segurança para execução de tarefas, bem como dos perigos existentes; A inclusão na permissão de trabalho, do seu prazo de validade e de medidas adicionais de precaução e mitigação; Estabelecimento de responsabilidades e atribuições para a Força de Trabalho responsável por emitir e aprovar as permissões de trabalho; necessidade de treinamento; e Definição de metodologia de arquivamento para cada tipo de permissão de trabalho, considerando prazos compatíveis com a relevância do serviço executado? | C3: RESOLUÇÃO ANP Nº 41, DE 09 DE OUTUBRO DE 2015 | D3: Aprova o Regulamento Técnico do Sistema de Gerenciamento de Segurança Operacional de Sistemas Submarinos - SGSS. | E3: Anexo Item 19.2 | F3: SEGURANÇA OPERACIONAL - Sistemas Submarinos | G3: Conforme | H3: PE-1PBR-00210- MS- PERMISSÃO PARA TRABALHO Sistema: Portal de Gestão Sandra Nery- LNGH | I3: Walcy Borges- SESM | J3: 30/5/2025
A4: 51639 | B4: O Operador do Contrato define e documenta os valores e a política de segurança operacional, seu comprometimento e obrigações para proteção da vida humana, do meio ambiente e das atividades econômicas próprias e de terceiros, sendo estes documentos aprovados pela alta gerência? | C4: RESOLUÇÃO ANP Nº 46, DE 01 DE NOVEMBRO DE 2016 | D4: Aprova o Regime de Segurança Operacional para Integridade de Poços de Petróleo e Gás Natural, que estabelece os requisitos de segurança operacional e de preservação do meio ambiente para perfuração, completação, avaliação, intervenção, produção e abandono de poços de petróleo e gás natural. | E4: Item 1.2 | F4: SEGURANÇA OPERACIONAL - Integridade de Poços | G4: Conforme | H4: "PL-0SPB-00002 POLÍTICA DE SEGURANÇA, MEIO AMBIENTE E SAÚDE - SMS https://portal.petrobras.com.br/sobre-nos/nossa-estrategia https://portal.petrobras.com.br/sustentabilidade-e-seguranca/seguranca Sistema:Portal de Gestão / Intranet Atendido conforme padrão PL-0SPB-00002 - POLÍTICA DE SEGURANÇA, MEIO AMBIENTE E SAÚDE - SMS disponível no portal de gestão." Sandra Nery-LNGH | I4: Walcy Borges- SESM | J4: 30/5/2025
A5: 52494 | B5: Os estudos, projetos, planos, relatórios, laudos e quaisquer outros trabalhos ou atividades de Engenharia de Segurança do Trabalho possuem as respectivas Anotações de Responsabilidade Técnica - ART vinculadas? | C5: RESOLUÇÃO CONFEA Nº 437, DE 27 DE NOVEMBRO DE 1999 | D5: Dispõe sobre a Anotação de Responsabilidade Técnica - ART relativa às atividades dos Engenheiros e Arquitetos, especialistas em Engenharia de Segurança do Trabalho e dá outras providências. | E5: Art. 1º, § 1º | F5: ART - Executar ou fiscalizar atividades sujeitas à emissão de ART junto ao sistema CONFEA/CREA | G5: Conforme | H5: Sim, conforme Padrão de Gestão de Contratos, Padrões de Engenharia, Padrões de Segurança e RH. Fabio Mota - DXV9 | I5: - FLVR | J5: 4/6/2025
A6: 53259 | B6: O sistema de proteção individual contra quedas - SPIQ da empresa é constituído por sistema de ancoragem, elemento de ligação e equipamento de proteção individual? | C6: NR-35 | D6: TRABALHO EM ALTURA. | E6: Anexo II Item 2.1 | F6: TRABALHO EM ALTURA - Executar/Fiscalizar atividades em TRABALHO EM ALTURA | G6: Conforme | H6: Os trabalhos em altura são realizados conforme o padrão PE-1PBR-00218 - TRABALHOS EM ALTURA, que possui como documento de referência e/ou complementar a NR-35 : PE-1PBR-00218 3.5.1.4. O SPIQ deve ser composto de cinturão de segurança tipo paraquedista (EPI), elemento de ligação, sistema de ancoragem e atender as orientações da NBR-16489. Fernando Rodrigues- CMQ6 | I6: Fernando Rodrigues- CMQ6 | J6: 29/4/2025
A7: 53323 | B7: A empresa estabelece, implementa e mantém procedimento com ações de resposta às emergências que envolvam o trabalho em altura contemplando os perigos associados à operação de resgate; a equipe de emergência e salvamento necessária e o seu dimensionamento; tempo estimado para o resgate; e técnicas apropriadas, equipamentos pessoais e/ou coletivos específicos e sistema de resgate disponível, de forma a reduzir o tempo de suspensão inerte do trabalhador e sua exposição aos perigos existentes? | C7: NR-35 | D7: TRABALHO EM ALTURA. | E7: Item 35.7.1 | F7: TRABALHO EM ALTURA - Executar/Fiscalizar atividades em TRABALHO EM ALTURA | G7: Conforme | H7: Sim,as orientações para o resgate em trabalhos em altura estão previstas nos padrões abaixo, que possuem como documento de referência e/ou complementar a NR-35 ::_x000D_ - PE-1PBR-00218 - TRABALHOS EM ALTURA - Anexo E._x000D_ 3.8.4. Emergência e salvamento_x000D_ 3.8.4.1. As ações de respostas às emergências que envolvam o trabalho em altura devem constar do plano de emergência da instalação Petrobras ou instalação da empresa contratada._x000D_ - PE-3BUZ-00100 - PLANO DE RESPOSTA A EMERGÊNCIAS NAS PLATAFORMAS_x000D_ - PE-3BUZ-00246 - RESGATE EM ALTURA E ESPAÇO CONFINADO._x000D_ Fernando Rodrigues- CMQ6 | I7: Fernando Rodrigues- CMQ6 | J7: 29/4/2025
A8: 54316 | B8: Na elaboração do Plano de Emergência Individual foram observadas as diretrizes trazidas pela presente Nota Técnica? | C8: NOTA TÉCNICA CGPEG/DILIC/IBAMA Nº 03, DE 20 DE SETEMBRO DE 2013 | D8: Diretrizes para aprovação dos Planos de Emergência Individual ¿ PEI, nos processos de licenciamento ambiental dos empreendimentos marítimos de exploração e produção de petróleo e gás natural. | E8: Item I | F8: RECURSOS HÍDRICOS - Controle de poluição por óleo e outras substâncias nocivas/perigosas em águas jurisdicionais brasileiras OFFSHORE | G8: Conforme | H8: Conforme procedimentos e obtenção de L.O PE-3BUZ-00219 PEI - PLANO DE EMERGÊNCIA INDIVIDUAL DA PLATAFORMA P-74 PE-3BUZ-00220 PEI - PLANO DE EMERGÊNCIA INDIVIDUAL DA PLATAFORMA P-75 PE-3BUZ-00221 PEI - PLANO DE EMERGÊNCIA INDIVIDUAL DA PLATAFORMA P-76 PE-3BUZ-00222 PEI - PLANO DE EMERGÊNCIA INDIVIDUAL DA PLATAFORMA P-77 Sistema: Portal de Gestão Walcy Borges- SESM | I8: Walcy Borges- SESM | J8: 8/5/2025
A9: 54471 | B9: Para cada local de trabalho com acesso por cordas existe um plano de autorresgate e resgate dos profissionais devidamente capacitados? | C9: NR-34 | D9: CONDIÇÕES E MEIO AMBIENTE DE TRABALHO NA INDÚSTRIA DA CONSTRUÇÃO,REPARAÇÃO E DESMONTE NAVAL. | E9: Item 34.6.6.4 | F9: ATIVIDADES OFFSHORE - TRABALHO EM ALTURA | G9: Conforme | H9: O supervisor N3 deve elaborar Plano de Resgate a ser utilizado em caso de emergência, mantendo os recursos disponíveis durante todo o período de realização do trabalho, conforme modelo de roteiro apresentado no Anexo D.O profissional de segurança deve conferir a disponibilidade dos equipamentos definidos no plano de resgate. Para atividades de acesso por cordas realizada no interior de espaços confinados, a responsabilidade do resgate em suspensão deve ser de um supervisor N3, sendo que este supervisor poderá fazer parte da equipe de resgate do serviço, conforme indicado na PET. | I9: Fernando Rodrigues- CMQ6 | J9: 17/2/2025
A10: 54547 | B10: 1- Os vasilhames contendo resíduos de tintas ou solventes são armazenados em local protegido, ventilado e sinalizado? 2 - Os resíduos de tintas ou solventes são tratados, dispostos ou retirados dos limites do estabelecimento em conformidade com a legislação ambiental? | C10: NR-34 | D10: CONDIÇÕES E MEIO AMBIENTE DE TRABALHO NA INDÚSTRIA DA CONSTRUÇÃO,REPARAÇÃO E DESMONTE NAVAL. | E10: Item 34.9.8 e 34.9.9 | F10: ATIVIDADES OFFSHORE - PINTURA | G10: Conforme | H10: Atendido pelo padrão PE-1PBR-00234, em anexo fotos para evidenciar. | I10: - FLVR | J10: 18/2/2025
A11: 54597 | B11: O piso de trabalho possui forração completa, antiderrapante, nivelado e fixado de modo seguro e resistente, permanecendo desimpedido? | C11: NR-34 | D11: CONDIÇÕES E MEIO AMBIENTE DE TRABALHO NA INDÚSTRIA DA CONSTRUÇÃO,REPARAÇÃO E DESMONTE NAVAL. | E11: Item 34.11.16 | F11: ATIVIDADES OFFSHORE - AMBIENTE NAVAL | G11: Conforme | H11: Sim,o piso de trabalho possui forração completa, antiderrapante, nivelado e fixado de modo seguro e resistente, permanecendo desimpedido. | I11: - FLVR | J11: 7/2/2025
A12: 54602 | B12: A plataforma do andaime é protegida em todo o seu perímetro, exceto na face de trabalho, com guarda-corpo rígido, fixo e formado por dois tubos metálicos, colocados horizontalmente a distância mínima do tablado de cinquenta centímetros e um metro e rodapés, junto ao piso, com altura mínima de quinze centímetros? | C12: NR-34 | D12: CONDIÇÕES E MEIO AMBIENTE DE TRABALHO NA INDÚSTRIA DA CONSTRUÇÃO,REPARAÇÃO E DESMONTE NAVAL. | E12: Item 34.11.21 | F12: ATIVIDADES OFFSHORE - AMBIENTE NAVAL | G12: Conforme | H12: Na montagem do andaime, o piso é nivelado, sem aberturas e as pranchas fixadas nas suas extremidades.As pranchas não tem mais do que 20 cm de trecho em balanço na área de trabalho.Os andaimes com pisos situados a mais de 1 m de altura são providos de escadas ou rampas, sendo proibido o uso de braçadeiras como degraus.São instalados rodapés e guarda-corpo duplo em todo o perímetro do andaime, com exceção do trecho onde será realizado o trabalho. | I12: - FLVR | J12: 7/2/2025
A13: 54605 | B13: A área é isolada durante os serviços de montagem, desmontagem ou manutenção de andaimes, permitindo-se o acesso somente à equipe envolvida nas atividades? | C13: NR-34 | D13: CONDIÇÕES E MEIO AMBIENTE DE TRABALHO NA INDÚSTRIA DA CONSTRUÇÃO,REPARAÇÃO E DESMONTE NAVAL. | E13: Item 34.11.28 | F13: ATIVIDADES OFFSHORE - AMBIENTE NAVAL | G13: Conforme | H13: A força de trabalho segue o determinado no padrão PE-1PBR 00220. ITEM 3.8.1. Toda montagem e desmontagem de andaime deve ser precedida de autorização e planejamento, conforme PE-1PBR-00210._x000D_ 3.8.1.1. Após verificar no local se todas as recomendações foram atendidas, através do preenchimento da lista de verificação de pré-montagem/desmontagem (Anexo A), compete ao operador da área rubricar na PT constituindo este ato a efetiva autorização para o início da montagem/desmontagem._x000D_ Nota: Esta LV deve ser preenchida e assinada pelo operador da área em conjunto com o requisitante ou executante._x000D_ 3.8.1.2. As listas de verificação devem ser anexadas à PT. | I13: - FLVR | J13: 7/2/2025
... A146: 106843 | B146: A Ficha de Dados de Segurança - FDS fornece uma descrição clara dos dados usados para identificar os perigos do produto e com as informações sobre a substância ou mistura conforme descrito no item 7.3? | C146: ABNT NBR 14725:2023 Versão Corrigida 2:2025 | D146: Produtos Químicos - Informações sobre segurança , saúde e meio ambiente - Aspectos Gerais do Sistema Globalmente Harmonizado (GHS), classificação, FDS e rotulagem de produtos químicos. | E146: Item 7.3 | F146: PRODUTOS QUÍMICOS - Utilizar PRODUTOS QUÍMICOS em geral (obrigações gerais) | G146: Conforme | H146: Sim. Link da evidência em Produtos Químico BUZ/ENGP/PMF Larissa Grayce- FIUX | I146: Larissa Valois-FIUX | J146: 18/7/2025
A147: 107148 | B147: O armazenamento de produtos químicos perigosos embalados (fracionados), as atividades de armazenamento e de movimentação dentro dos armazéns e o armazenamento temporário de produtos químicos perigosos são realizados de acordo com o item 4 desta ABNT? | C147: ABNT NBR 17160:2024 | D147: Armazenamento seguro de produtos químicos. | E147: Item 1 | F147: PRODUTOS QUÍMICOS - Utilizar PRODUTOS QUÍMICOS em geral (obrigações gerais) | G147: Não Respondida
A148: 107151 | B148: No armazenamento conjunto de produtos químicos, são avaliados os requisitos de incompatibilidades química conforme seção 9 e informações descritas nas fichas com dados de segurança dos produtos? | C148: ABNT NBR 17160:2024 | D148: Armazenamento seguro de produtos químicos. | E148: Item 6.1.4 | F148: PRODUTOS QUÍMICOS - Utilizar PRODUTOS QUÍMICOS em geral (obrigações gerais) | G148: Conforme | H148: Atende conforme padrão PE-3BUZ-00382 que está em implantação. Anexo A_x000D_ Fabio Mota- DXV9 | I148: Larissa Valois-FIUX | J148: 22/7/2025
A149: 107202 | B149: O empregador adota as medidas organizacionais para assegurar que apenas as pessoas autorizadas tenham acesso ao armazém devidamente nomeadas e instruídas em intervalos regulares? NOTA: A proibição deve ser indicada de forma clara e permanente, por meio de sinalização adequada. | C149: ABNT NBR 17160:2024 | D149: Armazenamento seguro de produtos químicos. | E149: Item 7.3 | F149: PRODUTOS QUÍMICOS - Utilizar PRODUTOS QUÍMICOS em geral (obrigações gerais) | G149: Conforme | H149: Sim, a empresa adota padrões de segurança e operacionais, que asseguram que apenas as pessoas autorizadas tenham acesso ao armazém devidamente nomeadas e instruídas em intervalos regulares, conforme PE-1PBR-00227 - MS - TRABALHOS COM PRODUTOS PERIGOSOS_x000D_ Fabio Mota- DXV9 | I149: Larissa Valois-FIUX | J149: 24/7/2025
A150: 107211 | B150: A certificação da qualificação de supervisor de proteção radiológica é renovável a cada cinco anos, sendo solicitado sua renovação em até 1 ano após a expiração da sua validade? | C150: RESOLUÇÃO CNEN Nº 340, DE 17 DE ABRIL DE 2025 | D150: Aprova a Norma CNEN NN 7.01 - Requisitos para Certificação da Qualificação de Supervisores de Proteção Radiológica. | E150: Art. 18 e Art. 19 | F150: RADIOPROTEÇÃO - Executar e/ou fiscalizar atividades com EQUIPAMENTOS RADIOATIVOS | G150: Conforme | H150: Sim, conforme definido pelo CNEN, as certificações são renovadas periodicamente - Fábio Mota - DXV9 | I150: FABIO MOTA DXV9 | J150: 22/7/2025
A151: 107228 | B151: O compartimento de armazenamento interno dos combustíveis e inflamáveis possui as especificações descritas no item 37.21.4, como por exemplo:ventilação e exaustão eficazes; sistema de tratamento ou eliminação segura dos gases tóxicos ou inflamáveis; vias e portas de acesso sinalizadas de forma legível e visível com os dizeres "INFLAMÁVEL"e "NÃO FUME"; e conjunto adequado para a contenção de vazamentos? | C151: NR-37 | D151: SEGURANÇA E SAÚDE EM PLATAFORMAS DE PETRÓLEO. | E151: Item 37.21.4 | F151: ATIVIDADES OFFSHORE - LÍQUIDOS COMBUSTÍVEIS E INFLAMÁVEIS | G151: Conforme | H151: "Sim, conforme Padrão PE-3BUZ-00382 - Gestão de Produtos Químicos em BUZ._x000D_ "_x000D_ Larissa Grayce- FIUX | I151: Larissa Valois-FIUX | J151: 24/7/2025
A152: 51431 | B152: Foi elaborado, implementado e documentado procedimentos e métodos para monitorar e medir regularmente as características principais das operações e atividades que possam causar acidentes, incluindo o registro das informações, o método de acompanhamento do desempenho, os controles operacionais pertinentes, a conformidade com as metas e objetivos de segurança operacional e a periodicidade de medição e controle? NOTA: É obrigatório a designação de um responsável pelo acompanhamento de cada Indicador de Desempenho. | C152: RESOLUÇÃO ANP Nº 41, DE 09 DE OUTUBRO DE 2015 | D152: Aprova o Regulamento Técnico do Sistema de Gerenciamento de Segurança Operacional de Sistemas Submarinos - SGSS. | E152: Anexo Item 11.3.1 e 11.3.1.1 | F152: SEGURANÇA OPERACIONAL - Sistemas Submarinos | G152: Conforme | H152: DI-1PBR-00125 - DIRETRIZES PARA O GERENCIAMENTO DA INTEGRIDADE DE SISTEMAS SUBMARINOS NA PETROBRAS Sistema: Portal de Gestão Sandra Nery- LNGH | I152: Walcy Borges- SESM | J152: 30/5/2025
A153: 51591 | B153: O Plano de Emergência é reavaliado sempre que uma análise de risco assim o indicar; quando a avaliação do desempenho do Plano de Emergência, decorrente do seu acionamento por incidente ou exercício simulado, recomendar; sempre que a instalação sofrer modificações físicas, operacionais ou organizacionais que afetem seus procedimentos ou a sua capacidade de resposta; ou em outras situações a critério da ANP? | C153: RESOLUÇÃO ANP Nº 43, DE 06 DE DEZEMBRO DE 2007 | D153: Institui o Regime de Segurança Operacional para as Instalações de Perfuração e Produção de Petróleo e Gás Natural. | E153: Prática de Gestão 14 - Item 14.7 | F153: SEGURANÇA OPERACIONAL - Atividade de Operação e Produção Marítima | G153: Conforme | H153: Sim. Conforme os padrões PE-3BUZ-00100 - PLANO DE RESPOSTA A EMERGÊNCIAS NAS PLATAFORMAS, PE-3BUZ-00222 - PEI - PLANO DE EMERGÊNCIA INDIVIDUAL DA PLATAFORMA P-77, PE-3BUZ-00220 - PEI - PLANO DE EMERGÊNCIA INDIVIDUAL DA PLATAFORMA P-75, PE-3BUZ-00219 - PEI - PLANO DE EMERGÊNCIA INDIVIDUAL DA PLATAFORMA P-74 e PE-3BUZ-00221 - PEI - PLANO DE EMERGÊNCIA INDIVIDUAL DA PLATAFORMA P-76. _x000D_ Fabio Mota- DXV9 | I153: Walcy Borges- SESM | J153: 23/5/2025
A154: 51599 | B154: Operador do Contrato designa a equipe responsável e inicia os trabalhos de investigação tão rapidamente quanto possível, não excedendo 48 horas após o encerramento do incidente, a fim de preservar as evidências, salvo por motivo de força maior devidamente justificado e documentado? | C154: RESOLUÇÃO ANP Nº 46, DE 01 DE NOVEMBRO DE 2016 | D154: Aprova o Regime de Segurança Operacional para Integridade de Poços de Petróleo e Gás Natural, que estabelece os requisitos de segurança operacional e de preservação do meio ambiente para perfuração, completação, avaliação, intervenção, produção e abandono de poços de petróleo e gás natural. | E154: Item 9.4.1 | F154: SEGURANÇA OPERACIONAL - Integridade de Poços | G154: Conforme | H154: Sim, conforme PP-1PBR-00150 GERIR ANOMALIAS DE SMS Sistema: SAP SMS Sandra Nery- LNGH | I154: Walcy Borges- SESM | J154: 30/5/2025
A155: 51613 | B155: O Operador da Instalação elaborou procedimento para condução da investigação de incidentes , incluindo dimensionamento e composição da equipe de investigação; e critérios para condução da investigação no local do incidente, observando a necessidade de preservar as evidências físicas, a programação e execução de entrevistas e a necessidade de coletar e identificar os documentos, dados e registros apropriados? | C155: RESOLUÇÃO ANP Nº 43, DE 06 DE DEZEMBRO DE 2007 | D155: Institui o Regime de Segurança Operacional para as Instalações de Perfuração e Produção de Petróleo e Gás Natural. | E155: Prática de Gestão 9 - Item 9.2 | F155: SEGURANÇA OPERACIONAL - Atividade de Operação e Produção Marítima | G155: Conforme | H155: Sim, conforme o padrão PP-1PBR-00150 - GERIR ANOMALIAS DE SMS disponível no portal de gestão. Fabio Mota-DXV9 | I155: Juliana Cabral-CYT6 | J155: 23/5/2025
A156: 51631 | B156: Foi elaborado procedimentos de controle abordando a identificação de novos perigos introduzidos pelas Operações Simultâneas e verificação da existência de medidas de prevenção e/ou mitigação adequadas para estes perigos; definição das responsabilidades, de modo a assegurar uma adequada coordenação entre todas as organizações envolvidas, incluindo resposta à emergência? | C156: RESOLUÇÃO ANP Nº 43, DE 06 DE DEZEMBRO DE 2007 | D156: Institui o Regime de Segurança Operacional para as Instalações de Perfuração e Produção de Petróleo e Gás Natural. | E156: Prática de Gestão 15 - Item 15.4 | F156: SEGURANÇA OPERACIONAL - Atividade de Operação e Produção Marítima | G156: Conforme | H156: Sim, conforme PE-1PBR-00211 - MS- TRABALHOS E OPERAÇÕES SIMULTÂNEAS.Sistema Portal de Gestão.Sandra Nery | I156: Walcy Borges- SESM | J156: 9/6/2025
A157: 51776 | B157: A adaptação do EPI (Equipamento de Proteção Individual) para uso por pessoa com deficiência feita pelo fabricante ou importador detentor do CA não invalida o certificado já emitido, sendo desnecessária a emissão de novo CA. | C157: NR-06 | D157: EQUIPAMENTOS DE PROTEÇÃO INDIVIDUAL - EPI. | E157: Item 6.9.5 | F157: EPI - Utilizar Equipamento de Proteção Individual e/ou uniformes | G157: Ciente | H157: Não se Aplica | I157: - FLVR | J157: 14/4/2025
A158: 52071 | B158: A unidade providenciou para todos os trabalhadores informações sobre: utilização dos equipamentos de combate ao incêndio; procedimentos de resposta aos cenários de emergências e para evacuação dos locais de trabalho com segurança; e dispositivos de alarme existentes? | C158: NR-23 | D158: PROTEÇÃO CONTRA INCÊNDIO. | E158: Item 23.3.2 | F158: INCÊNDIO E EXPLOSÃO / PREVENÇÃO - Obrigações gerais relativas à combate e prevenção a INCÊNDIOS | G158: Conforme | H158: Sim, Através de treinamento básico da NR-37, briefings de segurança para toda a força de trabalho e CBSP. Em treinamentos específicos para atuação na EOR. Sistema: SIRH Walcy Borges- SESM | I158: Walcy Borges- SESM | J158: 8/5/2025
A159: 52663 | B159: O Serviço de Radioproteção da empresa possui instalações para: a) acomodação do pessoal; b) higiene pessoal; c) troca e guarda de vestimentas; d) descontaminação externa de pessoas; e) aferição, ajuste, guarda e descontaminação de equipamentos; f) elaboração e arquivamento de documentos e registros; e g) pronta comunicação entre pessoas apropriadas da Instalação e com as pessoas e instituições externas relevantes para o caso de notificações e tomada de decisões em emergências? | C159: RESOLUÇÃO CNEN Nº 10, DE 19 DE JULHO DE 1988 | D159: Estabelece os requisitos à implantação e ao funcionamento de SERVIÇOS DE RADIOPROTEÇÃO. | E159: Item 4.3 | F159: RADIOPROTEÇÃO - Executar e/ou fiscalizar atividades com EQUIPAMENTOS RADIOATIVOS | G159: Conforme | H159: Para as Instalações Radiativas. conforme matrícula - Autoriização para Operação, emitida pela CNEN. | I159: FABIO MOTA DXV9 | J159: 3/6/2025
... A329: 107137 | B329: O empregador instrui os trabalhadores adequadamente para o manuseio e operação dos produtos químicos perigosos? | C329: ABNT NBR 17160:2024 | D329: Armazenamento seguro de produtos químicos. | E329: Item 6.3.4.1 | F329: PRODUTOS QUÍMICOS - Utilizar PRODUTOS QUÍMICOS em geral (obrigações gerais) | G329: Conforme | H329: Atendida através dos treinamentos do sistema SIRH e para as contratadas, através da fiscalização de contrato. _x000D_ Fabio Mota- DXv9 | I329: Larissa Valois-FIUX | J329: 22/7/2025
A330: 107149 | B330: Foi realizada análise de risco das atividades de armazenamento seguro de produtos químicos que contemplem aspectos descritos nos itens 5.1.1 ao 5.2.7? | C330: ABNT NBR 17160:2024 | D330: Armazenamento seguro de produtos químicos. | E330: Item 5 | F330: PRODUTOS QUÍMICOS - Utilizar PRODUTOS QUÍMICOS em geral (obrigações gerais) | G330: Não Respondida
A331: 107152 | B331: É mantido pelos responsáveis do armazém um inventário de produtos perigosos com os nomes dos produtos perigosos armazenados, a classificação de produtos perigosos ou as informações sobre as propriedades perigosas; a quantidade de produtos estocados e o setor do armazém? | C331: ABNT NBR 17160:2024 | D331: Armazenamento seguro de produtos químicos. | E331: Item 6.1.5 | F331: PRODUTOS QUÍMICOS - Utilizar PRODUTOS QUÍMICOS em geral (obrigações gerais) | G331: Conforme | H331: Sim, cada unidade possui o seu inventário e a Petrobras também possui o DIGIPQ (Demanda Inteligente & Gestão Integrada de Produtos Químicos), link: https://digipq.petrobras.com.br/#/Transacoes _x000D_ Larissa Grayce- FIUX | I331: Larissa Valois-FIUX | J331: 18/7/2025
A332: 107154 | B332: O empregador designa trabalhadores previamente instruídos e que estejam cientes dos perigos envolvidos e das medidas de proteção necessárias, com atividades relacionadas ao armazenamento de produtos perigosos? | C332: ABNT NBR 17160:2024 | D332: Armazenamento seguro de produtos químicos. | E332: Item 6.3.4.2 | F332: PRODUTOS QUÍMICOS - Utilizar PRODUTOS QUÍMICOS em geral (obrigações gerais) | G332: Conforme | H332: Os Técnicos de Segurança (TS) possuem, em sua formação profissional, disciplinas específicas sobre armazenamento e manuseio de produtos químicos, além de normas técnicas aplicáveis. A empresa mantém padrões internos de armazenamento de produtos químicos, cuja leitura é obrigatória para todos os envolvidos._x000D_ Adicionalmente, os riscos associados a produtos químicos são abordados:_x000D_ Nos briefings diários e comunicados internos;_x000D_ Nos cursos normativos offshore, que contemplam disciplinas sobre produtos químicos e suas medidas de controle._x000D_ Por fim, todas as atividades que envolvem manuseio de produtos químicos são previamente avaliadas:_x000D_ Serviços rotineiros: seguem Procedimentos Específicos (PE) com diretrizes claras de segurança;_x000D_ Serviços não rotineiros: são precedidos de Análise de Risco (APN2), com orientações detalhadas incluídas na Permissão para Trabalho em Risco Específico (PTRE). Fabio Mota- DXV9 | I332: Larissa Valois-FIUX | J332: 24/7/2025
A333: 107199 | B333: São fornecidos pelo empregador equipamentos de proteção individual e roupas de proteção quando da realização das atividades com produtos perigosos? NOTA: O empregador deve lavar e, se necessário, substituir e descartas as roupas de proteção. | C333: ABNT NBR 17160:2024 | D333: Armazenamento seguro de produtos químicos. | E333: Item 6.3.6 | F333: PRODUTOS QUÍMICOS - Utilizar PRODUTOS QUÍMICOS em geral (obrigações gerais) | G333: Conforme | H333: O registro de fornecimento, pelo empregador, dos equipamentos de proteção individual é armazenado na base de dados do Sistema SIS, Francisco Batalha- URFV | I333: Francisco Batalha- URFV | J333: 18/7/2025
A334: 107215 | B334: Foi elaborado relatório técnico de exposições ocupacionais ao calor, abordando no mínimo, os aspectos apresentados no item 11, de forma a possibilitar a compreensão sobre o trabalho desenvolvido e documentar os aspectos considerados no estudo? | C334: NORMA DE HIGIENE OCUPACIONAL - NHO 06, DE 31 DE MARÇO DE 2025 | D334: Avaliação da Exposição Ocupacional ao Calor - 3ª edição. | E334: Item 11 | F334: RISCOS AMBIENTAIS - Exposição ocupacional a agentes físicos - CALOR | G334: Conforme | H334: Este item será atendido nas atividades de rotina em sua forma integral na próxima Campanha de Higiene Ocupacional de Búzios, com previsão de início em novembro/2025, abrangendo as introduções incluídas na terceira versão da NHO 06 da FUNDACENTRO._x000D_ Leonardo Medina- CSQE | I334: LEONARDO MEDINA - CSQE | J334: 22/7/2025
A335: 51443 | B335: Os critérios para a formação da equipe de investigadores consideram a complexidade e o potencial de dano do Incidente; a inclusão de pelo menos um membro da equipe com amplo conhecimento da técnica de investigação a ser utilizada; a necessidade de inclusão de um membro da equipe com conhecimento da tarefa ou ambiente de trabalho relacionado ao Incidente; a necessidade de especialista técnico; e caso o Incidente envolva uma empresa contratada, a necessidade da inclusão de um empregado dessa empresa? | C335: RESOLUÇÃO ANP Nº 41, DE 09 DE OUTUBRO DE 2015 | D335: Aprova o Regulamento Técnico do Sistema de Gerenciamento de Segurança Operacional de Sistemas Submarinos - SGSS. | E335: Anexo Item 14.3.2 | F335: SEGURANÇA OPERACIONAL - Sistemas Submarinos | G335: Conforme | H335: "PP-1PBR-00150 - GERIR ANOMALIAS DE SMS._x000D_ _x000D_ Sistema: SAP-SMS"_x000D_ Sandra Nery- LNGH | I335: Walcy Borges- SESM | J335: 30/5/2025
